Workbook

Sheet Start Here
A1: A household financial strategy simulator for Australians with property, super and mortgage complexity who want to test retirement and wealth decisions before speaking to an adviser. [Best-in-Class] Australian Financial Planning Workbook
A3: Single consolidated workbook: detailed budget, multi-property portfolio (PPOR + 3 IPs), scenario toggles, deterministic projections, Monte Carlo probability fan, and an executive dashboard with charts. All figures are dummy demo values—replace locally with your real numbers.
A5: How to use:
A6: 1) Use 'Control Centre' to set Active Scenario, Profile inputs and AU rules.
A7: 2) Enter your detailed monthly budget on 'Budget'.
A8: 3) Enter balances and cashflows on 'Assets & Liabilities', 'Superannuation (Inputs)', 'Properties'.
A9: 4) Review 'Projections' + 'Monte Carlo', then the 'Dashboard'.

Sheet Control Centre
A1: Control Centre | Household Profile + Scenarios + AU Rules
A3: Primary input sheet for the workbook. Update household profile, scenario assumptions and AU rule settings here. Legacy sheets remain as mirrors so existing model links keep working.
A5: Household Profile | F5: Scenario Matrix | P5: Active Scenario
A6: Item | B6: Value | C6: Notes | F6: Scenario | G6: Retire Age | H6: Return Mean | I6: Volatility | J6: Inflation | K6: Property Growth | L6: Rent Yield | M6: Rental Income Growth | N6: Partner Retire Age | P6: Active Scenario | Q6: Base
A7: Your Age | B7: 48 | F7: Base | G7: 60 | H7: 0.065 | I7: 0.11 | J7: 0.025 | K7: 0.045 | L7: 0.050164706 | M7: 0.03 | N7: 53 | P7: Retire Age | Q7: =IF($Q$6="Base",$G$7,IF($Q$6="Conservative",$G$8,$G$9)) -> 60
A8: Partner Age | B8: 41 | F8: Conservative | G8: 62 | H8: 0.055 | I8: 0.09 | J8: 0.03 | K8: 0.035 | L8: 0.038 | M8: 0.025 | N8: 55 | P8: Return Mean | Q8: =IF($Q$6="Base",$H$7,IF($Q$6="Conservative",$H$8,$H$9)) -> 0.065
A9: Life Expectancy | B9: 90 | F9: Aggressive | G9: 58 | H9: 0.075 | I9: 0.14 | J9: 0.02 | K9: 0.055 | L9: 0.042 | M9: 0.035 | N9: 51 | P9: Volatility | Q9: =IF($Q$6="Base",$I$7,IF($Q$6="Conservative",$I$8,$I$9)) -> 0.11
A10: Your Gross income (p.a.) | B10: 180000 | C10: TBC with a job | P10: Inflation | Q10: =IF($Q$6="Base",$J$7,IF($Q$6="Conservative",$J$8,$J$9)) -> 0.025
A11: Spouse Gross income (p.a.) | B11: 166000 | P11: Property Growth | Q11: =IF($Q$6="Base",$K$7,IF($Q$6="Conservative",$K$8,$K$9)) -> 0.045
A12: Spouse Gross income (p.a.) Y1 (2027) | B12: 172000 | F12: Rental Growth Rationale | P12: Rent Yield | Q12: =IF($Q$6="Base",$L$7,IF($Q$6="Conservative",$L$8,$L$9)) -> 0.050164706
A13: Target retirement spending (after tax, p.a.) | B13: 110000 | C13: Demo | F13: Scenario | G13: Rental Growth | H13: Rationale | P13: Rental Income Growth | Q13: =IF($Q$6="Base",$M$7,IF($Q$6="Conservative",$M$8,$M$9)) -> 0.03
A14: Kids | B14: 2 | F14: Conservative | G14: 0.025 | H14: Roughly long-run CPI | P14: Partner Retire Age | Q14: =IF($Q$6="Base",$N$7,IF($Q$6="Conservative",$N$8,$N$9)) -> 53
A15: Other assets (non-super, non-property) | B15: 50000 | C15: Demo | F15: Base | G15: 0.03 | H15: CPI + modest real growth
A16: Partner Years Younger | B16: 7 | F16: Aggressive | G16: 0.035 | H16: Tight rental market, wage pressure
A17: Your Retire Age (scenario-driven) | B17: already exists
A18: Partner Retire Age – Base | B18: 55 | F18: Inflation Rationale
A19: Partner Retire Age – Conservative | B19: 60 | F19: Scenario | G19: Inflation | H19: Why
A20: Partner Retire Age – Aggressive | B20: 53 | F20: Scenario | G20: Inflation | H20: Why
A21: You Retirement Date Offset (FY) | B21: 0 | F21: Conservative | G21: 0.03 | H21: Higher cost pressure, stagflation risk | K21: Task (including Persona and Format), Context, References, Evaluate, and Iterate.
A22: Spouse Retirement Date Offset (FY) | B22: 0 | F22: Base | G22: 0.025 | H22: RBA midpoint, long-run normal
A24: AU Rules
A25: Rule | B25: Value | C25: Notes
A26: Super concessional cap | B26: 27500 | C26: Update for current FY
A27: Super tax rate (contrib/earnings) | B27: 0.15 | C27: Typical concessional tax
A28: Preservation age | B28: 60 | C28: Depends on DOB; common for many cohorts
A29: Medicare levy (base) | B29: 0.02 | C29: Approx
A30: Safe withdrawal rate | B30: 0.04 | C30: Rule-of-thumb baseline

Sheet Profile
A1: Household Profile (Inputs)
A3: Legacy mirror sheet. Primary edits now happen on 'Control Centre'. This sheet remains to preserve workbook links.
A5: Item | B5: Value | C5: Notes | E5: Derived
A6: Your Age | B6: ='Control Centre'!$B$7 -> 48 | E6: Active Retire Age | F6: =Scenarios!K7 -> 60
A7: Partner Age | B7: ='Control Centre'!$B$8 -> 41 | E7: Years to Retire | F7: =F6-INDEX(B:B,MATCH("Your Age",A:A,0)) -> 12
A8: Life Expectancy | B8: ='Control Centre'!$B$9 -> 90
A9: Your Gross income (p.a.) | B9: ='Control Centre'!$B$10 -> 180000 | C9: TBC with a job | E9: Active Spouse Retire Age | F9: =Scenarios!K15 -> 53
A10: Spouse Gross income (p.a.) | B10: ='Control Centre'!$B$11 -> 166000
A11: Spouse Gross income (p.a.) Y1 (2027) | B11: ='Control Centre'!$B$12 -> 172000
A12: Target retirement spending (after tax, p.a.) | B12: ='Control Centre'!$B$13 -> 110000 | C12: Demo
A13: Kids | B13: ='Control Centre'!$B$14 -> 2
A14: Other assets (non-super, non-property) | B14: ='Control Centre'!$B$15 -> 50000 | C14: Demo
A15: Partner Years Younger | B15: ='Control Centre'!$B$16 -> 7
A16: Your Retire Age (scenario-driven) | B16: ='Control Centre'!$B$17 -> already exists
A17: Partner Retire Age – Base | B17: ='Control Centre'!$B$18 -> 55
A18: Partner Retire Age – Conservative | B18: ='Control Centre'!$B$19 -> 60
A19: Partner Retire Age – Aggressive | B19: ='Control Centre'!$B$20 -> 53
A20: You Retirement Date Offset (FY) | B20: ='Control Centre'!$B$21 -> 0
A21: Spouse Retirement Date Offset (FY) | B21: ='Control Centre'!$B$22 -> 0

Sheet AU Rules
A1: Australian Super & Tax Scaffold
A3: Legacy mirror sheet. Primary edits now happen on 'Control Centre'. This sheet remains to preserve workbook links.
A5: Rule | B5: Value | C5: Notes
A6: ='Control Centre'!$A$26 -> Super concessional cap | B6: ='Control Centre'!$B$26 -> 27500 | C6: ='Control Centre'!$C$26 -> Update for current FY
A7: ='Control Centre'!$A$27 -> Super tax rate (contrib/earnings) | B7: ='Control Centre'!$B$27 -> 0.15 | C7: ='Control Centre'!$C$27 -> Typical concessional tax
A8: ='Control Centre'!$A$28 -> Preservation age | B8: ='Control Centre'!$B$28 -> 60 | C8: ='Control Centre'!$C$28 -> Depends on DOB; common for many cohorts
A9: ='Control Centre'!$A$29 -> Medicare levy (base) | B9: ='Control Centre'!$B$29 -> 0.02 | C9: ='Control Centre'!$C$29 -> Approx
A10: ='Control Centre'!$A$30 -> Safe withdrawal rate | B10: ='Control Centre'!$B$30 -> 0.04 | C10: ='Control Centre'!$C$30 -> Rule-of-thumb baseline

Sheet Scenarios
A1: Scenario Control
A3: Legacy mirror sheet. Primary edits now happen on 'Control Centre'. This sheet remains to preserve workbook links.
J4: Active Scenario
J5: ='Control Centre'!$Q$6 -> Base
A6: Scenario | B6: Retire Age | C6: Return Mean | D6: Volatility | E6: Inflation | F6: Property Growth | G6: Rent Yield | H6: Rental Income Growth | I6: Partner Retire Age | J6: Notes
A7: ='Control Centre'!$F$7 -> Base | B7: ='Control Centre'!$G$7 -> 60 | C7: ='Control Centre'!$H$7 -> 0.065 | D7: ='Control Centre'!$I$7 -> 0.11 | E7: ='Control Centre'!$J$7 -> 0.025 | F7: ='Control Centre'!$K$7 -> 0.045 | G7: ='Control Centre'!$L$7 -> 0.050164706 | H7: ='Control Centre'!$M$7 -> 0.03 | I7: ='Control Centre'!$N$7 -> 53 | J7: Active Retire Age | K7: ='Control Centre'!$Q$7 -> 60
A8: ='Control Centre'!$F$8 -> Conservative | B8: ='Control Centre'!$G$8 -> 62 | C8: ='Control Centre'!$H$8 -> 0.055 | D8: ='Control Centre'!$I$8 -> 0.09 | E8: ='Control Centre'!$J$8 -> 0.03 | F8: ='Control Centre'!$K$8 -> 0.035 | G8: ='Control Centre'!$L$8 -> 0.038 | H8: ='Control Centre'!$M$8 -> 0.025 | I8: ='Control Centre'!$N$8 -> 55 | J8: Active Return Mean | K8: ='Control Centre'!$Q$8 -> 0.065
A9: ='Control Centre'!$F$9 -> Aggressive | B9: ='Control Centre'!$G$9 -> 58 | C9: ='Control Centre'!$H$9 -> 0.075 | D9: ='Control Centre'!$I$9 -> 0.14 | E9: ='Control Centre'!$J$9 -> 0.02 | F9: ='Control Centre'!$K$9 -> 0.055 | G9: ='Control Centre'!$L$9 -> 0.042 | H9: ='Control Centre'!$M$9 -> 0.035 | I9: ='Control Centre'!$N$9 -> 51 | J9: Active Volatility | K9: ='Control Centre'!$Q$9 -> 0.11
J10: Active Inflation | K10: ='Control Centre'!$Q$10 -> 0.025
J11: Property Growth | K11: ='Control Centre'!$Q$11 -> 0.045
J12: Rent Yield | K12: ='Control Centre'!$Q$12 -> 0.050164706
A13: Rental Income Growth | J13: Active Rental Income Growth | K13: ='Control Centre'!$Q$13 -> 0.03
A14: Scenario | B14: Rental Growth | C14: Rationale
A15: ='Control Centre'!$F$14 -> Conservative | B15: ='Control Centre'!$G$14 -> 0.025 | C15: ='Control Centre'!$H$14 -> Roughly long-run CPI | J15: Active Spouse Retire Age | K15: ='Control Centre'!$Q$14 -> 53
A16: ='Control Centre'!$F$15 -> Base | B16: ='Control Centre'!$G$15 -> 0.03 | C16: ='Control Centre'!$H$15 -> CPI + modest real growth
A17: ='Control Centre'!$F$16 -> Aggressive | B17: ='Control Centre'!$G$16 -> 0.035 | C17: ='Control Centre'!$H$16 -> Tight rental market, wage pressure
A20: Sanity check vs your existing assumptions
A22: You currently have:
A23: Property Growth: 4.5%
A24: Inflation: (likely ~2.5–3.0%)
A25: That gives:
A26: Capital growth > rental growth ✔
A27: Rental growth ≥ inflation ✔
A28: Yield slowly compresses over time ✔ (realistic)
A29: This passes an adviser / bank sniff test immediately.
A32: Recommended Inflation Assumptions
A34: ='Control Centre'!$F$20 -> Scenario | B34: ='Control Centre'!$G$20 -> Inflation | C34: ='Control Centre'!$H$20 -> Why
A35: ='Control Centre'!$F$21 -> Conservative | B35: ='Control Centre'!$G$21 -> 0.03 | C35: ='Control Centre'!$H$21 -> Higher cost pressure, stagflation risk
A36: ='Control Centre'!$F$22 -> Base | B36: ='Control Centre'!$G$22 -> 0.025 | C36: ='Control Centre'!$H$22 -> RBA midpoint, long-run normal
A37: Aggressive | B37: 0.02 | C37: Productivity gains, benign inflation

Sheet Projections
B1: Projections (Deterministic, Annual)
P2: =P7-F7-E7 -> 53451.23
B3: Projects total net worth and post-retirement spend-down.
A5: Year | B5: Year | C5: Age You | D5: Spouse Age | E5: Earned Income You | F5: Earned Income Spouse (Base) | G5: Super Contribution – You | H5: Super Tax - You | I5: Super Contribution - Spouse | J5: Super Tax - Spouse | K5: Super Balance - You | L5: Super Balance - Spouse | M5: Total Super | N5: Tax You | O5: Tax Spouse | P5: Total Earned Income | Q5: Living Budget (Annual) | R5: Net Rental (After Tax) | S5: Net Household Cashflow (Pre-Retire) | T5: Annual Surplus (Pre-Retirement) | U5: Super | V5: Property Equity | W5: Other Assets | X5: Total Net Worth | Y5: Spend (post-retire) | Z5: After Spend
A6: =ROW()-ROW($A$6)+1 -> 1 | B6: 2026 | C6: =Profile!B6 -> 48 | D6: =Profile!B7 -> 41 | E6: =IF( $C6 < Scenarios!$K$7, _xlfn.XLOOKUP($B6,'Income Schedule'!$A$5:$A$60,'Income Schedule'!$B$5:$B$60,0), IF( $C6 = Scenarios!$K$7, _xlfn.XLOOKUP($B6,'Income Schedule'!$A$5:$A$60,'Income Schedule'!$B$5:$B$60,0) * (1-Profile!$B$20), 0 ) ) -> 45000 | F6: =IF( $C6 < (Scenarios!$K$15 + (Profile!$B$6-Profile!$B$7)), _xlfn.XLOOKUP($B6,'Income Schedule'!$A$5:$A$60,'Income Schedule'!$C$5:$C$60,0), IF( $C6 = (Scenarios!$K$15 + (Profile!$B$6-Profile!$B$7)), _xlfn.XLOOKUP($B6,'Income Schedule'!$A$5:$A$60,'Income Schedule'!$C$5:$C$60,0) * (1-Profile!$B$21), 0 ) ) -> 166000 | G6: =IF( $C6 < Scenarios!$K$7, IF('Superannuation (Inputs)'!$I$6="Fixed", 'Superannuation (Inputs)'!$C$6, 'Superannuation (Inputs)'!$J$6 ), IF( $C6 = Scenarios!$K$7, IF('Superannuation (Inputs)'!$I$6="Fixed", 'Superannuation (Inputs)'!$C$6*(1-Profile!$B$20), 'Superannuation (Inputs)'!$J$6 ), 0 ) ) -> 5400 | H6: =G6 * 'Superannuation (Inputs)'!$H$6 -> 810 | I6: =IF( $C6 < (Scenarios!$K$15 + (Profile!$B$6-Profile!$B$7)), IF('Superannuation (Inputs)'!$I$7="Fixed", 'Superannuation (Inputs)'!$C$7, 'Superannuation (Inputs)'!$J$7 ), IF( $C6 = (Scenarios!$K$15 + (Profile!$B$6-Profile!$B$7)), IF('Superannuation (Inputs)'!$I$7="Fixed", 'Superannuation (Inputs)'!$C$7*(1-Profile!$B$21), 'Superannuation (Inputs)'!$J$7 ), 0 ) ) -> 25564 | J6: =I6 * 'Superannuation (Inputs)'!$H$7 -> 3834.6 | K6: ='Superannuation (Inputs)'!$B$6 -> 636000 | L6: ='Superannuation (Inputs)'!$B$7 -> 452000 | M6: =K6+L6 -> 1088000 | N6: =(IF((E6 + 0.5*INDEX(Property_CF!$B$187:$AZ$187,1,$A6))<=18200,0, IF((E6 + 0.5*INDEX(Property_CF!$B$187:$AZ$187,1,$A6))<=45000,((E6 + 0.5*INDEX(Property_CF!$B$187:$AZ$187,1,$A6))-18200)*0.19, IF((E6 + 0.5*INDEX(Property_CF!$B$187:$AZ$187,1,$A6))<=120000,5092+((E6 + 0.5*INDEX(Property_CF!$B$187:$AZ$187,1,$A6))-45000)*0.325, IF((E6 + 0.5*INDEX(Property_CF!$B$187:$AZ$187,1,$A6))<=180000,29467+((E6 + 0.5*INDEX(Property_CF!$B$187:$AZ$187,1,$A6))-120000)*0.37, 51667+((E6 + 0.5*INDEX(Property_CF!$B$187:$AZ$187,1,$A6))-180000)*0.45)))))+((E6 + 0.5*INDEX(Property_CF!$B$187:$AZ$187,1,$A6)))*0.02 -> 5992 | O6: =(IF((F6 + 0.5*INDEX(Property_CF!$B$187:$AZ$187,1,$A6))<=18200,0, IF((F6 + 0.5*INDEX(Property_CF!$B$187:$AZ$187,1,$A6))<=45000,((F6 + 0.5*INDEX(Property_CF!$B$187:$AZ$187,1,$A6))-18200)*0.19, IF((F6 + 0.5*INDEX(Property_CF!$B$187:$AZ$187,1,$A6))<=120000,5092+((F6 + 0.5*INDEX(Property_CF!$B$187:$AZ$187,1,$A6))-45000)*0.325, IF((F6 + 0.5*INDEX(Property_CF!$B$187:$AZ$187,1,$A6))<=180000,29467+((F6 + 0.5*INDEX(Property_CF!$B$187:$AZ$187,1,$A6))-120000)*0.37, 51667+((F6 + 0.5*INDEX(Property_CF!$B$187:$AZ$187,1,$A6))-180000)*0.45)))))+((F6 + 0.5*INDEX(Property_CF!$B$187:$AZ$187,1,$A6)))*0.02 -> 49807 | P6: {=E6+F6+INDEX(Property_CF!$C$187:$AZ$187,1,$A6)} -> 258859.68 | Q6: =Budget!$P$6 -> 76477.3 | R6: =SUM('Rental Tax & Gearing'!$H$6:$H$8) -> -11228.788 | S6: =IF($C6 < Scenarios!$K$7, (P6 + R6 - Q6), 0 ) -> 171153.59 | T6: =IF($C6 < Scenarios!$K$7, P6 - Budget!$P$6, 0) -> 182382.38 | U6: ='Superannuation (Inputs)'!N6 -> 1088000 | V6: =Properties!M8 -> 1683071.9 | W6: =Profile!B14 + 'Assets & Liabilities'!G8 -> 353316.06 | X6: =SUM(U6:W6) -> 3124388 | Y6: =IF(C6>=Scenarios!$K$7, Profile!B9*(1+Scenarios!$K$10)^(C6-Scenarios!$K$7), 0) -> 0 | Z6: =X6-Y6 -> 3124388
A7: =ROW()-ROW($A$6)+1 -> 2 | B7: =B6+1 -> 2027 | C7: =C6+1 -> 49 | D7: =D6+1 -> 42 | E7: =IF( $C7 < Scenarios!$K$7, _xlfn.XLOOKUP($B7,'Income Schedule'!$A$5:$A$60,'Income Schedule'!$B$5:$B$60,0), IF( $C7 = Scenarios!$K$7, _xlfn.XLOOKUP($B7,'Income Schedule'!$A$5:$A$60,'Income Schedule'!$B$5:$B$60,0) * (1-Profile!$B$20), 0 ) ) -> 180000 | F7: =IF( $C7 < (Scenarios!$K$15 + (Profile!$B$6-Profile!$B$7)), _xlfn.XLOOKUP($B7,'Income Schedule'!$A$5:$A$60,'Income Schedule'!$C$5:$C$60,0), IF( $C7 = (Scenarios!$K$15 + (Profile!$B$6-Profile!$B$7)), _xlfn.XLOOKUP($B7,'Income Schedule'!$A$5:$A$60,'Income Schedule'!$C$5:$C$60,0) * (1-Profile!$B$21), 0 ) ) -> 172000 | G7: =IF( $C7 < Scenarios!$K$7, IF('Superannuation (Inputs)'!$I$6="Fixed", 'Superannuation (Inputs)'!$C$6, 'Superannuation (Inputs)'!$J$6 ), IF( $C7 = Scenarios!$K$7, IF('Superannuation (Inputs)'!$I$6="Fixed", 'Superannuation (Inputs)'!$C$6*(1-Profile!$B$20), 'Superannuation (Inputs)'!$J$6 ), 0 ) ) -> 5400 | H7: =G7 * 'Superannuation (Inputs)'!$H$6 -> 810 | I7: =IF( $C7 < (Scenarios!$K$15 + (Profile!$B$6-Profile!$B$7)), IF('Superannuation (Inputs)'!$I$7="Fixed", 'Superannuation (Inputs)'!$C$7, 'Superannuation (Inputs)'!$J$7 ), IF( $C7 = (Scenarios!$K$15 + (Profile!$B$6-Profile!$B$7)), IF('Superannuation (Inputs)'!$I$7="Fixed", 'Superannuation (Inputs)'!$C$7*(1-Profile!$B$21), 'Superannuation (Inputs)'!$J$7 ), 0 ) ) -> 25564 | J7: =I7 * 'Superannuation (Inputs)'!$H$7 -> 3834.6 | K7: =K6*(1+Scenarios!$K$8) + G7-H7 -> 681930 | L7: =L6*(1+Scenarios!$K$8) + H7-I7 -> 456626 | M7: =K7+L7 -> 1138556 | N7: =(IF((E7 + 0.5*INDEX(Property_CF!$B$187:$AZ$187,1,$A7))<=18200,0, IF((E7 + 0.5*INDEX(Property_CF!$B$187:$AZ$187,1,$A7))<=45000,((E7 + 0.5*INDEX(Property_CF!$B$187:$AZ$187,1,$A7))-18200)*0.19, IF((E7 + 0.5*INDEX(Property_CF!$B$187:$AZ$187,1,$A7))<=120000,5092+((E7 + 0.5*INDEX(Property_CF!$B$187:$AZ$187,1,$A7))-45000)*0.325, IF((E7 + 0.5*INDEX(Property_CF!$B$187:$AZ$187,1,$A7))<=180000,29467+((E7 + 0.5*INDEX(Property_CF!$B$187:$AZ$187,1,$A7))-120000)*0.37, 51667+((E7 + 0.5*INDEX(Property_CF!$B$187:$AZ$187,1,$A7))-180000)*0.45)))))+((E7 + 0.5*INDEX(Property_CF!$B$187:$AZ$187,1,$A7)))*0.02 -> 66514.024 | O7: =(IF((F7 + 0.5*INDEX(Property_CF!$B$187:$AZ$187,1,$A7))<=18200,0, IF((F7 + 0.5*INDEX(Property_CF!$B$187:$AZ$187,1,$A7))<=45000,((F7 + 0.5*INDEX(Property_CF!$B$187:$AZ$187,1,$A7))-18200)*0.19, IF((F7 + 0.5*INDEX(Property_CF!$B$187:$AZ$187,1,$A7))<=120000,5092+((F7 + 0.5*INDEX(Property_CF!$B$187:$AZ$187,1,$A7))-45000)*0.325, IF((F7 + 0.5*INDEX(Property_CF!$B$187:$AZ$187,1,$A7))<=180000,29467+((F7 + 0.5*INDEX(Property_CF!$B$187:$AZ$187,1,$A7))-120000)*0.37, 51667+((F7 + 0.5*INDEX(Property_CF!$B$187:$AZ$187,1,$A7))-180000)*0.45)))))+((F7 + 0.5*INDEX(Property_CF!$B$187:$AZ$187,1,$A7)))*0.02 -> 62754.024 | P7: {=E7+F7+INDEX(Property_CF!$C$187:$AZ$187,1,$A7)} -> 405451.23 | Q7: =Budget!$P$6 -> 76477.3 | R7: =SUM('Rental Tax & Gearing'!$H$6:$H$8) -> -11228.788 | S7: =IF($C7 < Scenarios!$K$7, (P7 + R7 - Q7), 0 ) -> 317745.14 | T7: =IF($C7 < Scenarios!$K$7, P7 - Budget!$P$6, 0) -> 328973.93 | U7: =U6*(1+Scenarios!$K$8) + IF(C7<Scenarios!$K$7, 'Superannuation (Inputs)'!$N$7, 0) -> 1213720 | V7: =V6*(1+Scenarios!$K$11) -> 1758810.1 | W7: =W6*(1+Scenarios!$K$8) + S7 -> 694026.75 | X7: =SUM(U7:W7) -> 3666556.9 | Y7: =IF(C7>=Scenarios!$K$7, Profile!B10*(1+Scenarios!$K$10)^(C7-Scenarios!$K$7), 0) -> 0 | Z7: =X7-Y7 -> 3666556.9
A8: =ROW()-ROW($A$6)+1 -> 3 | B8: =B7+1 -> 2028 | C8: =C7+1 -> 50 | D8: =D7+1 -> 43 | E8: =IF( $C8 < Scenarios!$K$7, _xlfn.XLOOKUP($B8,'Income Schedule'!$A$5:$A$60,'Income Schedule'!$B$5:$B$60,0), IF( $C8 = Scenarios!$K$7, _xlfn.XLOOKUP($B8,'Income Schedule'!$A$5:$A$60,'Income Schedule'!$B$5:$B$60,0) * (1-Profile!$B$20), 0 ) ) -> 180000 | F8: =IF( $C8 < (Scenarios!$K$15 + (Profile!$B$6-Profile!$B$7)), _xlfn.XLOOKUP($B8,'Income Schedule'!$A$5:$A$60,'Income Schedule'!$C$5:$C$60,0), IF( $C8 = (Scenarios!$K$15 + (Profile!$B$6-Profile!$B$7)), _xlfn.XLOOKUP($B8,'Income Schedule'!$A$5:$A$60,'Income Schedule'!$C$5:$C$60,0) * (1-Profile!$B$21), 0 ) ) -> 172000 | G8: =IF( $C8 < Scenarios!$K$7, IF('Superannuation (Inputs)'!$I$6="Fixed", 'Superannuation (Inputs)'!$C$6, 'Superannuation (Inputs)'!$J$6 ), IF( $C8 = Scenarios!$K$7, IF('Superannuation (Inputs)'!$I$6="Fixed", 'Superannuation (Inputs)'!$C$6*(1-Profile!$B$20), 'Superannuation (Inputs)'!$J$6 ), 0 ) ) -> 5400 | H8: =G8 * 'Superannuation (Inputs)'!$H$6 -> 810 | I8: =IF( $C8 < (Scenarios!$K$15 + (Profile!$B$6-Profile!$B$7)), IF('Superannuation (Inputs)'!$I$7="Fixed", 'Superannuation (Inputs)'!$C$7, 'Superannuation (Inputs)'!$J$7 ), IF( $C8 = (Scenarios!$K$15 + (Profile!$B$6-Profile!$B$7)), IF('Superannuation (Inputs)'!$I$7="Fixed", 'Superannuation (Inputs)'!$C$7*(1-Profile!$B$21), 'Superannuation (Inputs)'!$J$7 ), 0 ) ) -> 25564 | J8: =I8 * 'Superannuation (Inputs)'!$H$7 -> 3834.6 | K8: =K7*(1+Scenarios!$K$8) + G8-H8 -> 730845.45 | L8: =L7*(1+Scenarios!$K$8) + H8-I8 -> 461552.69 | M8: =K8+L8 -> 1192398.1 | N8: =(IF((E8 + 0.5*INDEX(Property_CF!$B$187:$AZ$187,1,$A8))<=18200,0, IF((E8 + 0.5*INDEX(Property_CF!$B$187:$AZ$187,1,$A8))<=45000,((E8 + 0.5*INDEX(Property_CF!$B$187:$AZ$187,1,$A8))-18200)*0.19, IF((E8 + 0.5*INDEX(Property_CF!$B$187:$AZ$187,1,$A8))<=120000,5092+((E8 + 0.5*INDEX(Property_CF!$B$187:$AZ$187,1,$A8))-45000)*0.325, IF((E8 + 0.5*INDEX(Property_CF!$B$187:$AZ$187,1,$A8))<=180000,29467+((E8 + 0.5*INDEX(Property_CF!$B$187:$AZ$187,1,$A8))-120000)*0.37, 51667+((E8 + 0.5*INDEX(Property_CF!$B$187:$AZ$187,1,$A8))-180000)*0.45)))))+((E8 + 0.5*INDEX(Property_CF!$B$187:$AZ$187,1,$A8)))*0.02 -> 67828.039 | O8: =(IF((F8 + 0.5*INDEX(Property_CF!$B$187:$AZ$187,1,$A8))<=18200,0, IF((F8 + 0.5*INDEX(Property_CF!$B$187:$AZ$187,1,$A8))<=45000,((F8 + 0.5*INDEX(Property_CF!$B$187:$AZ$187,1,$A8))-18200)*0.19, IF((F8 + 0.5*INDEX(Property_CF!$B$187:$AZ$187,1,$A8))<=120000,5092+((F8 + 0.5*INDEX(Property_CF!$B$187:$AZ$187,1,$A8))-45000)*0.325, IF((F8 + 0.5*INDEX(Property_CF!$B$187:$AZ$187,1,$A8))<=180000,29467+((F8 + 0.5*INDEX(Property_CF!$B$187:$AZ$187,1,$A8))-120000)*0.37, 51667+((F8 + 0.5*INDEX(Property_CF!$B$187:$AZ$187,1,$A8))-180000)*0.45)))))+((F8 + 0.5*INDEX(Property_CF!$B$187:$AZ$187,1,$A8)))*0.02 -> 64068.039 | P8: {=E8+F8+INDEX(Property_CF!$C$187:$AZ$187,1,$A8)} -> 408419.18 | Q8: =Budget!$P$6 -> 76477.3 | R8: =SUM('Rental Tax & Gearing'!$H$6:$H$8) -> -11228.788 | S8: =IF($C8 < Scenarios!$K$7, (P8 + R8 - Q8), 0 ) -> 320713.09 | T8: =IF($C8 < Scenarios!$K$7, P8 - Budget!$P$6, 0) -> 331941.88 | U8: =U7*(1+Scenarios!$K$8) + IF(C8<Scenarios!$K$7, 'Superannuation (Inputs)'!$N$7, 0) -> 1347611.8 | V8: =V7*(1+Scenarios!$K$11) -> 1837956.6 | W8: =W7*(1+0.03) -> 714847.55 | X8: =SUM(U8:W8) -> 3900416 | Y8: =IF(C8>=Scenarios!$K$7, Profile!B11*(1+Scenarios!$K$10)^(C8-Scenarios!$K$7), 0) -> 0 | Z8: =X8-Y8 -> 3900416
A9: =ROW()-ROW($A$6)+1 -> 4 | B9: =B8+1 -> 2029 | C9: =C8+1 -> 51 | D9: =D8+1 -> 44 | E9: =IF( $C9 < Scenarios!$K$7, _xlfn.XLOOKUP($B9,'Income Schedule'!$A$5:$A$60,'Income Schedule'!$B$5:$B$60,0), IF( $C9 = Scenarios!$K$7, _xlfn.XLOOKUP($B9,'Income Schedule'!$A$5:$A$60,'Income Schedule'!$B$5:$B$60,0) * (1-Profile!$B$20), 0 ) ) -> 180000 | F9: =IF( $C9 < (Scenarios!$K$15 + (Profile!$B$6-Profile!$B$7)), _xlfn.XLOOKUP($B9,'Income Schedule'!$A$5:$A$60,'Income Schedule'!$C$5:$C$60,0), IF( $C9 = (Scenarios!$K$15 + (Profile!$B$6-Profile!$B$7)), _xlfn.XLOOKUP($B9,'Income Schedule'!$A$5:$A$60,'Income Schedule'!$C$5:$C$60,0) * (1-Profile!$B$21), 0 ) ) -> 172000 | G9: =IF( $C9 < Scenarios!$K$7, IF('Superannuation (Inputs)'!$I$6="Fixed", 'Superannuation (Inputs)'!$C$6, 'Superannuation (Inputs)'!$J$6 ), IF( $C9 = Scenarios!$K$7, IF('Superannuation (Inputs)'!$I$6="Fixed", 'Superannuation (Inputs)'!$C$6*(1-Profile!$B$20), 'Superannuation (Inputs)'!$J$6 ), 0 ) ) -> 5400 | H9: =G9 * 'Superannuation (Inputs)'!$H$6 -> 810 | I9: =IF( $C9 < (Scenarios!$K$15 + (Profile!$B$6-Profile!$B$7)), IF('Superannuation (Inputs)'!$I$7="Fixed", 'Superannuation (Inputs)'!$C$7, 'Superannuation (Inputs)'!$J$7 ), IF( $C9 = (Scenarios!$K$15 + (Profile!$B$6-Profile!$B$7)), IF('Superannuation (Inputs)'!$I$7="Fixed", 'Superannuation (Inputs)'!$C$7*(1-Profile!$B$21), 'Superannuation (Inputs)'!$J$7 ), 0 ) ) -> 25564 | J9: =I9 * 'Superannuation (Inputs)'!$H$7 -> 3834.6 | K9: =K8*(1+Scenarios!$K$8) + G9-H9 -> 782940.4 | L9: =L8*(1+Scenarios!$K$8) + H9-I9 -> 466799.61 | M9: =K9+L9 -> 1249740 | N9: =(IF((E9 + 0.5*INDEX(Property_CF!$B$187:$AZ$187,1,$A9))<=18200,0, IF((E9 + 0.5*INDEX(Property_CF!$B$187:$AZ$187,1,$A9))<=45000,((E9 + 0.5*INDEX(Property_CF!$B$187:$AZ$187,1,$A9))-18200)*0.19, IF((E9 + 0.5*INDEX(Property_CF!$B$187:$AZ$187,1,$A9))<=120000,5092+((E9 + 0.5*INDEX(Property_CF!$B$187:$AZ$187,1,$A9))-45000)*0.325, IF((E9 + 0.5*INDEX(Property_CF!$B$187:$AZ$187,1,$A9))<=180000,29467+((E9 + 0.5*INDEX(Property_CF!$B$187:$AZ$187,1,$A9))-120000)*0.37, 51667+((E9 + 0.5*INDEX(Property_CF!$B$187:$AZ$187,1,$A9))-180000)*0.45)))))+((E9 + 0.5*INDEX(Property_CF!$B$187:$AZ$187,1,$A9)))*0.02 -> 68525.507 | O9: =(IF((F9 + 0.5*INDEX(Property_CF!$B$187:$AZ$187,1,$A9))<=18200,0, IF((F9 + 0.5*INDEX(Property_CF!$B$187:$AZ$187,1,$A9))<=45000,((F9 + 0.5*INDEX(Property_CF!$B$187:$AZ$187,1,$A9))-18200)*0.19, IF((F9 + 0.5*INDEX(Property_CF!$B$187:$AZ$187,1,$A9))<=120000,5092+((F9 + 0.5*INDEX(Property_CF!$B$187:$AZ$187,1,$A9))-45000)*0.325, IF((F9 + 0.5*INDEX(Property_CF!$B$187:$AZ$187,1,$A9))<=180000,29467+((F9 + 0.5*INDEX(Property_CF!$B$187:$AZ$187,1,$A9))-120000)*0.37, 51667+((F9 + 0.5*INDEX(Property_CF!$B$187:$AZ$187,1,$A9))-180000)*0.45)))))+((F9 + 0.5*INDEX(Property_CF!$B$187:$AZ$187,1,$A9)))*0.02 -> 64765.507 | P9: {=E9+F9+INDEX(Property_CF!$C$187:$AZ$187,1,$A9)} -> 411476.22 | Q9: =Budget!$P$6 -> 76477.3 | R9: =SUM('Rental Tax & Gearing'!$H$6:$H$8) -> -11228.788 | S9: =IF($C9 < Scenarios!$K$7, (P9 + R9 - Q9), 0 ) -> 323770.14 | T9: =IF($C9 < Scenarios!$K$7, P9 - Budget!$P$6, 0) -> 334998.92 | U9: =U8*(1+Scenarios!$K$8) + IF(C9<Scenarios!$K$7, 'Superannuation (Inputs)'!$N$7, 0) -> 1490206.6 | V9: =V8*(1+Scenarios!$K$11) -> 1920664.6 | W9: =W8*(1+0.03) -> 736292.98 | X9: =SUM(U9:W9) -> 4147164.2 | Y9: =IF(C9>=Scenarios!$K$7, Profile!B12*(1+Scenarios!$K$10)^(C9-Scenarios!$K$7), 0) -> 0 | Z9: =X9-Y9 -> 4147164.2
A10: =ROW()-ROW($A$6)+1 -> 5 | B10: =B9+1 -> 2030 | C10: =C9+1 -> 52 | D10: =D9+1 -> 45 | E10: =IF( $C10 < Scenarios!$K$7, _xlfn.XLOOKUP($B10,'Income Schedule'!$A$5:$A$60,'Income Schedule'!$B$5:$B$60,0), IF( $C10 = Scenarios!$K$7, _xlfn.XLOOKUP($B10,'Income Schedule'!$A$5:$A$60,'Income Schedule'!$B$5:$B$60,0) * (1-Profile!$B$20), 0 ) ) -> 180000 | F10: =IF( $C10 < (Scenarios!$K$15 + (Profile!$B$6-Profile!$B$7)), _xlfn.XLOOKUP($B10,'Income Schedule'!$A$5:$A$60,'Income Schedule'!$C$5:$C$60,0), IF( $C10 = (Scenarios!$K$15 + (Profile!$B$6-Profile!$B$7)), _xlfn.XLOOKUP($B10,'Income Schedule'!$A$5:$A$60,'Income Schedule'!$C$5:$C$60,0) * (1-Profile!$B$21), 0 ) ) -> 172000 | G10: =IF( $C10 < Scenarios!$K$7, IF('Superannuation (Inputs)'!$I$6="Fixed", 'Superannuation (Inputs)'!$C$6, 'Superannuation (Inputs)'!$J$6 ), IF( $C10 = Scenarios!$K$7, IF('Superannuation (Inputs)'!$I$6="Fixed", 'Superannuation (Inputs)'!$C$6*(1-Profile!$B$20), 'Superannuation (Inputs)'!$J$6 ), 0 ) ) -> 5400 | H10: =G10 * 'Superannuation (Inputs)'!$H$6 -> 810 | I10: =IF( $C10 < (Scenarios!$K$15 + (Profile!$B$6-Profile!$B$7)), IF('Superannuation (Inputs)'!$I$7="Fixed", 'Superannuation (Inputs)'!$C$7, 'Superannuation (Inputs)'!$J$7 ), IF( $C10 = (Scenarios!$K$15 + (Profile!$B$6-Profile!$B$7)), IF('Superannuation (Inputs)'!$I$7="Fixed", 'Superannuation (Inputs)'!$C$7*(1-Profile!$B$21), 'Superannuation (Inputs)'!$J$7 ), 0 ) ) -> 25564 | J10: =I10 * 'Superannuation (Inputs)'!$H$7 -> 3834.6 | K10: =K9*(1+Scenarios!$K$8) + G10-H10 -> 838421.53 | L10: =L9*(1+Scenarios!$K$8) + H10-I10 -> 472387.59 | M10: =K10+L10 -> 1310809.1 | N10: =(IF((E10 + 0.5*INDEX(Property_CF!$B$187:$AZ$187,1,$A10))<=18200,0, IF((E10 + 0.5*INDEX(Property_CF!$B$187:$AZ$187,1,$A10))<=45000,((E10 + 0.5*INDEX(Property_CF!$B$187:$AZ$187,1,$A10))-18200)*0.19, IF((E10 + 0.5*INDEX(Property_CF!$B$187:$AZ$187,1,$A10))<=120000,5092+((E10 + 0.5*INDEX(Property_CF!$B$187:$AZ$187,1,$A10))-45000)*0.325, IF((E10 + 0.5*INDEX(Property_CF!$B$187:$AZ$187,1,$A10))<=180000,29467+((E10 + 0.5*INDEX(Property_CF!$B$187:$AZ$187,1,$A10))-120000)*0.37, 51667+((E10 + 0.5*INDEX(Property_CF!$B$187:$AZ$187,1,$A10))-180000)*0.45)))))+((E10 + 0.5*INDEX(Property_CF!$B$187:$AZ$187,1,$A10)))*0.02 -> 69243.912 | O10: =(IF((F10 + 0.5*INDEX(Property_CF!$B$187:$AZ$187,1,$A10))<=18200,0, IF((F10 + 0.5*INDEX(Property_CF!$B$187:$AZ$187,1,$A10))<=45000,((F10 + 0.5*INDEX(Property_CF!$B$187:$AZ$187,1,$A10))-18200)*0.19, IF((F10 + 0.5*INDEX(Property_CF!$B$187:$AZ$187,1,$A10))<=120000,5092+((F10 + 0.5*INDEX(Property_CF!$B$187:$AZ$187,1,$A10))-45000)*0.325, IF((F10 + 0.5*INDEX(Property_CF!$B$187:$AZ$187,1,$A10))<=180000,29467+((F10 + 0.5*INDEX(Property_CF!$B$187:$AZ$187,1,$A10))-120000)*0.37, 51667+((F10 + 0.5*INDEX(Property_CF!$B$187:$AZ$187,1,$A10))-180000)*0.45)))))+((F10 + 0.5*INDEX(Property_CF!$B$187:$AZ$187,1,$A10)))*0.02 -> 65483.912 | P10: {=E10+F10+INDEX(Property_CF!$C$187:$AZ$187,1,$A10)} -> 408289.17 | Q10: =Budget!$P$6 -> 76477.3 | R10: =SUM('Rental Tax & Gearing'!$H$6:$H$8) -> -11228.788 | S10: =IF($C10 < Scenarios!$K$7, (P10 + R10 - Q10), 0 ) -> 320583.08 | T10: =IF($C10 < Scenarios!$K$7, P10 - Budget!$P$6, 0) -> 331811.87 | U10: =U9*(1+Scenarios!$K$8) + IF(C10<Scenarios!$K$7, 'Superannuation (Inputs)'!$N$7, 0) -> 1642070 | V10: =V9*(1+Scenarios!$K$11) -> 2007094.6 | W10: =W9*(1+0.03) -> 758381.76 | X10: =SUM(U10:W10) -> 4407546.3 | Y10: =IF(C10>=Scenarios!$K$7, Profile!B13*(1+Scenarios!$K$10)^(C10-Scenarios!$K$7), 0) -> 0 | Z10: =X10-Y10 -> 4407546.3
A11: =ROW()-ROW($A$6)+1 -> 6 | B11: =B10+1 -> 2031 | C11: =C10+1 -> 53 | D11: =D10+1 -> 46 | E11: =IF( $C11 < Scenarios!$K$7, _xlfn.XLOOKUP($B11,'Income Schedule'!$A$5:$A$60,'Income Schedule'!$B$5:$B$60,0), IF( $C11 = Scenarios!$K$7, _xlfn.XLOOKUP($B11,'Income Schedule'!$A$5:$A$60,'Income Schedule'!$B$5:$B$60,0) * (1-Profile!$B$20), 0 ) ) -> 180000 | F11: =IF( $C11 < (Scenarios!$K$15 + (Profile!$B$6-Profile!$B$7)), _xlfn.XLOOKUP($B11,'Income Schedule'!$A$5:$A$60,'Income Schedule'!$C$5:$C$60,0), IF( $C11 = (Scenarios!$K$15 + (Profile!$B$6-Profile!$B$7)), _xlfn.XLOOKUP($B11,'Income Schedule'!$A$5:$A$60,'Income Schedule'!$C$5:$C$60,0) * (1-Profile!$B$21), 0 ) ) -> 172000 | G11: =IF( $C11 < Scenarios!$K$7, IF('Superannuation (Inputs)'!$I$6="Fixed", 'Superannuation (Inputs)'!$C$6, 'Superannuation (Inputs)'!$J$6 ), IF( $C11 = Scenarios!$K$7, IF('Superannuation (Inputs)'!$I$6="Fixed", 'Superannuation (Inputs)'!$C$6*(1-Profile!$B$20), 'Superannuation (Inputs)'!$J$6 ), 0 ) ) -> 5400 | H11: =G11 * 'Superannuation (Inputs)'!$H$6 -> 810 | I11: =IF( $C11 < (Scenarios!$K$15 + (Profile!$B$6-Profile!$B$7)), IF('Superannuation (Inputs)'!$I$7="Fixed", 'Superannuation (Inputs)'!$C$7, 'Superannuation (Inputs)'!$J$7 ), IF( $C11 = (Scenarios!$K$15 + (Profile!$B$6-Profile!$B$7)), IF('Superannuation (Inputs)'!$I$7="Fixed", 'Superannuation (Inputs)'!$C$7*(1-Profile!$B$21), 'Superannuation (Inputs)'!$J$7 ), 0 ) ) -> 25564 | J11: =I11 * 'Superannuation (Inputs)'!$H$7 -> 3834.6 | K11: =K10*(1+Scenarios!$K$8) + G11-H11 -> 897508.93 | L11: =L10*(1+Scenarios!$K$8) + H11-I11 -> 478338.78 | M11: =K11+L11 -> 1375847.7 | N11: =(IF((E11 + 0.5*INDEX(Property_CF!$B$187:$AZ$187,1,$A11))<=18200,0, IF((E11 + 0.5*INDEX(Property_CF!$B$187:$AZ$187,1,$A11))<=45000,((E11 + 0.5*INDEX(Property_CF!$B$187:$AZ$187,1,$A11))-18200)*0.19, IF((E11 + 0.5*INDEX(Property_CF!$B$187:$AZ$187,1,$A11))<=120000,5092+((E11 + 0.5*INDEX(Property_CF!$B$187:$AZ$187,1,$A11))-45000)*0.325, IF((E11 + 0.5*INDEX(Property_CF!$B$187:$AZ$187,1,$A11))<=180000,29467+((E11 + 0.5*INDEX(Property_CF!$B$187:$AZ$187,1,$A11))-120000)*0.37, 51667+((E11 + 0.5*INDEX(Property_CF!$B$187:$AZ$187,1,$A11))-180000)*0.45)))))+((E11 + 0.5*INDEX(Property_CF!$B$187:$AZ$187,1,$A11)))*0.02 -> 68494.955 | O11: =(IF((F11 + 0.5*INDEX(Property_CF!$B$187:$AZ$187,1,$A11))<=18200,0, IF((F11 + 0.5*INDEX(Property_CF!$B$187:$AZ$187,1,$A11))<=45000,((F11 + 0.5*INDEX(Property_CF!$B$187:$AZ$187,1,$A11))-18200)*0.19, IF((F11 + 0.5*INDEX(Property_CF!$B$187:$AZ$187,1,$A11))<=120000,5092+((F11 + 0.5*INDEX(Property_CF!$B$187:$AZ$187,1,$A11))-45000)*0.325, IF((F11 + 0.5*INDEX(Property_CF!$B$187:$AZ$187,1,$A11))<=180000,29467+((F11 + 0.5*INDEX(Property_CF!$B$187:$AZ$187,1,$A11))-120000)*0.37, 51667+((F11 + 0.5*INDEX(Property_CF!$B$187:$AZ$187,1,$A11))-180000)*0.45)))))+((F11 + 0.5*INDEX(Property_CF!$B$187:$AZ$187,1,$A11)))*0.02 -> 64734.955 | P11: {=E11+F11+INDEX(Property_CF!$C$187:$AZ$187,1,$A11)} -> 417350.87 | Q11: =Budget!$P$6 -> 76477.3 | R11: =SUM('Rental Tax & Gearing'!$H$6:$H$8) -> -11228.788 | S11: =IF($C11 < Scenarios!$K$7, (P11 + R11 - Q11), 0 ) -> 329644.78 | T11: =IF($C11 < Scenarios!$K$7, P11 - Budget!$P$6, 0) -> 340873.57 | U11: =U10*(1+Scenarios!$K$8) + IF(C11<Scenarios!$K$7, 'Superannuation (Inputs)'!$N$7, 0) -> 1803804.5 | V11: =V10*(1+Scenarios!$K$11) -> 2097413.8 | W11: =W10*(1+0.03) -> 781133.22 | X11: =SUM(U11:W11) -> 4682351.6 | Y11: =IF(C11>=Scenarios!$K$7, Profile!B14*(1+Scenarios!$K$10)^(C11-Scenarios!$K$7), 0) -> 0 | Z11: =X11-Y11 -> 4682351.6
A12: =ROW()-ROW($A$6)+1 -> 7 | B12: =B11+1 -> 2032 | C12: =C11+1 -> 54 | D12: =D11+1 -> 47 | E12: =IF( $C12 < Scenarios!$K$7, _xlfn.XLOOKUP($B12,'Income Schedule'!$A$5:$A$60,'Income Schedule'!$B$5:$B$60,0), IF( $C12 = Scenarios!$K$7, _xlfn.XLOOKUP($B12,'Income Schedule'!$A$5:$A$60,'Income Schedule'!$B$5:$B$60,0) * (1-Profile!$B$20), 0 ) ) -> 180000 | F12: =IF( $C12 < (Scenarios!$K$15 + (Profile!$B$6-Profile!$B$7)), _xlfn.XLOOKUP($B12,'Income Schedule'!$A$5:$A$60,'Income Schedule'!$C$5:$C$60,0), IF( $C12 = (Scenarios!$K$15 + (Profile!$B$6-Profile!$B$7)), _xlfn.XLOOKUP($B12,'Income Schedule'!$A$5:$A$60,'Income Schedule'!$C$5:$C$60,0) * (1-Profile!$B$21), 0 ) ) -> 172000 | G12: =IF( $C12 < Scenarios!$K$7, IF('Superannuation (Inputs)'!$I$6="Fixed", 'Superannuation (Inputs)'!$C$6, 'Superannuation (Inputs)'!$J$6 ), IF( $C12 = Scenarios!$K$7, IF('Superannuation (Inputs)'!$I$6="Fixed", 'Superannuation (Inputs)'!$C$6*(1-Profile!$B$20), 'Superannuation (Inputs)'!$J$6 ), 0 ) ) -> 5400 | H12: =G12 * 'Superannuation (Inputs)'!$H$6 -> 810 | I12: =IF( $C12 < (Scenarios!$K$15 + (Profile!$B$6-Profile!$B$7)), IF('Superannuation (Inputs)'!$I$7="Fixed", 'Superannuation (Inputs)'!$C$7, 'Superannuation (Inputs)'!$J$7 ), IF( $C12 = (Scenarios!$K$15 + (Profile!$B$6-Profile!$B$7)), IF('Superannuation (Inputs)'!$I$7="Fixed", 'Superannuation (Inputs)'!$C$7*(1-Profile!$B$21), 'Superannuation (Inputs)'!$J$7 ), 0 ) ) -> 25564 | J12: =I12 * 'Superannuation (Inputs)'!$H$7 -> 3834.6 | K12: =K11*(1+Scenarios!$K$8) + G12-H12 -> 960437.01 | L12: =L11*(1+Scenarios!$K$8) + H12-I12 -> 484676.8 | M12: =K12+L12 -> 1445113.8 | N12: =(IF((E12 + 0.5*INDEX(Property_CF!$B$187:$AZ$187,1,$A12))<=18200,0, IF((E12 + 0.5*INDEX(Property_CF!$B$187:$AZ$187,1,$A12))<=45000,((E12 + 0.5*INDEX(Property_CF!$B$187:$AZ$187,1,$A12))-18200)*0.19, IF((E12 + 0.5*INDEX(Property_CF!$B$187:$AZ$187,1,$A12))<=120000,5092+((E12 + 0.5*INDEX(Property_CF!$B$187:$AZ$187,1,$A12))-45000)*0.325, IF((E12 + 0.5*INDEX(Property_CF!$B$187:$AZ$187,1,$A12))<=180000,29467+((E12 + 0.5*INDEX(Property_CF!$B$187:$AZ$187,1,$A12))-120000)*0.37, 51667+((E12 + 0.5*INDEX(Property_CF!$B$187:$AZ$187,1,$A12))-180000)*0.45)))))+((E12 + 0.5*INDEX(Property_CF!$B$187:$AZ$187,1,$A12)))*0.02 -> 70624.454 | O12: =(IF((F12 + 0.5*INDEX(Property_CF!$B$187:$AZ$187,1,$A12))<=18200,0, IF((F12 + 0.5*INDEX(Property_CF!$B$187:$AZ$187,1,$A12))<=45000,((F12 + 0.5*INDEX(Property_CF!$B$187:$AZ$187,1,$A12))-18200)*0.19, IF((F12 + 0.5*INDEX(Property_CF!$B$187:$AZ$187,1,$A12))<=120000,5092+((F12 + 0.5*INDEX(Property_CF!$B$187:$AZ$187,1,$A12))-45000)*0.325, IF((F12 + 0.5*INDEX(Property_CF!$B$187:$AZ$187,1,$A12))<=180000,29467+((F12 + 0.5*INDEX(Property_CF!$B$187:$AZ$187,1,$A12))-120000)*0.37, 51667+((F12 + 0.5*INDEX(Property_CF!$B$187:$AZ$187,1,$A12))-180000)*0.45)))))+((F12 + 0.5*INDEX(Property_CF!$B$187:$AZ$187,1,$A12)))*0.02 -> 66864.454 | P12: {=E12+F12+INDEX(Property_CF!$C$187:$AZ$187,1,$A12)} -> 422811.48 | Q12: =Budget!$P$6 -> 76477.3 | R12: =SUM('Rental Tax & Gearing'!$H$6:$H$8) -> -11228.788 | S12: =IF($C12 < Scenarios!$K$7, (P12 + R12 - Q12), 0 ) -> 335105.4 | T12: =IF($C12 < Scenarios!$K$7, P12 - Budget!$P$6, 0) -> 346334.18 | U12: =U11*(1+Scenarios!$K$8) + IF(C12<Scenarios!$K$7, 'Superannuation (Inputs)'!$N$7, 0) -> 1976051.8 | V12: =V11*(1+Scenarios!$K$11) -> 2191797.4 | W12: =W11*(1+0.03) -> 804567.21 | X12: =SUM(U12:W12) -> 4972416.5 | Y12: =IF(C12>=Scenarios!$K$7, Profile!B15*(1+Scenarios!$K$10)^(C12-Scenarios!$K$7), 0) -> 0 | Z12: =X12-Y12 -> 4972416.5
A13: =ROW()-ROW($A$6)+1 -> 8 | B13: =B12+1 -> 2033 | C13: =C12+1 -> 55 | D13: =D12+1 -> 48 | E13: =IF( $C13 < Scenarios!$K$7, _xlfn.XLOOKUP($B13,'Income Schedule'!$A$5:$A$60,'Income Schedule'!$B$5:$B$60,0), IF( $C13 = Scenarios!$K$7, _xlfn.XLOOKUP($B13,'Income Schedule'!$A$5:$A$60,'Income Schedule'!$B$5:$B$60,0) * (1-Profile!$B$20), 0 ) ) -> 180000 | F13: =IF( $C13 < (Scenarios!$K$15 + (Profile!$B$6-Profile!$B$7)), _xlfn.XLOOKUP($B13,'Income Schedule'!$A$5:$A$60,'Income Schedule'!$C$5:$C$60,0), IF( $C13 = (Scenarios!$K$15 + (Profile!$B$6-Profile!$B$7)), _xlfn.XLOOKUP($B13,'Income Schedule'!$A$5:$A$60,'Income Schedule'!$C$5:$C$60,0) * (1-Profile!$B$21), 0 ) ) -> 172000 | G13: =IF( $C13 < Scenarios!$K$7, IF('Superannuation (Inputs)'!$I$6="Fixed", 'Superannuation (Inputs)'!$C$6, 'Superannuation (Inputs)'!$J$6 ), IF( $C13 = Scenarios!$K$7, IF('Superannuation (Inputs)'!$I$6="Fixed", 'Superannuation (Inputs)'!$C$6*(1-Profile!$B$20), 'Superannuation (Inputs)'!$J$6 ), 0 ) ) -> 5400 | H13: =G13 * 'Superannuation (Inputs)'!$H$6 -> 810 | I13: =IF( $C13 < (Scenarios!$K$15 + (Profile!$B$6-Profile!$B$7)), IF('Superannuation (Inputs)'!$I$7="Fixed", 'Superannuation (Inputs)'!$C$7, 'Superannuation (Inputs)'!$J$7 ), IF( $C13 = (Scenarios!$K$15 + (Profile!$B$6-Profile!$B$7)), IF('Superannuation (Inputs)'!$I$7="Fixed", 'Superannuation (Inputs)'!$C$7*(1-Profile!$B$21), 'Superannuation (Inputs)'!$J$7 ), 0 ) ) -> 25564 | J13: =I13 * 'Superannuation (Inputs)'!$H$7 -> 3834.6 | K13: =K12*(1+Scenarios!$K$8) + G13-H13 -> 1027455.4 | L13: =L12*(1+Scenarios!$K$8) + H13-I13 -> 491426.8 | M13: =K13+L13 -> 1518882.2 | N13: =(IF((E13 + 0.5*INDEX(Property_CF!$B$187:$AZ$187,1,$A13))<=18200,0, IF((E13 + 0.5*INDEX(Property_CF!$B$187:$AZ$187,1,$A13))<=45000,((E13 + 0.5*INDEX(Property_CF!$B$187:$AZ$187,1,$A13))-18200)*0.19, IF((E13 + 0.5*INDEX(Property_CF!$B$187:$AZ$187,1,$A13))<=120000,5092+((E13 + 0.5*INDEX(Property_CF!$B$187:$AZ$187,1,$A13))-45000)*0.325, IF((E13 + 0.5*INDEX(Property_CF!$B$187:$AZ$187,1,$A13))<=180000,29467+((E13 + 0.5*INDEX(Property_CF!$B$187:$AZ$187,1,$A13))-120000)*0.37, 51667+((E13 + 0.5*INDEX(Property_CF!$B$187:$AZ$187,1,$A13))-180000)*0.45)))))+((E13 + 0.5*INDEX(Property_CF!$B$187:$AZ$187,1,$A13)))*0.02 -> 71907.698 | O13: =(IF((F13 + 0.5*INDEX(Property_CF!$B$187:$AZ$187,1,$A13))<=18200,0, IF((F13 + 0.5*INDEX(Property_CF!$B$187:$AZ$187,1,$A13))<=45000,((F13 + 0.5*INDEX(Property_CF!$B$187:$AZ$187,1,$A13))-18200)*0.19, IF((F13 + 0.5*INDEX(Property_CF!$B$187:$AZ$187,1,$A13))<=120000,5092+((F13 + 0.5*INDEX(Property_CF!$B$187:$AZ$187,1,$A13))-45000)*0.325, IF((F13 + 0.5*INDEX(Property_CF!$B$187:$AZ$187,1,$A13))<=180000,29467+((F13 + 0.5*INDEX(Property_CF!$B$187:$AZ$187,1,$A13))-120000)*0.37, 51667+((F13 + 0.5*INDEX(Property_CF!$B$187:$AZ$187,1,$A13))-180000)*0.45)))))+((F13 + 0.5*INDEX(Property_CF!$B$187:$AZ$187,1,$A13)))*0.02 -> 68147.698 | P13: {=E13+F13+INDEX(Property_CF!$C$187:$AZ$187,1,$A13)} -> 428497.15 | Q13: =Budget!$P$6 -> 76477.3 | R13: =SUM('Rental Tax & Gearing'!$H$6:$H$8) -> -11228.788 | S13: =IF($C13 < Scenarios!$K$7, (P13 + R13 - Q13), 0 ) -> 340791.06 | T13: =IF($C13 < Scenarios!$K$7, P13 - Budget!$P$6, 0) -> 352019.85 | U13: =U12*(1+Scenarios!$K$8) + IF(C13<Scenarios!$K$7, 'Superannuation (Inputs)'!$N$7, 0) -> 2159495.2 | V13: =V12*(1+Scenarios!$K$11) -> 2290428.3 | W13: =W12*(1+0.03) -> 828704.23 | X13: =SUM(U13:W13) -> 5278627.8 | Y13: =IF(C13>=Scenarios!$K$7, Profile!B16*(1+Scenarios!$K$10)^(C13-Scenarios!$K$7), 0) -> 0 | Z13: =X13-Y13 -> 5278627.8
A14: =ROW()-ROW($A$6)+1 -> 9 | B14: =B13+1 -> 2034 | C14: =C13+1 -> 56 | D14: =D13+1 -> 49 | E14: =IF( $C14 < Scenarios!$K$7, _xlfn.XLOOKUP($B14,'Income Schedule'!$A$5:$A$60,'Income Schedule'!$B$5:$B$60,0), IF( $C14 = Scenarios!$K$7, _xlfn.XLOOKUP($B14,'Income Schedule'!$A$5:$A$60,'Income Schedule'!$B$5:$B$60,0) * (1-Profile!$B$20), 0 ) ) -> 180000 | F14: =IF( $C14 < (Scenarios!$K$15 + (Profile!$B$6-Profile!$B$7)), _xlfn.XLOOKUP($B14,'Income Schedule'!$A$5:$A$60,'Income Schedule'!$C$5:$C$60,0), IF( $C14 = (Scenarios!$K$15 + (Profile!$B$6-Profile!$B$7)), _xlfn.XLOOKUP($B14,'Income Schedule'!$A$5:$A$60,'Income Schedule'!$C$5:$C$60,0) * (1-Profile!$B$21), 0 ) ) -> 172000 | G14: =IF( $C14 < Scenarios!$K$7, IF('Superannuation (Inputs)'!$I$6="Fixed", 'Superannuation (Inputs)'!$C$6, 'Superannuation (Inputs)'!$J$6 ), IF( $C14 = Scenarios!$K$7, IF('Superannuation (Inputs)'!$I$6="Fixed", 'Superannuation (Inputs)'!$C$6*(1-Profile!$B$20), 'Superannuation (Inputs)'!$J$6 ), 0 ) ) -> 5400 | H14: =G14 * 'Superannuation (Inputs)'!$H$6 -> 810 | I14: =IF( $C14 < (Scenarios!$K$15 + (Profile!$B$6-Profile!$B$7)), IF('Superannuation (Inputs)'!$I$7="Fixed", 'Superannuation (Inputs)'!$C$7, 'Superannuation (Inputs)'!$J$7 ), IF( $C14 = (Scenarios!$K$15 + (Profile!$B$6-Profile!$B$7)), IF('Superannuation (Inputs)'!$I$7="Fixed", 'Superannuation (Inputs)'!$C$7*(1-Profile!$B$21), 'Superannuation (Inputs)'!$J$7 ), 0 ) ) -> 25564 | J14: =I14 * 'Superannuation (Inputs)'!$H$7 -> 3834.6 | K14: =K13*(1+Scenarios!$K$8) + G14-H14 -> 1098830 | L14: =L13*(1+Scenarios!$K$8) + H14-I14 -> 498615.54 | M14: =K14+L14 -> 1597445.6 | N14: =(IF((E14 + 0.5*INDEX(Property_CF!$B$187:$AZ$187,1,$A14))<=18200,0, IF((E14 + 0.5*INDEX(Property_CF!$B$187:$AZ$187,1,$A14))<=45000,((E14 + 0.5*INDEX(Property_CF!$B$187:$AZ$187,1,$A14))-18200)*0.19, IF((E14 + 0.5*INDEX(Property_CF!$B$187:$AZ$187,1,$A14))<=120000,5092+((E14 + 0.5*INDEX(Property_CF!$B$187:$AZ$187,1,$A14))-45000)*0.325, IF((E14 + 0.5*INDEX(Property_CF!$B$187:$AZ$187,1,$A14))<=180000,29467+((E14 + 0.5*INDEX(Property_CF!$B$187:$AZ$187,1,$A14))-120000)*0.37, 51667+((E14 + 0.5*INDEX(Property_CF!$B$187:$AZ$187,1,$A14))-180000)*0.45)))))+((E14 + 0.5*INDEX(Property_CF!$B$187:$AZ$187,1,$A14)))*0.02 -> 73243.829 | O14: =(IF((F14 + 0.5*INDEX(Property_CF!$B$187:$AZ$187,1,$A14))<=18200,0, IF((F14 + 0.5*INDEX(Property_CF!$B$187:$AZ$187,1,$A14))<=45000,((F14 + 0.5*INDEX(Property_CF!$B$187:$AZ$187,1,$A14))-18200)*0.19, IF((F14 + 0.5*INDEX(Property_CF!$B$187:$AZ$187,1,$A14))<=120000,5092+((F14 + 0.5*INDEX(Property_CF!$B$187:$AZ$187,1,$A14))-45000)*0.325, IF((F14 + 0.5*INDEX(Property_CF!$B$187:$AZ$187,1,$A14))<=180000,29467+((F14 + 0.5*INDEX(Property_CF!$B$187:$AZ$187,1,$A14))-120000)*0.37, 51667+((F14 + 0.5*INDEX(Property_CF!$B$187:$AZ$187,1,$A14))-180000)*0.45)))))+((F14 + 0.5*INDEX(Property_CF!$B$187:$AZ$187,1,$A14)))*0.02 -> 69483.829 | P14: {=E14+F14+INDEX(Property_CF!$C$187:$AZ$187,1,$A14)} -> 430033.07 | Q14: =Budget!$P$6 -> 76477.3 | R14: =SUM('Rental Tax & Gearing'!$H$6:$H$8) -> -11228.788 | S14: =IF($C14 < Scenarios!$K$7, (P14 + R14 - Q14), 0 ) -> 342326.98 | T14: =IF($C14 < Scenarios!$K$7, P14 - Budget!$P$6, 0) -> 353555.77 | U14: =U13*(1+Scenarios!$K$8) + IF(C14<Scenarios!$K$7, 'Superannuation (Inputs)'!$N$7, 0) -> 2354862.4 | V14: =V13*(1+Scenarios!$K$11) -> 2393497.6 | W14: =W13*(1+0.03) -> 853565.36 | X14: =SUM(U14:W14) -> 5601925.3 | Y14: =IF(C14>=Scenarios!$K$7, Profile!B17*(1+Scenarios!$K$10)^(C14-Scenarios!$K$7), 0) -> 0 | Z14: =X14-Y14 -> 5601925.3
A15: =ROW()-ROW($A$6)+1 -> 10 | B15: =B14+1 -> 2035 | C15: =C14+1 -> 57 | D15: =D14+1 -> 50 | E15: =IF( $C15 < Scenarios!$K$7, _xlfn.XLOOKUP($B15,'Income Schedule'!$A$5:$A$60,'Income Schedule'!$B$5:$B$60,0), IF( $C15 = Scenarios!$K$7, _xlfn.XLOOKUP($B15,'Income Schedule'!$A$5:$A$60,'Income Schedule'!$B$5:$B$60,0) * (1-Profile!$B$20), 0 ) ) -> 180000 | F15: =IF( $C15 < (Scenarios!$K$15 + (Profile!$B$6-Profile!$B$7)), _xlfn.XLOOKUP($B15,'Income Schedule'!$A$5:$A$60,'Income Schedule'!$C$5:$C$60,0), IF( $C15 = (Scenarios!$K$15 + (Profile!$B$6-Profile!$B$7)), _xlfn.XLOOKUP($B15,'Income Schedule'!$A$5:$A$60,'Income Schedule'!$C$5:$C$60,0) * (1-Profile!$B$21), 0 ) ) -> 172000 | G15: =IF( $C15 < Scenarios!$K$7, IF('Superannuation (Inputs)'!$I$6="Fixed", 'Superannuation (Inputs)'!$C$6, 'Superannuation (Inputs)'!$J$6 ), IF( $C15 = Scenarios!$K$7, IF('Superannuation (Inputs)'!$I$6="Fixed", 'Superannuation (Inputs)'!$C$6*(1-Profile!$B$20), 'Superannuation (Inputs)'!$J$6 ), 0 ) ) -> 5400 | H15: =G15 * 'Superannuation (Inputs)'!$H$6 -> 810 | I15: =IF( $C15 < (Scenarios!$K$15 + (Profile!$B$6-Profile!$B$7)), IF('Superannuation (Inputs)'!$I$7="Fixed", 'Superannuation (Inputs)'!$C$7, 'Superannuation (Inputs)'!$J$7 ), IF( $C15 = (Scenarios!$K$15 + (Profile!$B$6-Profile!$B$7)), IF('Superannuation (Inputs)'!$I$7="Fixed", 'Superannuation (Inputs)'!$C$7*(1-Profile!$B$21), 'Superannuation (Inputs)'!$J$7 ), 0 ) ) -> 25564 | J15: =I15 * 'Superannuation (Inputs)'!$H$7 -> 3834.6 | K15: =K14*(1+Scenarios!$K$8) + G15-H15 -> 1174844 | L15: =L14*(1+Scenarios!$K$8) + H15-I15 -> 506271.55 | M15: =K15+L15 -> 1681115.5 | N15: =(IF((E15 + 0.5*INDEX(Property_CF!$B$187:$AZ$187,1,$A15))<=18200,0, IF((E15 + 0.5*INDEX(Property_CF!$B$187:$AZ$187,1,$A15))<=45000,((E15 + 0.5*INDEX(Property_CF!$B$187:$AZ$187,1,$A15))-18200)*0.19, IF((E15 + 0.5*INDEX(Property_CF!$B$187:$AZ$187,1,$A15))<=120000,5092+((E15 + 0.5*INDEX(Property_CF!$B$187:$AZ$187,1,$A15))-45000)*0.325, IF((E15 + 0.5*INDEX(Property_CF!$B$187:$AZ$187,1,$A15))<=180000,29467+((E15 + 0.5*INDEX(Property_CF!$B$187:$AZ$187,1,$A15))-120000)*0.37, 51667+((E15 + 0.5*INDEX(Property_CF!$B$187:$AZ$187,1,$A15))-180000)*0.45)))))+((E15 + 0.5*INDEX(Property_CF!$B$187:$AZ$187,1,$A15)))*0.02 -> 73604.772 | O15: =(IF((F15 + 0.5*INDEX(Property_CF!$B$187:$AZ$187,1,$A15))<=18200,0, IF((F15 + 0.5*INDEX(Property_CF!$B$187:$AZ$187,1,$A15))<=45000,((F15 + 0.5*INDEX(Property_CF!$B$187:$AZ$187,1,$A15))-18200)*0.19, IF((F15 + 0.5*INDEX(Property_CF!$B$187:$AZ$187,1,$A15))<=120000,5092+((F15 + 0.5*INDEX(Property_CF!$B$187:$AZ$187,1,$A15))-45000)*0.325, IF((F15 + 0.5*INDEX(Property_CF!$B$187:$AZ$187,1,$A15))<=180000,29467+((F15 + 0.5*INDEX(Property_CF!$B$187:$AZ$187,1,$A15))-120000)*0.37, 51667+((F15 + 0.5*INDEX(Property_CF!$B$187:$AZ$187,1,$A15))-180000)*0.45)))))+((F15 + 0.5*INDEX(Property_CF!$B$187:$AZ$187,1,$A15)))*0.02 -> 69844.772 | P15: {=E15+F15+INDEX(Property_CF!$C$187:$AZ$187,1,$A15)} -> 440585.86 | Q15: =Budget!$P$6 -> 76477.3 | R15: =SUM('Rental Tax & Gearing'!$H$6:$H$8) -> -11228.788 | S15: =IF($C15 < Scenarios!$K$7, (P15 + R15 - Q15), 0 ) -> 352879.77 | T15: =IF($C15 < Scenarios!$K$7, P15 - Budget!$P$6, 0) -> 364108.56 | U15: =U14*(1+Scenarios!$K$8) + IF(C15<Scenarios!$K$7, 'Superannuation (Inputs)'!$N$7, 0) -> 2562928.5 | V15: =V14*(1+Scenarios!$K$11) -> 2501205 | W15: =W14*(1+0.03) -> 879172.32 | X15: =SUM(U15:W15) -> 5943305.8 | Y15: =IF(C15>=Scenarios!$K$7, Profile!B18*(1+Scenarios!$K$10)^(C15-Scenarios!$K$7), 0) -> 0 | Z15: =X15-Y15 -> 5943305.8
A16: =ROW()-ROW($A$6)+1 -> 11 | B16: =B15+1 -> 2036 | C16: =C15+1 -> 58 | D16: =D15+1 -> 51 | E16: =IF( $C16 < Scenarios!$K$7, _xlfn.XLOOKUP($B16,'Income Schedule'!$A$5:$A$60,'Income Schedule'!$B$5:$B$60,0), IF( $C16 = Scenarios!$K$7, _xlfn.XLOOKUP($B16,'Income Schedule'!$A$5:$A$60,'Income Schedule'!$B$5:$B$60,0) * (1-Profile!$B$20), 0 ) ) -> 180000 | F16: =IF( $C16 < (Scenarios!$K$15 + (Profile!$B$6-Profile!$B$7)), _xlfn.XLOOKUP($B16,'Income Schedule'!$A$5:$A$60,'Income Schedule'!$C$5:$C$60,0), IF( $C16 = (Scenarios!$K$15 + (Profile!$B$6-Profile!$B$7)), _xlfn.XLOOKUP($B16,'Income Schedule'!$A$5:$A$60,'Income Schedule'!$C$5:$C$60,0) * (1-Profile!$B$21), 0 ) ) -> 172000 | G16: =IF( $C16 < Scenarios!$K$7, IF('Superannuation (Inputs)'!$I$6="Fixed", 'Superannuation (Inputs)'!$C$6, 'Superannuation (Inputs)'!$J$6 ), IF( $C16 = Scenarios!$K$7, IF('Superannuation (Inputs)'!$I$6="Fixed", 'Superannuation (Inputs)'!$C$6*(1-Profile!$B$20), 'Superannuation (Inputs)'!$J$6 ), 0 ) ) -> 5400 | H16: =G16 * 'Superannuation (Inputs)'!$H$6 -> 810 | I16: =IF( $C16 < (Scenarios!$K$15 + (Profile!$B$6-Profile!$B$7)), IF('Superannuation (Inputs)'!$I$7="Fixed", 'Superannuation (Inputs)'!$C$7, 'Superannuation (Inputs)'!$J$7 ), IF( $C16 = (Scenarios!$K$15 + (Profile!$B$6-Profile!$B$7)), IF('Superannuation (Inputs)'!$I$7="Fixed", 'Superannuation (Inputs)'!$C$7*(1-Profile!$B$21), 'Superannuation (Inputs)'!$J$7 ), 0 ) ) -> 25564 | J16: =I16 * 'Superannuation (Inputs)'!$H$7 -> 3834.6 | K16: =K15*(1+Scenarios!$K$8) + G16-H16 -> 1255798.8 | L16: =L15*(1+Scenarios!$K$8) + H16-I16 -> 514425.2 | M16: =K16+L16 -> 1770224 | N16: =(IF((E16 + 0.5*INDEX(Property_CF!$B$187:$AZ$187,1,$A16))<=18200,0, IF((E16 + 0.5*INDEX(Property_CF!$B$187:$AZ$187,1,$A16))<=45000,((E16 + 0.5*INDEX(Property_CF!$B$187:$AZ$187,1,$A16))-18200)*0.19, IF((E16 + 0.5*INDEX(Property_CF!$B$187:$AZ$187,1,$A16))<=120000,5092+((E16 + 0.5*INDEX(Property_CF!$B$187:$AZ$187,1,$A16))-45000)*0.325, IF((E16 + 0.5*INDEX(Property_CF!$B$187:$AZ$187,1,$A16))<=180000,29467+((E16 + 0.5*INDEX(Property_CF!$B$187:$AZ$187,1,$A16))-120000)*0.37, 51667+((E16 + 0.5*INDEX(Property_CF!$B$187:$AZ$187,1,$A16))-180000)*0.45)))))+((E16 + 0.5*INDEX(Property_CF!$B$187:$AZ$187,1,$A16)))*0.02 -> 76084.677 | O16: =(IF((F16 + 0.5*INDEX(Property_CF!$B$187:$AZ$187,1,$A16))<=18200,0, IF((F16 + 0.5*INDEX(Property_CF!$B$187:$AZ$187,1,$A16))<=45000,((F16 + 0.5*INDEX(Property_CF!$B$187:$AZ$187,1,$A16))-18200)*0.19, IF((F16 + 0.5*INDEX(Property_CF!$B$187:$AZ$187,1,$A16))<=120000,5092+((F16 + 0.5*INDEX(Property_CF!$B$187:$AZ$187,1,$A16))-45000)*0.325, IF((F16 + 0.5*INDEX(Property_CF!$B$187:$AZ$187,1,$A16))<=180000,29467+((F16 + 0.5*INDEX(Property_CF!$B$187:$AZ$187,1,$A16))-120000)*0.37, 51667+((F16 + 0.5*INDEX(Property_CF!$B$187:$AZ$187,1,$A16))-180000)*0.45)))))+((F16 + 0.5*INDEX(Property_CF!$B$187:$AZ$187,1,$A16)))*0.02 -> 72324.677 | P16: {=E16+F16+INDEX(Property_CF!$C$187:$AZ$187,1,$A16)} -> 447009.8 | Q16: =Budget!$P$6 -> 76477.3 | R16: =SUM('Rental Tax & Gearing'!$H$6:$H$8) -> -11228.788 | S16: =IF($C16 < Scenarios!$K$7, (P16 + R16 - Q16), 0 ) -> 359303.71 | T16: =IF($C16 < Scenarios!$K$7, P16 - Budget!$P$6, 0) -> 370532.5 | U16: =U15*(1+Scenarios!$K$8) + IF(C16<Scenarios!$K$7, 'Superannuation (Inputs)'!$N$7, 0) -> 2784518.8 | V16: =V15*(1+Scenarios!$K$11) -> 2613759.2 | W16: =W15*(1+0.03) -> 905547.49 | X16: =SUM(U16:W16) -> 6303825.5 | Y16: =IF(C16>=Scenarios!$K$7, Profile!B19*(1+Scenarios!$K$10)^(C16-Scenarios!$K$7), 0) -> 0 | Z16: =X16-Y16 -> 6303825.5
A17: =ROW()-ROW($A$6)+1 -> 12 | B17: =B16+1 -> 2037 | C17: =C16+1 -> 59 | D17: =D16+1 -> 52 | E17: =IF( $C17 < Scenarios!$K$7, _xlfn.XLOOKUP($B17,'Income Schedule'!$A$5:$A$60,'Income Schedule'!$B$5:$B$60,0), IF( $C17 = Scenarios!$K$7, _xlfn.XLOOKUP($B17,'Income Schedule'!$A$5:$A$60,'Income Schedule'!$B$5:$B$60,0) * (1-Profile!$B$20), 0 ) ) -> 180000 | F17: =IF( $C17 < (Scenarios!$K$15 + (Profile!$B$6-Profile!$B$7)), _xlfn.XLOOKUP($B17,'Income Schedule'!$A$5:$A$60,'Income Schedule'!$C$5:$C$60,0), IF( $C17 = (Scenarios!$K$15 + (Profile!$B$6-Profile!$B$7)), _xlfn.XLOOKUP($B17,'Income Schedule'!$A$5:$A$60,'Income Schedule'!$C$5:$C$60,0) * (1-Profile!$B$21), 0 ) ) -> 172000 | G17: =IF( $C17 < Scenarios!$K$7, IF('Superannuation (Inputs)'!$I$6="Fixed", 'Superannuation (Inputs)'!$C$6, 'Superannuation (Inputs)'!$J$6 ), IF( $C17 = Scenarios!$K$7, IF('Superannuation (Inputs)'!$I$6="Fixed", 'Superannuation (Inputs)'!$C$6*(1-Profile!$B$20), 'Superannuation (Inputs)'!$J$6 ), 0 ) ) -> 5400 | H17: =G17 * 'Superannuation (Inputs)'!$H$6 -> 810 | I17: =IF( $C17 < (Scenarios!$K$15 + (Profile!$B$6-Profile!$B$7)), IF('Superannuation (Inputs)'!$I$7="Fixed", 'Superannuation (Inputs)'!$C$7, 'Superannuation (Inputs)'!$J$7 ), IF( $C17 = (Scenarios!$K$15 + (Profile!$B$6-Profile!$B$7)), IF('Superannuation (Inputs)'!$I$7="Fixed", 'Superannuation (Inputs)'!$C$7*(1-Profile!$B$21), 'Superannuation (Inputs)'!$J$7 ), 0 ) ) -> 25564 | J17: =I17 * 'Superannuation (Inputs)'!$H$7 -> 3834.6 | K17: =K16*(1+Scenarios!$K$8) + G17-H17 -> 1342015.8 | L17: =L16*(1+Scenarios!$K$8) + H17-I17 -> 523108.84 | M17: =K17+L17 -> 1865124.6 | N17: =(IF((E17 + 0.5*INDEX(Property_CF!$B$187:$AZ$187,1,$A17))<=18200,0, IF((E17 + 0.5*INDEX(Property_CF!$B$187:$AZ$187,1,$A17))<=45000,((E17 + 0.5*INDEX(Property_CF!$B$187:$AZ$187,1,$A17))-18200)*0.19, IF((E17 + 0.5*INDEX(Property_CF!$B$187:$AZ$187,1,$A17))<=120000,5092+((E17 + 0.5*INDEX(Property_CF!$B$187:$AZ$187,1,$A17))-45000)*0.325, IF((E17 + 0.5*INDEX(Property_CF!$B$187:$AZ$187,1,$A17))<=180000,29467+((E17 + 0.5*INDEX(Property_CF!$B$187:$AZ$187,1,$A17))-120000)*0.37, 51667+((E17 + 0.5*INDEX(Property_CF!$B$187:$AZ$187,1,$A17))-180000)*0.45)))))+((E17 + 0.5*INDEX(Property_CF!$B$187:$AZ$187,1,$A17)))*0.02 -> 77594.302 | O17: =(IF((F17 + 0.5*INDEX(Property_CF!$B$187:$AZ$187,1,$A17))<=18200,0, IF((F17 + 0.5*INDEX(Property_CF!$B$187:$AZ$187,1,$A17))<=45000,((F17 + 0.5*INDEX(Property_CF!$B$187:$AZ$187,1,$A17))-18200)*0.19, IF((F17 + 0.5*INDEX(Property_CF!$B$187:$AZ$187,1,$A17))<=120000,5092+((F17 + 0.5*INDEX(Property_CF!$B$187:$AZ$187,1,$A17))-45000)*0.325, IF((F17 + 0.5*INDEX(Property_CF!$B$187:$AZ$187,1,$A17))<=180000,29467+((F17 + 0.5*INDEX(Property_CF!$B$187:$AZ$187,1,$A17))-120000)*0.37, 51667+((F17 + 0.5*INDEX(Property_CF!$B$187:$AZ$187,1,$A17))-180000)*0.45)))))+((F17 + 0.5*INDEX(Property_CF!$B$187:$AZ$187,1,$A17)))*0.02 -> 73834.302 | P17: {=E17+F17+INDEX(Property_CF!$C$187:$AZ$187,1,$A17)} -> 453703.22 | Q17: =Budget!$P$6 -> 76477.3 | R17: =SUM('Rental Tax & Gearing'!$H$6:$H$8) -> -11228.788 | S17: =IF($C17 < Scenarios!$K$7, (P17 + R17 - Q17), 0 ) -> 365997.13 | T17: =IF($C17 < Scenarios!$K$7, P17 - Budget!$P$6, 0) -> 377225.92 | U17: =U16*(1+Scenarios!$K$8) + IF(C17<Scenarios!$K$7, 'Superannuation (Inputs)'!$N$7, 0) -> 3020512.5 | V17: =V16*(1+Scenarios!$K$11) -> 2731378.4 | W17: =W16*(1+0.03) -> 932713.91 | X17: =SUM(U17:W17) -> 6684604.8 | Y17: =IF(C17>=Scenarios!$K$7, Profile!B20*(1+Scenarios!$K$10)^(C17-Scenarios!$K$7), 0) -> 0 | Z17: =X17-Y17 -> 6684604.8
A18: =ROW()-ROW($A$6)+1 -> 13 | B18: =B17+1 -> 2038 | C18: =C17+1 -> 60 | D18: =D17+1 -> 53 | E18: =IF( $C18 < Scenarios!$K$7, _xlfn.XLOOKUP($B18,'Income Schedule'!$A$5:$A$60,'Income Schedule'!$B$5:$B$60,0), IF( $C18 = Scenarios!$K$7, _xlfn.XLOOKUP($B18,'Income Schedule'!$A$5:$A$60,'Income Schedule'!$B$5:$B$60,0) * (1-Profile!$B$20), 0 ) ) -> 180000 | F18: =IF( $C18 < (Scenarios!$K$15 + (Profile!$B$6-Profile!$B$7)), _xlfn.XLOOKUP($B18,'Income Schedule'!$A$5:$A$60,'Income Schedule'!$C$5:$C$60,0), IF( $C18 = (Scenarios!$K$15 + (Profile!$B$6-Profile!$B$7)), _xlfn.XLOOKUP($B18,'Income Schedule'!$A$5:$A$60,'Income Schedule'!$C$5:$C$60,0) * (1-Profile!$B$21), 0 ) ) -> 172000 | G18: =IF( $C18 < Scenarios!$K$7, IF('Superannuation (Inputs)'!$I$6="Fixed", 'Superannuation (Inputs)'!$C$6, 'Superannuation (Inputs)'!$J$6 ), IF( $C18 = Scenarios!$K$7, IF('Superannuation (Inputs)'!$I$6="Fixed", 'Superannuation (Inputs)'!$C$6*(1-Profile!$B$20), 'Superannuation (Inputs)'!$J$6 ), 0 ) ) -> 5400 | H18: =G18 * 'Superannuation (Inputs)'!$H$6 -> 810 | I18: =IF( $C18 < (Scenarios!$K$15 + (Profile!$B$6-Profile!$B$7)), IF('Superannuation (Inputs)'!$I$7="Fixed", 'Superannuation (Inputs)'!$C$7, 'Superannuation (Inputs)'!$J$7 ), IF( $C18 = (Scenarios!$K$15 + (Profile!$B$6-Profile!$B$7)), IF('Superannuation (Inputs)'!$I$7="Fixed", 'Superannuation (Inputs)'!$C$7*(1-Profile!$B$21), 'Superannuation (Inputs)'!$J$7 ), 0 ) ) -> 25564 | J18: =I18 * 'Superannuation (Inputs)'!$H$7 -> 3834.6 | K18: =K17*(1+Scenarios!$K$8) + G18-H18 -> 1433836.8 | L18: =L17*(1+Scenarios!$K$8) + H18-I18 -> 532356.91 | M18: =K18+L18 -> 1966193.7 | N18: =(IF((E18 + 0.5*INDEX(Property_CF!$B$187:$AZ$187,1,$A18))<=18200,0, IF((E18 + 0.5*INDEX(Property_CF!$B$187:$AZ$187,1,$A18))<=45000,((E18 + 0.5*INDEX(Property_CF!$B$187:$AZ$187,1,$A18))-18200)*0.19, IF((E18 + 0.5*INDEX(Property_CF!$B$187:$AZ$187,1,$A18))<=120000,5092+((E18 + 0.5*INDEX(Property_CF!$B$187:$AZ$187,1,$A18))-45000)*0.325, IF((E18 + 0.5*INDEX(Property_CF!$B$187:$AZ$187,1,$A18))<=180000,29467+((E18 + 0.5*INDEX(Property_CF!$B$187:$AZ$187,1,$A18))-120000)*0.37, 51667+((E18 + 0.5*INDEX(Property_CF!$B$187:$AZ$187,1,$A18))-180000)*0.45)))))+((E18 + 0.5*INDEX(Property_CF!$B$187:$AZ$187,1,$A18)))*0.02 -> 79167.257 | O18: =(IF((F18 + 0.5*INDEX(Property_CF!$B$187:$AZ$187,1,$A18))<=18200,0, IF((F18 + 0.5*INDEX(Property_CF!$B$187:$AZ$187,1,$A18))<=45000,((F18 + 0.5*INDEX(Property_CF!$B$187:$AZ$187,1,$A18))-18200)*0.19, IF((F18 + 0.5*INDEX(Property_CF!$B$187:$AZ$187,1,$A18))<=120000,5092+((F18 + 0.5*INDEX(Property_CF!$B$187:$AZ$187,1,$A18))-45000)*0.325, IF((F18 + 0.5*INDEX(Property_CF!$B$187:$AZ$187,1,$A18))<=180000,29467+((F18 + 0.5*INDEX(Property_CF!$B$187:$AZ$187,1,$A18))-120000)*0.37, 51667+((F18 + 0.5*INDEX(Property_CF!$B$187:$AZ$187,1,$A18))-180000)*0.45)))))+((F18 + 0.5*INDEX(Property_CF!$B$187:$AZ$187,1,$A18)))*0.02 -> 75407.257 | P18: {=E18+F18+INDEX(Property_CF!$C$187:$AZ$187,1,$A18)} -> 456292.04 | Q18: =Budget!$P$6 -> 76477.3 | R18: =SUM('Rental Tax & Gearing'!$H$6:$H$8) -> -11228.788 | S18: =IF($C18 < Scenarios!$K$7, (P18 + R18 - Q18), 0 ) -> 0 | T18: =IF($C18 < Scenarios!$K$7, P18 - Budget!$P$6, 0) -> 0 | U18: =U17*(1+Scenarios!$K$8) + IF(C18<Scenarios!$K$7, 'Superannuation (Inputs)'!$N$7, 0) -> 3216845.8 | V18: =V17*(1+Scenarios!$K$11) -> 2854290.4 | W18: =W17*(1+0.03) -> 960695.33 | X18: =SUM(U18:W18) -> 7031831.6 | Y18: =IF(C18>=Scenarios!$K$7, Profile!B21*(1+Scenarios!$K$10)^(C18-Scenarios!$K$7), 0) -> 0 | Z18: =X18-Y18 -> 7031831.6
A19: =ROW()-ROW($A$6)+1 -> 14 | B19: =B18+1 -> 2039 | C19: =C18+1 -> 61 | D19: =D18+1 -> 54 | E19: =IF( $C19 < Scenarios!$K$7, _xlfn.XLOOKUP($B19,'Income Schedule'!$A$5:$A$60,'Income Schedule'!$B$5:$B$60,0), IF( $C19 = Scenarios!$K$7, _xlfn.XLOOKUP($B19,'Income Schedule'!$A$5:$A$60,'Income Schedule'!$B$5:$B$60,0) * (1-Profile!$B$20), 0 ) ) -> 0 | F19: =IF( $C19 < (Scenarios!$K$15 + (Profile!$B$6-Profile!$B$7)), _xlfn.XLOOKUP($B19,'Income Schedule'!$A$5:$A$60,'Income Schedule'!$C$5:$C$60,0), IF( $C19 = (Scenarios!$K$15 + (Profile!$B$6-Profile!$B$7)), _xlfn.XLOOKUP($B19,'Income Schedule'!$A$5:$A$60,'Income Schedule'!$C$5:$C$60,0) * (1-Profile!$B$21), 0 ) ) -> 0 | G19: =IF( $C19 < Scenarios!$K$7, IF('Superannuation (Inputs)'!$I$6="Fixed", 'Superannuation (Inputs)'!$C$6, 'Superannuation (Inputs)'!$J$6 ), IF( $C19 = Scenarios!$K$7, IF('Superannuation (Inputs)'!$I$6="Fixed", 'Superannuation (Inputs)'!$C$6*(1-Profile!$B$20), 'Superannuation (Inputs)'!$J$6 ), 0 ) ) -> 0 | H19: =G19 * 'Superannuation (Inputs)'!$H$6 -> 0 | I19: =IF( $C19 < (Scenarios!$K$15 + (Profile!$B$6-Profile!$B$7)), IF('Superannuation (Inputs)'!$I$7="Fixed", 'Superannuation (Inputs)'!$C$7, 'Superannuation (Inputs)'!$J$7 ), IF( $C19 = (Scenarios!$K$15 + (Profile!$B$6-Profile!$B$7)), IF('Superannuation (Inputs)'!$I$7="Fixed", 'Superannuation (Inputs)'!$C$7*(1-Profile!$B$21), 'Superannuation (Inputs)'!$J$7 ), 0 ) ) -> 0 | J19: =I19 * 'Superannuation (Inputs)'!$H$7 -> 0 | K19: =K18*(1+Scenarios!$K$8) + G19-H19 -> 1527036.2 | L19: =L18*(1+Scenarios!$K$8) + H19-I19 -> 566960.11 | M19: =K19+L19 -> 2093996.3 | N19: =(IF((E19 + 0.5*INDEX(Property_CF!$B$187:$AZ$187,1,$A19))<=18200,0, IF((E19 + 0.5*INDEX(Property_CF!$B$187:$AZ$187,1,$A19))<=45000,((E19 + 0.5*INDEX(Property_CF!$B$187:$AZ$187,1,$A19))-18200)*0.19, IF((E19 + 0.5*INDEX(Property_CF!$B$187:$AZ$187,1,$A19))<=120000,5092+((E19 + 0.5*INDEX(Property_CF!$B$187:$AZ$187,1,$A19))-45000)*0.325, IF((E19 + 0.5*INDEX(Property_CF!$B$187:$AZ$187,1,$A19))<=180000,29467+((E19 + 0.5*INDEX(Property_CF!$B$187:$AZ$187,1,$A19))-120000)*0.37, 51667+((E19 + 0.5*INDEX(Property_CF!$B$187:$AZ$187,1,$A19))-180000)*0.45)))))+((E19 + 0.5*INDEX(Property_CF!$B$187:$AZ$187,1,$A19)))*0.02 -> 8457.3767 | O19: =(IF((F19 + 0.5*INDEX(Property_CF!$B$187:$AZ$187,1,$A19))<=18200,0, IF((F19 + 0.5*INDEX(Property_CF!$B$187:$AZ$187,1,$A19))<=45000,((F19 + 0.5*INDEX(Property_CF!$B$187:$AZ$187,1,$A19))-18200)*0.19, IF((F19 + 0.5*INDEX(Property_CF!$B$187:$AZ$187,1,$A19))<=120000,5092+((F19 + 0.5*INDEX(Property_CF!$B$187:$AZ$187,1,$A19))-45000)*0.325, IF((F19 + 0.5*INDEX(Property_CF!$B$187:$AZ$187,1,$A19))<=180000,29467+((F19 + 0.5*INDEX(Property_CF!$B$187:$AZ$187,1,$A19))-120000)*0.37, 51667+((F19 + 0.5*INDEX(Property_CF!$B$187:$AZ$187,1,$A19))-180000)*0.45)))))+((F19 + 0.5*INDEX(Property_CF!$B$187:$AZ$187,1,$A19)))*0.02 -> 8457.3767 | P19: {=E19+F19+INDEX(Property_CF!$C$187:$AZ$187,1,$A19)} -> 115947.45 | Q19: =Budget!$P$6 -> 76477.3 | R19: =SUM('Rental Tax & Gearing'!$H$6:$H$8) -> -11228.788 | S19: =IF($C19 < Scenarios!$K$7, (P19 + R19 - Q19), 0 ) -> 0 | T19: =IF($C19 < Scenarios!$K$7, P19 - Budget!$P$6, 0) -> 0 | U19: =U18*(1+Scenarios!$K$8) + IF(C19<Scenarios!$K$7, 'Superannuation (Inputs)'!$N$7, 0) -> 3425940.8 | V19: =V18*(1+Scenarios!$K$11) -> 2982733.5 | W19: =W18*(1+0.03) -> 989516.19 | X19: =SUM(U19:W19) -> 7398190.5 | Y19: =IF(C19>=Scenarios!$K$7, Profile!B22*(1+Scenarios!$K$10)^(C19-Scenarios!$K$7), 0) -> 0 | Z19: =X19-Y19 -> 7398190.5
... A47: =ROW()-ROW($A$6)+1 -> 42 | B47: =B46+1 -> 2067 | C47: =C46+1 -> 89 | D47: =D46+1 -> 82 | E47: =IF( $C47 < Scenarios!$K$7, _xlfn.XLOOKUP($B47,'Income Schedule'!$A$5:$A$60,'Income Schedule'!$B$5:$B$60,0), IF( $C47 = Scenarios!$K$7, _xlfn.XLOOKUP($B47,'Income Schedule'!$A$5:$A$60,'Income Schedule'!$B$5:$B$60,0) * (1-Profile!$B$20), 0 ) ) -> 0 | F47: =IF( $C47 < (Scenarios!$K$15 + (Profile!$B$6-Profile!$B$7)), _xlfn.XLOOKUP($B47,'Income Schedule'!$A$5:$A$60,'Income Schedule'!$C$5:$C$60,0), IF( $C47 = (Scenarios!$K$15 + (Profile!$B$6-Profile!$B$7)), _xlfn.XLOOKUP($B47,'Income Schedule'!$A$5:$A$60,'Income Schedule'!$C$5:$C$60,0) * (1-Profile!$B$21), 0 ) ) -> 0 | G47: =IF( $C47 < Scenarios!$K$7, IF('Superannuation (Inputs)'!$I$6="Fixed", 'Superannuation (Inputs)'!$C$6, 'Superannuation (Inputs)'!$J$6 ), IF( $C47 = Scenarios!$K$7, IF('Superannuation (Inputs)'!$I$6="Fixed", 'Superannuation (Inputs)'!$C$6*(1-Profile!$B$20), 'Superannuation (Inputs)'!$J$6 ), 0 ) ) -> 0 | H47: =G47 * 'Superannuation (Inputs)'!$H$6 -> 0 | I47: =IF( $C47 < (Scenarios!$K$15 + (Profile!$B$6-Profile!$B$7)), IF('Superannuation (Inputs)'!$I$7="Fixed", 'Superannuation (Inputs)'!$C$7, 'Superannuation (Inputs)'!$J$7 ), IF( $C47 = (Scenarios!$K$15 + (Profile!$B$6-Profile!$B$7)), IF('Superannuation (Inputs)'!$I$7="Fixed", 'Superannuation (Inputs)'!$C$7*(1-Profile!$B$21), 'Superannuation (Inputs)'!$J$7 ), 0 ) ) -> 0 | J47: =I47 * 'Superannuation (Inputs)'!$H$7 -> 0 | K47: =K46*(1+Scenarios!$K$8) + G47-H47 -> 8905090.6 | L47: =L46*(1+Scenarios!$K$8) + H47-I47 -> 3306294.4 | M47: =K47+L47 -> 12211385 | N47: =(IF((E47 + 0.5*INDEX(Property_CF!$B$187:$AZ$187,1,$A47))<=18200,0, IF((E47 + 0.5*INDEX(Property_CF!$B$187:$AZ$187,1,$A47))<=45000,((E47 + 0.5*INDEX(Property_CF!$B$187:$AZ$187,1,$A47))-18200)*0.19, IF((E47 + 0.5*INDEX(Property_CF!$B$187:$AZ$187,1,$A47))<=120000,5092+((E47 + 0.5*INDEX(Property_CF!$B$187:$AZ$187,1,$A47))-45000)*0.325, IF((E47 + 0.5*INDEX(Property_CF!$B$187:$AZ$187,1,$A47))<=180000,29467+((E47 + 0.5*INDEX(Property_CF!$B$187:$AZ$187,1,$A47))-120000)*0.37, 51667+((E47 + 0.5*INDEX(Property_CF!$B$187:$AZ$187,1,$A47))-180000)*0.45)))))+((E47 + 0.5*INDEX(Property_CF!$B$187:$AZ$187,1,$A47)))*0.02 -> 42004.738 | O47: =(IF((F47 + 0.5*INDEX(Property_CF!$B$187:$AZ$187,1,$A47))<=18200,0, IF((F47 + 0.5*INDEX(Property_CF!$B$187:$AZ$187,1,$A47))<=45000,((F47 + 0.5*INDEX(Property_CF!$B$187:$AZ$187,1,$A47))-18200)*0.19, IF((F47 + 0.5*INDEX(Property_CF!$B$187:$AZ$187,1,$A47))<=120000,5092+((F47 + 0.5*INDEX(Property_CF!$B$187:$AZ$187,1,$A47))-45000)*0.325, IF((F47 + 0.5*INDEX(Property_CF!$B$187:$AZ$187,1,$A47))<=180000,29467+((F47 + 0.5*INDEX(Property_CF!$B$187:$AZ$187,1,$A47))-120000)*0.37, 51667+((F47 + 0.5*INDEX(Property_CF!$B$187:$AZ$187,1,$A47))-180000)*0.45)))))+((F47 + 0.5*INDEX(Property_CF!$B$187:$AZ$187,1,$A47)))*0.02 -> 42004.738 | P47: {=E47+F47+INDEX(Property_CF!$C$187:$AZ$187,1,$A47)} -> 306147.88 | Q47: =Budget!$P$6 -> 76477.3 | R47: =SUM('Rental Tax & Gearing'!$H$6:$H$8) -> -11228.788 | S47: =IF($C47 < Scenarios!$K$7, (P47 + R47 - Q47), 0 ) -> 0 | T47: =IF($C47 < Scenarios!$K$7, P47 - Budget!$P$6, 0) -> 0 | U47: =U46*(1+Scenarios!$K$8) + IF(C47<Scenarios!$K$7, 'Superannuation (Inputs)'!$N$7, 0) -> 19978776 | V47: =V46*(1+Scenarios!$K$11) -> 10229881 | W47: =W46*(1+0.03) -> 2263941.5 | X47: =SUM(U47:W47) -> 32472598 | Y47: =IF(C47>=Scenarios!$K$7, Profile!B50*(1+Scenarios!$K$10)^(C47-Scenarios!$K$7), 0) -> 0 | Z47: =X47-Y47 -> 32472598

Sheet Budget
A1: Detailed Budget (Monthly)
A3: Enter monthly amounts by category. Annual total feeds projections.
A5: Category | B5: Jan | C5: Feb | D5: Mar | E5: Apr | F5: May | G5: Jun | H5: Jul | I5: Aug | J5: Sep | K5: Oct | L5: Nov | M5: Dec | N5: Annual | P5: Annual Budget Total
A6: Housing | B6: =B7 -> 0 | C6: =C7 -> 675 | D6: =D7 -> 0 | E6: =E7 -> 0 | F6: =F7 -> 675 | G6: =G7 -> 0 | H6: =H7 -> 0 | I6: =I7 -> 675 | ... M6: =M7 -> 0 | N6: =SUM(B6:M6) -> 2700 | P6: =N78 -> 76477.3
A7: UNLEY Council | C7: 675 | F7: 675 | I7: 675 | L7: 675 | N7: {=SUM(B7:M7)} -> 2700
A8: Utilities | B8: =SUM(B9:B15) -> 730 | C8: =SUM(C9:C15) -> 130 | D8: =SUM(D9:D15) -> 490 | E8: =SUM(E9:E15) -> 780 | F8: =SUM(F9:F15) -> 130 | G8: =SUM(G9:G15) -> 328 | H8: =SUM(H9:H15) -> 1130 | I8: =SUM(I9:I15) -> 130 | ... M8: =SUM(M9:M15) -> 130 | N8: =SUM(B8:M8) -> 6278
A9: Gas - RED energy | B9: 350 | E9: 300 | H9: 350 | K9: 350 | N9: {=SUM(B9:M9)} -> 1350
A10: Electricity - RED energy | B10: 250 | E10: 350 | H10: 650 | K10: 1200 | N10: {=SUM(B10:M10)} -> 2450
A11: Broadband - TPG | B11: 95 | C11: =B11 -> 95 | D11: =C11 -> 95 | E11: =D11 -> 95 | F11: =E11 -> 95 | G11: =F11 -> 95 | H11: =G11 -> 95 | I11: =H11 -> 95 | J11: =I11 -> 95 | ... M11: =L11 -> 95 | N11: {=SUM(B11:M11)} -> 1140
A12: Mobile - Woolworths Laura | B12: 35 | C12: =B12 -> 35 | D12: =C12 -> 35 | E12: =D12 -> 35 | F12: =E12 -> 35 | G12: =F12 -> 35 | H12: =G12 -> 35 | I12: =H12 -> 35 | J12: =I12 -> 35 | ... M12: =L12 -> 35 | N12: {=SUM(B12:M12)} -> 420
A13: Mobile - Telstra Brett | D13: 360 | L13: 360 | N13: {=SUM(B13:M13)} -> 720
A14: Apple Watch Annual Plan - Beckett | G14: 99 | N14: {=SUM(B14:M14)} -> 99
A15: Apple Watch Annual Plan - Quinn | G15: 99 | N15: {=SUM(B15:M15)} -> 99
A16: Groceries | B16: =SUM(B17) -> 2500 | C16: =SUM(C17) -> 2500 | D16: =SUM(D17) -> 2500 | E16: =SUM(E17) -> 2500 | F16: =SUM(F17) -> 2500 | G16: =SUM(G17) -> 2500 | H16: =SUM(H17) -> 2500 | I16: =SUM(I17) -> 2500 | ... M16: =SUM(M17) -> 2500 | N16: =SUM(B16:M16) -> 30000
A17: Grocery / Takeout | B17: 2500 | C17: 2500 | D17: 2500 | E17: 2500 | F17: 2500 | G17: 2500 | H17: 2500 | I17: 2500 | J17: 2500 | K17: 2500 | L17: 2500 | M17: 2500 | N17: {=SUM(B17:M17)} -> 30000
A18: Transport | B18: =SUM(B19:B22) -> 240 | C18: =SUM(C19:C22) -> 240 | D18: =SUM(D19:D22) -> 2165 | E18: =SUM(E19:E22) -> 240 | F18: =SUM(F19:F22) -> 240 | G18: =SUM(G19:G22) -> 240 | H18: =SUM(H19:H22) -> 240 | I18: =SUM(I19:I22) -> 240 | ... M18: =SUM(M19:M22) -> 240 | N18: =SUM(B18:M18) -> 4805
A19: Local transit (bus) | B19: 160 | C19: 160 | D19: 160 | E19: 160 | F19: 160 | G19: 160 | H19: 160 | I19: 160 | J19: 160 | K19: 160 | L19: 160 | M19: 160 | N19: {=SUM(B19:M19)} -> 1920
A20: NRMA Road Assist | D20: 125 | N20: {=SUM(B20:M20)} -> 125
A21: Car Service | D21: 1800 | N21: {=SUM(B21:M21)} -> 1800
A22: Fuel | B22: 80 | C22: =B22 -> 80 | D22: =C22 -> 80 | E22: =D22 -> 80 | F22: =E22 -> 80 | G22: =F22 -> 80 | H22: =G22 -> 80 | I22: =H22 -> 80 | J22: =I22 -> 80 | ... M22: =L22 -> 80 | N22: {=SUM(B22:M22)} -> 960
A23: Insurance | B23: =SUM(B24:B29) -> 119.99 | C23: =SUM(C24:C29) -> 0 | D23: =SUM(D24:D29) -> 0 | E23: =SUM(E24:E29) -> 1610 | F23: =SUM(F24:F29) -> 0 | G23: =SUM(G24:G29) -> 204.5 | H23: =SUM(H24:H29) -> 2800 | I23: =SUM(I24:I29) -> 3750 | ... M23: =SUM(M24:M29) -> 0 | N23: =SUM(B23:M23) -> 8484.49
A24: AppleCare+ 13" Macbook Air M3 | B24: 119.99 | N24: {=SUM(B24:M24)} -> 119.99
A25: AppleCare+ with theft & loss Iphone 16 Pro Max | G25: =409/2 -> 204.5 | N25: {=SUM(B25:M25)} -> 204.5
A26: Health Insurance - HCF | I26: 3750 | N26: {=SUM(B26:M26)} -> 3750
A27: Home & Contents Insurance | H27: 2800 | N27: {=SUM(B27:M27)} -> 2800
A28: Vehicle - BMW 118i 2012 - Registration / Greenslip (NRMA) | E28: 660 | N28: {=SUM(B28:M28)} -> 660
A29: Vehicle - BMW 118i 20212 - Comprehensive Insurance (NRMA) | E29: 950 | N29: {=SUM(B29:M29)} -> 950
A30: Health | B30: =SUM(B31:B47) -> 891.84 | C30: =SUM(C31:C47) -> 355 | D30: =SUM(D31:D47) -> 360 | E30: =SUM(E31:E47) -> 300 | F30: =SUM(F31:F47) -> 355 | G30: =SUM(G31:G47) -> 360 | H30: =SUM(H31:H47) -> 300 | I30: =SUM(I31:I47) -> 595 | ... M30: =SUM(M31:M47) -> 1087.56 | N30: =SUM(B30:M30) -> 7281.24
A31: Yoga Development | M31: 300 | N31: =SUM(B31:M31) -> 300
A32: Migraine | D32: 360 | G32: 360 | J32: 360 | M32: 360 | N32: =SUM(B32:M32) -> 1440
A33: Sport | N33: =SUM(B33:M33) -> 0
A34: Rugby Australia Registration | B34: 246.84 | N34: =SUM(B34:M34) -> 246.84
A35: SANFL Registration (PlayHQ) | M35: 427.56 | N35: =SUM(B35:M35) -> 427.56
A36: Basketball Connect | K36: 321.84 | N36: =SUM(B36:M36) -> 321.84
A37: Life Be in It After School Basketball | I37: 160 | N37: =SUM(B37:M37) -> 160
A38: Life Be in It Futsal | I38: 80 | N38: =SUM(B38:M38) -> 80
A39: Dance | C39: 355 | F39: 355 | I39: 355 | L39: 355 | N39: =SUM(B39:M39) -> 1420
A40: Gymnastics | B40: 300 | E40: 300 | H40: 300 | K40: 300 | N40: =SUM(B40:M40) -> 1200
A41: Sport Memberships | N41: =SUM(B41:M41) -> 0
A42: Wallabies Membership | B42: 295 | N42: =SUM(B42:M42) -> 295
A43: Wallabies Membership Beckett | B43: 50 | N43: =SUM(B43:M43) -> 50
A44: South Australia Cricket Association (SACA) Brett | J44: 435 | N44: =SUM(B44:M44) -> 435
A45: SACA Laura | J45: 435 | N45: =SUM(B45:M45) -> 435
A46: SACA Beckett | J46: 235 | N46: =SUM(B46:M46) -> 235
A47: SACA Quinn | J47: 235 | N47: =SUM(B47:M47) -> 235
A48: Education/Childcare | B48: 350 | C48: 350 | D48: 350 | E48: 350 | F48: 350 | G48: 350 | H48: 350 | I48: 350 | J48: 350 | K48: 350 | L48: 350 | M48: 350 | N48: =SUM(B48:M48) -> 4200
A49: School Fees Quinn Aenid | C49: 465 | N49: =SUM(B49:M49) -> 465
A50: School Fees Beckett Hofman | C50: 465 | N50: =SUM(B50:M50) -> 465
A51: Subscriptions | B51: =SUM(B52:B66) -> 262.89 | C51: =SUM(C52:C66) -> 132.9 | D51: =SUM(D52:D66) -> 132.9 | E51: =SUM(E52:E66) -> 515.77 | F51: =SUM(F52:F66) -> 132.9 | G51: =SUM(G52:G66) -> 132.9 | H51: =SUM(H52:H66) -> 132.9 | I51: =SUM(I52:I66) -> 248.89 | ... M51: =SUM(M52:M66) -> 249.89 | N51: =SUM(B51:M51) -> 2905.57
A52: Apple One | B52: 49.95 | C52: 49.95 | D52: 49.95 | E52: 49.95 | F52: 49.95 | G52: 49.95 | H52: 49.95 | I52: 49.95 | J52: 49.95 | K52: 49.95 | L52: 49.95 | M52: 49.95 | N52: =SUM(B52:M52) -> 599.4
A53: AMC plus | E53: 83.88 | N53: =SUM(B53:M53) -> 83.88
A54: BritBox | L54: 139.99 | N54: =SUM(B54:M54) -> 139.99
A55: Cruncyroll | M55: 116.99 | N55: =SUM(B55:M55) -> 116.99
A56: Disney+ | L56: 209.99 | N56: =SUM(B56:M56) -> 209.99
A57: Duolingo | B57: 129.99 | N57: =SUM(B57:M57) -> 129.99
A58: HBO Go | E58: 219.99 | N58: =SUM(B58:M58) -> 219.99
A59: Netflix | B59: 37.98 | C59: 37.98 | D59: 37.98 | E59: 37.98 | F59: 37.98 | G59: 37.98 | H59: 37.98 | I59: 37.98 | J59: 37.98 | K59: 37.98 | L59: 37.98 | M59: 37.98 | N59: =SUM(B59:M59) -> 455.76
A60: Paramount+ | I60: 115.99 | N60: =SUM(B60:M60) -> 115.99
A61: PlayStation Deluxe | L61: 214.95 | N61: =SUM(B61:M61) -> 214.95
A62: Prime | E62: 79 | N62: =SUM(B62:M62) -> 79
A63: Prime Video Ad Free | B63: 2.99 | C63: 2.99 | D63: 2.99 | E63: 2.99 | F63: 2.99 | G63: 2.99 | H63: 2.99 | I63: 2.99 | J63: 2.99 | K63: 2.99 | L63: 2.99 | M63: 2.99 | N63: =SUM(B63:M63) -> 35.88
A64: Stan | B64: 17.49 | C64: 17.49 | D64: 17.49 | E64: 17.49 | F64: 17.49 | G64: 17.49 | H64: 17.49 | I64: 17.49 | J64: 17.49 | K64: 17.49 | L64: 17.49 | M64: 17.49 | N64: =SUM(B64:M64) -> 209.88
A65: Stan SPORT | B65: 20.49 | C65: 20.49 | D65: 20.49 | E65: 20.49 | F65: 20.49 | G65: 20.49 | H65: 20.49 | I65: 20.49 | J65: 20.49 | K65: 20.49 | L65: 20.49 | M65: 20.49 | N65: =SUM(B65:M65) -> 245.88
A66: NY Times | B66: 4 | C66: 4 | D66: 4 | E66: 4 | F66: 4 | G66: 4 | H66: 4 | I66: 4 | J66: 4 | K66: 4 | L66: 4 | M66: 4 | N66: =SUM(B66:M66) -> 48
A67: Discretionary | B67: =SUM(B68:B72) -> 58 | C67: =SUM(C68:C72) -> 50 | D67: =SUM(D68:D72) -> 50 | E67: =SUM(E68:E72) -> 50 | F67: =SUM(F68:F72) -> 50 | G67: =SUM(G68:G72) -> 50 | H67: =SUM(H68:H72) -> 50 | I67: =SUM(I68:I72) -> 50 | ... M67: =SUM(M68:M72) -> 50 | N67: =SUM(B67:M67) -> 1123
A68: Medicine Sans Frontiers | B68: 25 | C68: 25 | D68: 25 | E68: 25 | F68: 25 | G68: 25 | H68: 25 | I68: 25 | J68: 25 | K68: 25 | L68: 25 | M68: 25 | N68: =SUM(B68:M68) -> 300
A69: Effective Altruism | B69: 25 | C69: 25 | D69: 25 | E69: 25 | F69: 25 | G69: 25 | H69: 25 | I69: 25 | J69: 25 | K69: 25 | L69: 25 | M69: 25 | N69: =SUM(B69:M69) -> 300
A70: Australian Conservation Foundation | B70: 8 | N70: =SUM(B70:M70) -> 8
A71: Sport Memberships | N71: =SUM(B71:M71) -> 0
A72: SACA Transferrable | J72: 515 | N72: =SUM(B72:M72) -> 515
A73: Travel | B73: =SUM(B74) -> 0 | C73: =SUM(C74) -> 2500 | D73: =SUM(D74) -> 0 | E73: =SUM(E74) -> 0 | F73: =SUM(F74) -> 0 | G73: =SUM(G74) -> 2000 | H73: =SUM(H74) -> 0 | I73: =SUM(I74) -> 0 | ... M73: =SUM(M74) -> 0 | N73: =SUM(B73:M73) -> 4500
A74: Travel | C74: 2500 | G74: 2000 | N74: =SUM(B74:M74) -> 4500
A75: Other | B75: 350 | C75: 350 | D75: 350 | E75: 350 | F75: 350 | G75: 350 | H75: 350 | I75: 350 | J75: 350 | K75: 350 | L75: 350 | M75: 350 | N75: =SUM(B75:M75) -> 4200
A76: Miscellaneous | B76: 2500 | C76: 1000 | D76: 1000 | E76: 1000 | F76: 1000 | G76: 1000 | H76: 1000 | I76: 1000 | J76: 1000 | K76: 1000 | L76: 1000 | M76: 2000 | N76: =SUM(B76:M76) -> 14500
A78: TOTAL | B78: =B6+B8+B16+B18+B23+B30+B48+B51+B67+B73+B75 -> 5502.72 | C78: =C6+C8+C16+C18+C23+C30+C48+C51+C67+C73+C75 -> 7282.9 | D78: =D6+D8+D16+D18+D23+D30+D48+D51+D67+D73+D75 -> 6397.9 | E78: =E6+E8+E16+E18+E23+E30+E48+E51+E67+E73+E75 -> 6695.77 | F78: =F6+F8+F16+F18+F23+F30+F48+F51+F67+F73+F75 -> 4782.9 | G78: =G6+G8+G16+G18+G23+G30+G48+G51+G67+G73+G75 -> 6515.4 | H78: =H6+H8+H16+H18+H23+H30+H48+H51+H67+H73+H75 -> 7852.9 | I78: =I6+I8+I16+I18+I23+I30+I48+I51+I67+I73+I75 -> 8888.89 | ... M78: =M6+M8+M16+M18+M23+M30+M48+M51+M67+M73+M75 -> 4957.45 | N78: =SUM(B78:M78) -> 76477.3

Sheet Assets & Liabilities
A1: Assets & Liabilities (Non-property / Non-super)
A3: Enter balances outside property and super. Properties/Super handled on their own tabs.
A5: Category | B5: Item | C5: Value | D5: Notes | F5: Totals
A6: Assets | B6: Cash & savings | C6: 265000 | D6: Redundancy 2025 | F6: Total Assets | G6: =SUMIF(A:A,"Assets",C:C) -> 303316.06
A7: Assets | B7: Shares/ETFs (non-super) | C7: 33763.86 | D7: ASX:VAS Vanguard Australian Shares Index | F7: Total Liabilities | G7: =SUMIF(A:A,"Liabilities",C:C) -> 0
A8: Assets | B8: Shares/ETFs (non-super) | C8: 4552.2 | D8: ASX:VGS MSCI Index International Shares ETF | F8: Net (excl prop/super) | G8: =G6-G7 -> 303316.06
A9: Assets | B9: Other assets | C9: 0
A10: Liabilities | B10: Credit cards | C10: 0
A11: Liabilities | B11: Other loans | C11: 0

Sheet Income Schedule
A1: Income Tax (AU)
A4: Year | B4: Gross Income | C4: Spouse Gross Income
A5: 2026 | B5: =(180000/12)*3 -> 45000 | C5: 166000
A6: =A5+1 -> 2027 | B6: 180000 | C6: 172000
A7: =A6+1 -> 2028 | B7: 180000 | C7: 172000
A8: =A7+1 -> 2029 | B8: 180000 | C8: 172000
A9: =A8+1 -> 2030 | B9: 180000 | C9: 172000
A10: =A9+1 -> 2031 | B10: 180000 | C10: 172000
A11: =A10+1 -> 2032 | B11: 180000 | C11: 172000
A12: =A11+1 -> 2033 | B12: 180000 | C12: 172000
A13: =A12+1 -> 2034 | B13: 180000 | C13: 172000
A14: =A13+1 -> 2035 | B14: 180000 | C14: 172000
A15: =A14+1 -> 2036 | B15: 180000 | C15: 172000
A16: =A15+1 -> 2037 | B16: 180000 | C16: 172000
A17: =A16+1 -> 2038 | B17: 180000 | C17: 172000
... A24: =A23+1 -> 2045 | B24: 180000 | C24: 172000

Sheet Income Tax (AU)
A1: Income Tax (AU)
A4: Bracket Lower | B4: Bracket Upper | C4: Marginal Rate | E4: You | H4: Spouse
A5: 0 | B5: 18200 | C5: 0
A6: 18200 | B6: 45000 | C6: 0.19 | E6: Gross Income | F6: =Projections!E6 -> 45000 | H6: Gross Income | I6: =Projections!F6 -> 166000
A7: 45000 | B7: 120000 | C7: 0.325 | E7: Taxable Income | F7: =F6 -> 45000 | H7: Taxable Income | I7: =I6 -> 166000
A8: 120000 | B8: 180000 | C8: 0.37 | E8: PAYG Tax | F8: =IF(F7<=18200,0, IF(F7<=45000,(F7-18200)*0.19, IF(F7<=120000,5092+(F7-45000)*0.325, IF(F7<=180000,29467+(F7-120000)*0.37, 51667+(F7-180000)*0.45)))) -> 5092 | H8: PAYG Tax | I8: =IF(I7<=18200,0, IF(I7<=45000,(I7-18200)*0.19, IF(I7<=120000,5092+(I7-45000)*0.325, IF(I7<=180000,29467+(I7-120000)*0.37, 51667+(I7-180000)*0.45)))) -> 46487
A9: 180000 | B9: 9999999 | C9: 0.45 | E9: Medicare Levy (2%) | F9: =F7*0.02 -> 900 | H9: Medicare Levy (2%) | I9: =-I7*0.02 -> -3320
E10: Total Tax | F10: =F8+F9 -> 5992 | H10: Total Tax | I10: =I8+I9 -> 43167
E11: Net Income | F11: =F7-F10 -> 39008 | H11: Net Income | I11: =I7-I10 -> 122833

Sheet Superannuation (Inputs)
A1: Superannuation (Inputs)
A3: Enter super balances and annual contributions.
A5: Person | B5: Opening Balance | C5: Annual Contribution | D5: Notes | E5: SG% (Employer) | F5: Salary Sacrifice (Annual) | G5: Concessional Cap | H5: Contribution Tax Rate | I5: Contribution Type | J5: Gross Concessional Contribution (Modelled) | K5: Contribution Tax (15%) | M5: Totals
A6: Brett | B6: 636000 | C6: 27500 | D6: 46023 | E6: 0.12 | F6: 0 | G6: 27500 | H6: 0.15 | I6: SG+SS | J6: =IF($I6="Fixed", $C6, MIN($G6, ($E6*Projections!$E6) + $F6) ) -> 5400 | K6: =$J6*$H6 -> 810 | M6: Total Super | N6: =SUM(B6:B7) -> 1088000
A7: Laura | B7: 452000 | C7: 27500 | D7: 46023 | E7: 0.154 | F7: 0 | G7: 27500 | H7: 0.15 | I7: SG+SS | J7: =IF($I7="Fixed", $C7, MIN($G7, ($E7*Projections!$F6) + $F7) ) -> 25564 | K7: =$J7*$H7 -> 3834.6 | M7: Total Contrib | N7: =SUM(C6:C7) -> 55000

Sheet Properties
A1: Property Portfolio (PPOR + Investment Properties)
A3: Enter PPOR and 3+ IPs. Acquire Age supports planning future purchases.
A5: Property | B5: Type | C5: Value | D5: Loan Balance | E5: Rate | F5: IO End Age | H5: Annual Rent | I5: Acquire Age | J5: Notes | L5: Portfolio Totals
A6: PPOR - Arnold St Parkside | B6: Home | C6: 2040000 | D6: 732934.8 | E6: 0.0544 | H6: 0 | I6: 42 | J6: Home | L6: Total Property Value | M6: =SUM(C6:C9) -> 4140000
A7: ='Property Expenses (Detail)'!A7 -> IP1 - Albany St Crows Nest | B7: Investment | C7: 850000 | D7: 473993.29 | E7: 0.0579 | F7: 52 | H7: =820*52 -> 42640 | I7: 38 | J7: Existing IO | L7: Total Loans | M7: =SUM(D6:D9) -> 2456928.1
A8: IP2 | B8: Investment | C8: 600000 | D8: 600000 | E8: 0.0579 | F8: 57 | H8: =550*52 -> 28600 | I8: 49 | J8: Future buy | L8: Property Equity | M8: =M6-M7 -> 1683071.9
A9: IP3 | B9: Investment | C9: 650000 | D9: 650000 | E9: 0.0579 | F9: 59 | H9: =575*52 -> 29900 | I9: 54 | J9: Future buy
A11: Capital Works Fund Plan
A12: 29 Albany Street
A13: Crows Nest NSW 2065
A14: Strata Plan 90614
A16: PlanOffsetYears = 1
C20: 2025 | D20: 2026 | E20: 2027 | F20: 2028 | G20: 2029 | H20: 2030 | I20: 2031 | J20: 2032 | K20: 2033 | L20: 2034 | M20: 2035 | N20: 2036 | O20: 2037 | P20: 2038 | Q20: 2039
A21: Description | B21: Unit Entitlement | C21: Yr 1 | D21: Yr 2 | E21: Yr 3 | F21: Yr 4 | G21: Yr 5 | H21: Yr 6 | I21: Yr 7 | J21: Yr 8 | K21: Yr 9 | L21: Yr 10 | M21: Yr 11 | N21: Yr 12 | O21: Yr 13 | P21: Yr 14 | Q21: Yr 15
A22: Body Corporate Capital Works | B22: 7 | C22: =110*$B$22 -> 770 | D22: =180.4*$B$22 -> 1262.8 | E22: =270.6*$B$22 -> 1894.2 | F22: =281.42*$B$22 -> 1969.94 | G22: =292.68*$B$22 -> 2048.76 | H22: =304.39*$B$22 -> 2130.73 | I22: =441.36*$B$22 -> 3089.52 | J22: =459.02*$B$22 -> 3213.14 | K22: =477.38*$B$22 -> 3341.66 | L22: =496.47*$B$22 -> 3475.29 | M22: =516.33*$B$22 -> 3614.31 | N22: =536.99*$B$22 -> 3758.93 | O22: =558.46*$B$22 -> 3909.22 | P22: =580.8*$B$22 -> 4065.6 | Q22: =604.04*$B$22 -> 4228.28
A23: Because Yr 1 in your model = Plan Year 2 (the plan is already a year old), we just need to:
A24: map each model year column to the correct plan-year index
A25: pull the plan value while it exists
A26: after the plan runs out, inflate from the last available plan year using Scenario inflation

Sheet WC Levy Table
D4: 15 Year Levy Table
F5: Unit Entitlement
D6: Lot 4 29 103 Albany St, Crows Nest | F6: 7
B8: Year | C8: Year To Total | D8: Total Contribution | F8: Contribution per Unit Entitlement | H8: Quarterly Contribution | K8: Annual CW
B9: dd/mm/yyyy | C9: dd/mm/yyyy | D9: Including GST | E9: GST Component | F9: Including GST | G9: GST Component | H9: Including GST | I9: GST Component
B10: 1 | C10: 31/05/2025 | D10: 11000 | E10: =D10/11 -> 1000 | F10: =D10/100 -> 110 | G10: =F10/11 -> 10 | H10: =F10/4 -> 27.5 | I10: =H10/11 -> 2.5 | K10: =($F$6/100)*D10 -> 770
B11: 2 | C11: 31/05/2026 | D11: 18040 | E11: =D11/11 -> 1640 | F11: =D11/100 -> 180.4 | G11: =F11/11 -> 16.4 | H11: =F11/4 -> 45.1 | I11: =H11/11 -> 4.1 | K11: =($F$6/100)*D11 -> 1262.8
B12: 3 | C12: 31/05/2027 | D12: 27060 | E12: =D12/11 -> 2460 | F12: =D12/100 -> 270.6 | G12: =F12/11 -> 24.6 | H12: =F12/4 -> 67.65 | I12: =H12/11 -> 6.15 | K12: =($F$6/100)*D12 -> 1894.2
B13: 4 | C13: 31/05/2028 | D13: 28142.4 | E13: =D13/11 -> 2558.4 | F13: =D13/100 -> 281.424 | G13: =F13/11 -> 25.584 | H13: =F13/4 -> 70.356 | I13: =H13/11 -> 6.396 | K13: =($F$6/100)*D13 -> 1969.968
B14: 5 | C14: 31/05/2029 | D14: 29268.1 | E14: =D14/11 -> 2660.7364 | F14: =D14/100 -> 292.681 | G14: =F14/11 -> 26.607364 | H14: =F14/4 -> 73.17025 | I14: =H14/11 -> 6.6518409 | K14: =($F$6/100)*D14 -> 2048.767
B15: 6 | C15: 31/05/2030 | D15: 30438.82 | E15: =D15/11 -> 2767.1655 | F15: =D15/100 -> 304.3882 | G15: =F15/11 -> 27.671655 | H15: =F15/4 -> 76.09705 | I15: =H15/11 -> 6.9179136 | K15: =($F$6/100)*D15 -> 2130.7174
B16: 7 | C16: 31/05/2031 | D16: 44136.28 | E16: =D16/11 -> 4012.3891 | F16: =D16/100 -> 441.3628 | G16: =F16/11 -> 40.123891 | H16: =F16/4 -> 110.3407 | I16: =H16/11 -> 10.030973 | K16: =($F$6/100)*D16 -> 3089.5396
B17: 8 | C17: 31/05/2032 | D17: 45901.74 | E17: =D17/11 -> 4172.8855 | F17: =D17/100 -> 459.0174 | G17: =F17/11 -> 41.728855 | H17: =F17/4 -> 114.75435 | I17: =H17/11 -> 10.432214 | K17: =($F$6/100)*D17 -> 3213.1218
B18: 9 | C18: 31/05/2033 | D18: 47737.8 | E18: =D18/11 -> 4339.8 | F18: =D18/100 -> 477.378 | G18: =F18/11 -> 43.398 | H18: =F18/4 -> 119.3445 | I18: =H18/11 -> 10.8495 | K18: =($F$6/100)*D18 -> 3341.646
B19: 10 | C19: 31/05/2034 | D19: 49647.31 | E19: =D19/11 -> 4513.3918 | F19: =D19/100 -> 496.4731 | G19: =F19/11 -> 45.133918 | H19: =F19/4 -> 124.11827 | I19: =H19/11 -> 11.28348 | K19: =($F$6/100)*D19 -> 3475.3117
B20: 11 | C20: 31/05/2035 | D20: 51633.21 | E20: =D20/11 -> 4693.9282 | F20: =D20/100 -> 516.3321 | G20: =F20/11 -> 46.939282 | H20: =F20/4 -> 129.08302 | I20: =H20/11 -> 11.73482 | K20: =($F$6/100)*D20 -> 3614.3247
B21: 12 | C21: 31/05/2036 | D21: 53698.54 | E21: =D21/11 -> 4881.6855 | F21: =D21/100 -> 536.9854 | G21: =F21/11 -> 48.816855 | H21: =F21/4 -> 134.24635 | I21: =H21/11 -> 12.204214 | K21: =($F$6/100)*D21 -> 3758.8978
... B24: 15 | C24: 31/05/2039 | D24: 60403.54 | E24: =D24/11 -> 5491.2309 | F24: =D24/100 -> 604.0354 | G24: =F24/11 -> 54.912309 | H24: =F24/4 -> 151.00885 | I24: =H24/11 -> 13.728077 | K24: =($F$6/100)*D24 -> 4228.2478

Sheet Property_CF
A1: Property Portfolio (PPOR + Investment Properties)
A3: Enter PPOR and 3+ IPs. Acquire Age supports planning future purchases. Cashflow & Tax.
B4: Input | C4: 2026 | D4: 2027 | E4: 2028 | F4: 2029 | G4: 2030 | H4: 2031 | I4: 2032 | J4: 2033 | K4: 2034 | L4: 2035 | M4: 2036 | N4: 2037 | O4: 2038 | P4: 2039 | Q4: 2040 | R4: 2041 | S4: 2042 | T4: 2043
A5: Description / Years | C5: 1 | D5: 2 | E5: 3 | F5: 4 | G5: 5 | H5: 6 | I5: 7 | J5: 8 | K5: 9 | L5: 10 | M5: 11 | N5: 12 | O5: 13 | P5: 14 | Q5: 15 | R5: 16 | S5: 17 | T5: 18 | U5: 19 | V5: 20 | W5: 21 | X5: 22 | Y5: 23 | Z5: 24 | AA5: 25 | AB5: 26 | AC5: 27 | AD5: 28 | AE5: 29 | AF5: 30 | AG5: 31 | AH5: 32 | AI5: 33 | AJ5: 34 | AK5: 35 | AL5: 36 | AM5: 37 | AN5: 38 | AO5: 39 | AP5: 40 | AQ5: 41 | AR5: 42 | AS5: 43 | AT5: 44 | AU5: 45 | AV5: 46 | AW5: 47 | AX5: 48 | AY5: 49 | AZ5: 50
A6: =Properties!A6 -> PPOR - Arnold St Parkside
A8: INCOME
A9: 1. Gross Rent | B9: 0 | C9: 0 | D9: =C9 * (1 + Scenarios!$K$13) -> 0 | E9: =D9 * (1 + Scenarios!$K$13) -> 0 | F9: =E9 * (1 + Scenarios!$K$13) -> 0 | G9: =F9 * (1 + Scenarios!$K$13) -> 0 | H9: =G9 * (1 + Scenarios!$K$13) -> 0 | I9: =H9 * (1 + Scenarios!$K$13) -> 0 | J9: =I9 * (1 + Scenarios!$K$13) -> 0 | K9: =J9 * (1 + Scenarios!$K$13) -> 0 | ... AZ9: =AY9 * (1 + Scenarios!$K$13) -> 0
A10: PROPERTY EXPENSES (Statutory & Fixed): Council rates, land tax, water charges, body corporate fees, and insurance (building, contents, landlord).
A11: 2. Council Rates | B11: =2700.5*1+Scenarios!$K$10 -> 2700.525 | C11: =2700.5*1+Scenarios!$K$10 -> 2700.525 | D11: =C11 * (1 + Scenarios!$K$10) -> 2768.0381 | E11: =D11 * (1 + Scenarios!$K$10) -> 2837.2391 | F11: =E11 * (1 + Scenarios!$K$10) -> 2908.1701 | G11: =F11 * (1 + Scenarios!$K$10) -> 2980.8743 | H11: =G11 * (1 + Scenarios!$K$10) -> 3055.3962 | I11: =H11 * (1 + Scenarios!$K$10) -> 3131.7811 | J11: =I11 * (1 + Scenarios!$K$10) -> 3210.0756 | K11: =J11 * (1 + Scenarios!$K$10) -> 3290.3275 | ... AZ11: =AY11 * (1 + Scenarios!$K$10) -> 9055.6078
A12: 3. Water Charges | D12: =C12* (1 + Scenarios!$K$10) -> 0 | E12: =D12* (1 + Scenarios!$K$10) -> 0 | F12: =E12* (1 + Scenarios!$K$10) -> 0 | G12: =F12* (1 + Scenarios!$K$10) -> 0 | H12: =G12* (1 + Scenarios!$K$10) -> 0 | I12: =H12* (1 + Scenarios!$K$10) -> 0 | J12: =I12* (1 + Scenarios!$K$10) -> 0 | K12: =J12* (1 + Scenarios!$K$10) -> 0 | ... AZ12: =AY12* (1 + Scenarios!$K$10) -> 0
A13: 4. Body Corporate - Administrative | B13: 0 | C13: 0 | D13: =C13* (1 + Scenarios!$K$10) -> 0 | E13: =D13* (1 + Scenarios!$K$10) -> 0 | F13: =E13* (1 + Scenarios!$K$10) -> 0 | G13: =F13* (1 + Scenarios!$K$10) -> 0 | H13: =G13* (1 + Scenarios!$K$10) -> 0 | I13: =H13* (1 + Scenarios!$K$10) -> 0 | J13: =I13* (1 + Scenarios!$K$10) -> 0 | K13: =J13* (1 + Scenarios!$K$10) -> 0 | ... AZ13: =AY13* (1 + Scenarios!$K$10) -> 0
A14: 5. Body Corporate - Capital Works | B14: 0 | C14: 0 | D14: 0 | E14: 0 | F14: 0 | G14: 0 | H14: 0 | I14: 0 | J14: 0 | K14: 0 | L14: 0 | M14: 0 | N14: 0 | O14: 0 | P14: 0 | Q14: 0 | R14: 0 | S14: 0 | T14: 0 | U14: 0 | V14: 0 | W14: 0 | X14: 0 | Y14: 0 | Z14: 0 | AA14: 0 | AB14: 0 | AC14: 0 | AD14: 0 | AE14: 0 | AF14: 0 | AG14: 0 | AH14: 0 | AI14: 0 | AJ14: 0 | AK14: 0 | AL14: 0 | AM14: 0 | AN14: 0 | AO14: 0 | AP14: 0 | AQ14: 0 | AR14: 0 | AS14: 0 | AT14: 0 | AU14: 0 | AV14: 0 | AW14: 0 | AX14: 0 | AY14: 0 | AZ14: 0
A15: 6. Insurance - Building [N/A IP1 - Included in Body Corporate Administrative budget] | B15: 0 | C15: 0 | D15: =C15* (1 + Scenarios!$K$10) -> 0 | E15: =D15* (1 + Scenarios!$K$10) -> 0 | F15: =E15* (1 + Scenarios!$K$10) -> 0 | G15: =F15* (1 + Scenarios!$K$10) -> 0 | H15: =G15* (1 + Scenarios!$K$10) -> 0 | I15: =H15* (1 + Scenarios!$K$10) -> 0 | J15: =I15* (1 + Scenarios!$K$10) -> 0 | K15: =J15* (1 + Scenarios!$K$10) -> 0 | ... AZ15: =AY15* (1 + Scenarios!$K$10) -> 0
A16: 7. Insurance - Contents [N/A; assumption continuously tennated] | B16: 0 | C16: 0 | D16: =C16* (1 + Scenarios!$K$10) -> 0 | E16: =D16* (1 + Scenarios!$K$10) -> 0 | F16: =E16* (1 + Scenarios!$K$10) -> 0 | G16: =F16* (1 + Scenarios!$K$10) -> 0 | H16: =G16* (1 + Scenarios!$K$10) -> 0 | I16: =H16* (1 + Scenarios!$K$10) -> 0 | J16: =I16* (1 + Scenarios!$K$10) -> 0 | K16: =J16* (1 + Scenarios!$K$10) -> 0 | ... AZ16: =AY16* (1 + Scenarios!$K$10) -> 0
A17: 8. Insurance - Landlord | B17: 700 | C17: =B17 -> 700 | D17: =C17* (1 + Scenarios!$K$10) -> 717.5 | E17: =D17* (1 + Scenarios!$K$10) -> 735.4375 | F17: =E17* (1 + Scenarios!$K$10) -> 753.82344 | G17: =F17* (1 + Scenarios!$K$10) -> 772.66902 | H17: =G17* (1 + Scenarios!$K$10) -> 791.98575 | I17: =H17* (1 + Scenarios!$K$10) -> 811.78539 | J17: =I17* (1 + Scenarios!$K$10) -> 832.08003 | K17: =J17* (1 + Scenarios!$K$10) -> 852.88203 | ... AZ17: =AY17* (1 + Scenarios!$K$10) -> 2347.2938
A18: MANAGEMENT & MAINTENANCE: Real estate agent fees/commissions, cleaning, gardening, lawn mowing, and pest control.
A19: 9. RE Property Management Fees % (assumption row) | B19: 0.066 | C19: 0.066 | D19: =C19 -> 0.066 | E19: =D19 -> 0.066 | F19: =E19 -> 0.066 | G19: =F19 -> 0.066 | H19: =G19 -> 0.066 | I19: =H19 -> 0.066 | J19: =I19 -> 0.066 | K19: =J19 -> 0.066 | ... AZ19: =AY19 -> 0.066
A20: 10. RE Property Management Fees | B20: =B9*B19 -> 0 | C20: =C9*C19 -> 0 | D20: =D9*D19 -> 0 | E20: =E9*E19 -> 0 | F20: =F9*F19 -> 0 | G20: =G9*G19 -> 0 | H20: =H9*H19 -> 0 | I20: =I9*I19 -> 0 | J20: =J9*J19 -> 0 | K20: ='Property Expenses (Detail)'!$C$7*Property_CF!K9 -> 0 | L20: ='Property Expenses (Detail)'!$C$7*Property_CF!L9 -> 0 | M20: ='Property Expenses (Detail)'!$C$7*Property_CF!M9 -> 0 | N20: ='Property Expenses (Detail)'!$C$7*Property_CF!N9 -> 0 | O20: ='Property Expenses (Detail)'!$C$7*Property_CF!O9 -> 0 | P20: ='Property Expenses (Detail)'!$C$7*Property_CF!P9 -> 0 | Q20: ='Property Expenses (Detail)'!$C$7*Property_CF!Q9 -> 0 | R20: ='Property Expenses (Detail)'!$C$7*Property_CF!R9 -> 0 | ... AZ20: ='Property Expenses (Detail)'!$C$7*Property_CF!AZ9 -> 0
A21: 11. Cleaning | D21: =C21* (1 + Scenarios!$K$10) -> 0 | E21: =D21* (1 + Scenarios!$K$10) -> 0 | F21: =E21* (1 + Scenarios!$K$10) -> 0 | G21: =F21* (1 + Scenarios!$K$10) -> 0 | H21: =G21* (1 + Scenarios!$K$10) -> 0 | I21: =H21* (1 + Scenarios!$K$10) -> 0 | J21: =I21* (1 + Scenarios!$K$10) -> 0 | K21: =J21* (1 + Scenarios!$K$10) -> 0 | ... AZ21: =AY21* (1 + Scenarios!$K$10) -> 0
A22: 12. Gardening [N/A IP1] | B22: 0 | C22: 0 | D22: =C22* (1 + Scenarios!$K$10) -> 0 | E22: =D22* (1 + Scenarios!$K$10) -> 0 | F22: =E22* (1 + Scenarios!$K$10) -> 0 | G22: =F22* (1 + Scenarios!$K$10) -> 0 | H22: =G22* (1 + Scenarios!$K$10) -> 0 | I22: =H22* (1 + Scenarios!$K$10) -> 0 | J22: =I22* (1 + Scenarios!$K$10) -> 0 | K22: =J22* (1 + Scenarios!$K$10) -> 0 | ... AZ22: =AY22* (1 + Scenarios!$K$10) -> 0
A23: 13. Lawn Mowing [N/A IP1] | B23: 0 | C23: 0 | D23: =C23* (1 + Scenarios!$K$10) -> 0 | E23: =D23* (1 + Scenarios!$K$10) -> 0 | F23: =E23* (1 + Scenarios!$K$10) -> 0 | G23: =F23* (1 + Scenarios!$K$10) -> 0 | H23: =G23* (1 + Scenarios!$K$10) -> 0 | I23: =H23* (1 + Scenarios!$K$10) -> 0 | J23: =I23* (1 + Scenarios!$K$10) -> 0 | K23: =J23* (1 + Scenarios!$K$10) -> 0 | ... AZ23: =AY23* (1 + Scenarios!$K$10) -> 0
A24: 14. Pest Control [N/A IP1] | B24: 0 | C24: 0 | D24: =C24* (1 + Scenarios!$K$10) -> 0 | E24: =D24* (1 + Scenarios!$K$10) -> 0 | F24: =E24* (1 + Scenarios!$K$10) -> 0 | G24: =F24* (1 + Scenarios!$K$10) -> 0 | H24: =G24* (1 + Scenarios!$K$10) -> 0 | I24: =H24* (1 + Scenarios!$K$10) -> 0 | J24: =I24* (1 + Scenarios!$K$10) -> 0 | K24: =J24* (1 + Scenarios!$K$10) -> 0 | ... AZ24: =AY24* (1 + Scenarios!$K$10) -> 0
A25: FINANCIAL & LEGAL: Interest on loans, bank charges, and legal expenses for tenant issues.
A26: 15. Interest Expense | B26: =Loan_IO_to_PI!M26 -> 27444.211 | C26: =Loan_IO_to_PI!N26 -> 27444.211 | D26: =Loan_IO_to_PI!O26 -> 27444.211 | E26: =Loan_IO_to_PI!P26 -> 27444.211 | F26: =Loan_IO_to_PI!Q26 -> 27444.211 | G26: =Loan_IO_to_PI!R26 -> 27444.211 | H26: =Loan_IO_to_PI!S26 -> 25341.452 | I26: =Loan_IO_to_PI!T26 -> 23116.944 | ... Z26: =Loan_IO_to_PI!AK26 -> 0 | AA26: 0 | AB26: 0 | AC26: 0 | AD26: 0 | AE26: 0 | AF26: 0 | AG26: 0 | AH26: 0 | AI26: 0 | AJ26: 0 | AK26: 0 | AL26: 0 | AM26: 0 | AN26: 0 | AO26: 0 | AP26: 0 | AQ26: 0 | AR26: 0 | AS26: 0 | AT26: 0 | AU26: 0 | AV26: 0 | AW26: 0 | AX26: 0 | AY26: 0 | AZ26: 0
A27: 16. Principle Repayment (cash non-deductible) | B27: =Loan_IO_to_PI!M28 -> 0 | C27: =Loan_IO_to_PI!N28 -> 0 | D27: =Loan_IO_to_PI!O28 -> 0 | E27: =Loan_IO_to_PI!P28 -> 0 | F27: =Loan_IO_to_PI!Q28 -> 0 | G27: =Loan_IO_to_PI!R28 -> 36317.082 | H27: =Loan_IO_to_PI!S28 -> 38419.841 | I27: =Loan_IO_to_PI!T28 -> 40644.35 | ... Z27: =Loan_IO_to_PI!AK28 -> 0 | AA27: 0 | AB27: 0 | AC27: 0 | AD27: 0 | AE27: 0 | AF27: 0 | AG27: 0 | AH27: 0 | AI27: 0 | AJ27: 0 | AK27: 0 | AL27: 0 | AM27: 0 | AN27: 0 | AO27: 0 | AP27: 0 | AQ27: 0 | AR27: 0 | AS27: 0 | AT27: 0 | AU27: 0 | AV27: 0 | AW27: 0 | AX27: 0 | AY27: 0 | AZ27: 0
A28: 17. Bank Charges | B28: =IF( AND( Loan_IO_to_PI!M$24="P&I", Loan_IO_to_PI!L$24="IO", Loan_IO_to_PI!M$28>0 ), Loan_IO_to_PI!$B$8, 0 ) -> 0 | C28: =IF( AND( Loan_IO_to_PI!N$24="P&I", Loan_IO_to_PI!M$24="IO", Loan_IO_to_PI!N$28>0 ), Loan_IO_to_PI!$B$8, 0 ) -> 0 | D28: =IF( AND( Loan_IO_to_PI!O$24="P&I", Loan_IO_to_PI!N$24="IO", Loan_IO_to_PI!O$28>0 ), Loan_IO_to_PI!$B$8, 0 ) -> 0 | E28: =IF( AND( Loan_IO_to_PI!P$24="P&I", Loan_IO_to_PI!O$24="IO", Loan_IO_to_PI!P$28>0 ), Loan_IO_to_PI!$B$8, 0 ) -> 0 | F28: =IF( AND( Loan_IO_to_PI!Q$24="P&I", Loan_IO_to_PI!P$24="IO", Loan_IO_to_PI!Q$28>0 ), Loan_IO_to_PI!$B$8, 0 ) -> 0 | G28: =IF( AND( Loan_IO_to_PI!R$24="P&I", Loan_IO_to_PI!Q$24="IO", Loan_IO_to_PI!R$28>0 ), Loan_IO_to_PI!$B$8, 0 ) -> 650 | H28: =IF( AND( Loan_IO_to_PI!S$24="P&I", Loan_IO_to_PI!R$24="IO", Loan_IO_to_PI!S$28>0 ), Loan_IO_to_PI!$B$8, 0 ) -> 0 | I28: =IF( AND( Loan_IO_to_PI!T$24="P&I", Loan_IO_to_PI!S$24="IO", Loan_IO_to_PI!T$28>0 ), Loan_IO_to_PI!$B$8, 0 ) -> 0 | ... AZ28: =IF( AND( Loan_IO_to_PI!BK$24="P&I", Loan_IO_to_PI!BJ$24="IO", Loan_IO_to_PI!BK$28>0 ), Loan_IO_to_PI!$B$8, 0 ) -> 0
A29: 18. Legal Expenses | B29: =0 -> 0 | C29: =0 -> 0 | D29: =C29* (1 + Scenarios!$K$10) -> 0 | E29: =D29* (1 + Scenarios!$K$10) -> 0 | F29: =E29* (1 + Scenarios!$K$10) -> 0 | G29: =F29* (1 + Scenarios!$K$10) -> 0 | H29: =G29* (1 + Scenarios!$K$10) -> 0 | I29: =H29* (1 + Scenarios!$K$10) -> 0 | J29: =I29* (1 + Scenarios!$K$10) -> 0 | K29: =J29* (1 + Scenarios!$K$10) -> 0 | ... AZ29: =AY29* (1 + Scenarios!$K$10) -> 0
A30: OPERATIONAL: Advertising for tenants, stationery, postage, phone calls, and, in some cases, travel expenses (though travel to inspect residential property is generally not deductible).
A31: 19. Advertising for tenants | B31: =IF( MOD(B5-1, Assumptions!$B$57)=0, Assumptions!$B$54+Assumptions!$B$55, 0 ) -> 0 | C31: =IF( MOD(C5-1, Assumptions!$B$57)=0, Assumptions!$B$54+Assumptions!$B$55, 0 ) -> 1462 | D31: =IF( MOD(D5-1, Assumptions!$B$57)=0, Assumptions!$B$54+Assumptions!$B$55, 0 ) -> 0 | E31: =IF( MOD(E5-1, Assumptions!$B$57)=0, Assumptions!$B$54+Assumptions!$B$55, 0 ) -> 0 | F31: =IF( MOD(F5-1, Assumptions!$B$57)=0, Assumptions!$B$54+Assumptions!$B$55, 0 ) -> 0 | G31: =IF( MOD(G5-1, Assumptions!$B$57)=0, Assumptions!$B$54+Assumptions!$B$55, 0 ) -> 1462 | H31: =IF( MOD(H5-1, Assumptions!$B$57)=0, Assumptions!$B$54+Assumptions!$B$55, 0 ) -> 0 | I31: =IF( MOD(I5-1, Assumptions!$B$57)=0, Assumptions!$B$54+Assumptions!$B$55, 0 ) -> 0 | ... AZ31: =IF( MOD(AZ5-1, Assumptions!$B$57)=0, Assumptions!$B$54+Assumptions!$B$55, 0 ) -> 0
A32: 20. Stationery | B32: =0 -> 0 | C32: =0 -> 0 | D32: =C32* (1 + Scenarios!$K$10) -> 0 | E32: =D32* (1 + Scenarios!$K$10) -> 0 | F32: =E32* (1 + Scenarios!$K$10) -> 0 | G32: =F32* (1 + Scenarios!$K$10) -> 0 | H32: =G32* (1 + Scenarios!$K$10) -> 0 | I32: =H32* (1 + Scenarios!$K$10) -> 0 | J32: =I32* (1 + Scenarios!$K$10) -> 0 | K32: =J32* (1 + Scenarios!$K$10) -> 0 | ... AZ32: =AY32* (1 + Scenarios!$K$10) -> 0
A33: 21. Postage | B33: =0 -> 0 | C33: =0 -> 0 | D33: =C33* (1 + Scenarios!$K$10) -> 0 | E33: =D33* (1 + Scenarios!$K$10) -> 0 | F33: =E33* (1 + Scenarios!$K$10) -> 0 | G33: =F33* (1 + Scenarios!$K$10) -> 0 | H33: =G33* (1 + Scenarios!$K$10) -> 0 | I33: =H33* (1 + Scenarios!$K$10) -> 0 | J33: =I33* (1 + Scenarios!$K$10) -> 0 | K33: =J33* (1 + Scenarios!$K$10) -> 0 | ... AZ33: =AY33* (1 + Scenarios!$K$10) -> 0
A34: 22. Phone Calls | B34: =0 -> 0 | C34: =0 -> 0 | D34: =C34* (1 + Scenarios!$K$10) -> 0 | E34: =D34* (1 + Scenarios!$K$10) -> 0 | F34: =E34* (1 + Scenarios!$K$10) -> 0 | G34: =F34* (1 + Scenarios!$K$10) -> 0 | H34: =G34* (1 + Scenarios!$K$10) -> 0 | I34: =H34* (1 + Scenarios!$K$10) -> 0 | J34: =I34* (1 + Scenarios!$K$10) -> 0 | K34: =J34* (1 + Scenarios!$K$10) -> 0 | ... AZ34: =AY34* (1 + Scenarios!$K$10) -> 0
A35: 23. Travel Expenses [Travel to inspect residential property is generally not deductible.] | B35: =0 -> 0 | C35: =0 -> 0 | D35: =C35* (1 + Scenarios!$K$10) -> 0 | E35: =D35* (1 + Scenarios!$K$10) -> 0 | F35: =E35* (1 + Scenarios!$K$10) -> 0 | G35: =F35* (1 + Scenarios!$K$10) -> 0 | H35: =G35* (1 + Scenarios!$K$10) -> 0 | I35: =H35* (1 + Scenarios!$K$10) -> 0 | J35: =I35* (1 + Scenarios!$K$10) -> 0 | K35: =J35* (1 + Scenarios!$K$10) -> 0 | ... AZ35: =AY35* (1 + Scenarios!$K$10) -> 0
A36: REPAIRS: Costs to fix damage or deterioration (e.g., repairing a broken fence, fixing a leaking tap).
A37: 24. Repairs & Maintenance | D37: =C37* (1 + Scenarios!$K$10) -> 0 | E37: =D37* (1 + Scenarios!$K$10) -> 0 | F37: =E37* (1 + Scenarios!$K$10) -> 0 | G37: =F37* (1 + Scenarios!$K$10) -> 0 | H37: =G37* (1 + Scenarios!$K$10) -> 0 | I37: =H37* (1 + Scenarios!$K$10) -> 0 | J37: =I37* (1 + Scenarios!$K$10) -> 0 | K37: =J37* (1 + Scenarios!$K$10) -> 0 | ... AZ37: =AY37* (1 + Scenarios!$K$10) -> 0
A38: DEDUCTIONS CLAIMED OVER SEVERAL YEARS:
A39: 25. Depreciation (Decline in Value) - Plant & Equipment: For plant and equipment (e.g., blinds, carpets, appliances) costing over $300 Second-hand assets purchased after 9 May 2017 are not deductible. (Zero if post-2017 second-hand assets.) | B39: =0 -> 0 | C39: =0 -> 0 | D39: =0 -> 0 | E39: =0 -> 0 | F39: =0 -> 0 | G39: =0 -> 0 | H39: =0 -> 0 | I39: =0 -> 0 | ... AZ39: =0 -> 0
A40: 26. Capital Works Deduction: Structural improvements, such as building renovations, extensions, or new fences, generally depreciated at 2.5% per year. | B40: =Assumptions!$B$69*Assumptions!$B$70 -> 5538.775 | C40: =Assumptions!$B$69*Assumptions!$B$70 -> 5538.775 | D40: =Assumptions!$B$69*Assumptions!$B$70 -> 5538.775 | E40: =Assumptions!$B$69*Assumptions!$B$70 -> 5538.775 | F40: =Assumptions!$B$69*Assumptions!$B$70 -> 5538.775 | G40: =Assumptions!$B$69*Assumptions!$B$70 -> 5538.775 | H40: =Assumptions!$B$69*Assumptions!$B$70 -> 5538.775 | I40: =Assumptions!$B$69*Assumptions!$B$70 -> 5538.775 | ... AZ40: =Assumptions!$B$69*Assumptions!$B$70 -> 5538.775
A41: 27. Borrowing Expenses Amortised: Fees for obtaining a loan (e.g., mortgage application fees, mortgage broker fees), generally spread over 5 years or the loan term. | B41: =Loan_IO_to_PI!M31 -> 0 | C41: =Loan_IO_to_PI!N31 -> 0 | D41: =Loan_IO_to_PI!O31 -> 0 | E41: =Loan_IO_to_PI!P31 -> 0 | F41: =Loan_IO_to_PI!Q31 -> 0 | G41: =Loan_IO_to_PI!R31 -> 0 | H41: =Loan_IO_to_PI!S31 -> 0 | I41: =Loan_IO_to_PI!T31 -> 0 | ... Z41: =Loan_IO_to_PI!AK31 -> 0 | AA41: 0 | AB41: 0 | AC41: 0 | AD41: 0 | AE41: 0 | AF41: 0 | AG41: 0 | AH41: 0 | AI41: 0 | AJ41: 0 | AK41: 0 | AL41: 0 | AM41: 0 | AN41: 0 | AO41: 0 | AP41: 0 | AQ41: 0 | AR41: 0 | AS41: 0 | AT41: 0 | AU41: 0 | AV41: 0 | AW41: 0 | AX41: 0 | AY41: 0 | AZ41: 0
A42: 28. Other Deductible Expenses | D42: =C42* (1 + Scenarios!$K$10) -> 0 | E42: =D42* (1 + Scenarios!$K$10) -> 0 | F42: =E42* (1 + Scenarios!$K$10) -> 0 | G42: =F42* (1 + Scenarios!$K$10) -> 0 | H42: =G42* (1 + Scenarios!$K$10) -> 0 | I42: =H42* (1 + Scenarios!$K$10) -> 0 | J42: =I42* (1 + Scenarios!$K$10) -> 0 | K42: =J42* (1 + Scenarios!$K$10) -> 0 | ... AZ42: =AY42* (1 + Scenarios!$K$10) -> 0
A43: TOTALS:
A44: 29. Total Deductible Expenses | C44: =SUM(C11,C12,C13,C14,C17,C20,C21,C22,C23,C24,C26,C28,C29,C31,C37,C39,C40,C41,C42) -> 37845.511
A45: 30. Net Rental Income / (Loss) | C45: =C9 - C44 -> -37845.511
A46: 31. Net Rental Cashflow (cash only) | C46: =C45 + C39 + C40 + C41 -> -32306.736
C49: 2026 | D49: 2027 | E49: 2028 | F49: 2029 | G49: 2030 | H49: 2031 | I49: 2032 | J49: 2033 | K49: 2034 | L49: 2035 | M49: 2036 | N49: 2037 | O49: 2038 | P49: 2039 | Q49: 2040 | R49: 2041 | S49: 2042 | T49: 2043
A50: Description / Years | C50: 1 | D50: 2 | E50: 3 | F50: 4 | G50: 5 | H50: 6 | I50: 7 | J50: 8 | K50: 9 | L50: 10 | M50: 11 | N50: 12 | O50: 13 | P50: 14 | Q50: 15 | R50: 16 | S50: 17 | T50: 18 | U50: 19 | V50: 20 | W50: 21 | X50: 22 | Y50: 23 | Z50: 24 | AA50: 25 | AB50: 26 | AC50: 27 | AD50: 28 | AE50: 29 | AF50: 30 | AG50: 31 | AH50: 32 | AI50: 33 | AJ50: 34 | AK50: 35 | AL50: 36 | AM50: 37 | AN50: 38 | AO50: 39 | AP50: 40 | AQ50: 41 | AR50: 42 | AS50: 43 | AT50: 44 | AU50: 45 | AV50: 46 | AW50: 47 | AX50: 48 | AY50: 49 | AZ50: 50
A51: =Properties!A7 -> IP1 - Albany St Crows Nest
A53: INCOME
A54: 1. Gross Rent | B54: =820*52 -> 42640 | C54: =B54 -> 42640 | D54: =C54 * (1 + Scenarios!$K$13) -> 43919.2 | E54: =D54 * (1 + Scenarios!$K$13) -> 45236.776 | F54: =E54 * (1 + Scenarios!$K$13) -> 46593.879 | G54: =F54 * (1 + Scenarios!$K$13) -> 47991.696 | H54: =G54 * (1 + Scenarios!$K$13) -> 49431.447 | I54: =H54 * (1 + Scenarios!$K$13) -> 50914.39 | J54: =I54 * (1 + Scenarios!$K$13) -> 52441.822 | K54: =J54 * (1 + Scenarios!$K$13) -> 54015.076 | ... AZ54: =AY54 * (1 + Scenarios!$K$13) -> 181485.2
A55: PROPERTY EXPENSES (Statutory & Fixed): Council rates, land tax, water charges, body corporate fees, and insurance (building, contents, landlord).
A56: 2. Council Rates | B56: 660 | C56: =B56+(B56*1+Scenarios!$K$10) -> 1320.025 | D56: =C56 * (1 + Scenarios!$K$10) -> 1353.0256 | E56: =D56 * (1 + Scenarios!$K$10) -> 1386.8513 | F56: =E56 * (1 + Scenarios!$K$10) -> 1421.5225 | G56: =F56 * (1 + Scenarios!$K$10) -> 1457.0606 | H56: =G56 * (1 + Scenarios!$K$10) -> 1493.4871 | I56: =H56 * (1 + Scenarios!$K$10) -> 1530.8243 | J56: =I56 * (1 + Scenarios!$K$10) -> 1569.0949 | K56: =J56 * (1 + Scenarios!$K$10) -> 1608.3223 | ... AZ56: =AY56 * (1 + Scenarios!$K$10) -> 4426.4092
A57: 3. Water Charges | B57: 750 | C57: =B57 -> 750 | D57: =C57* (1 + Scenarios!$K$10) -> 768.75 | E57: =D57* (1 + Scenarios!$K$10) -> 787.96875 | F57: =E57* (1 + Scenarios!$K$10) -> 807.66797 | G57: =F57* (1 + Scenarios!$K$10) -> 827.85967 | H57: =G57* (1 + Scenarios!$K$10) -> 848.55616 | I57: =H57* (1 + Scenarios!$K$10) -> 869.77006 | J57: =I57* (1 + Scenarios!$K$10) -> 891.51432 | K57: =J57* (1 + Scenarios!$K$10) -> 913.80217 | ... AZ57: =AY57* (1 + Scenarios!$K$10) -> 2514.9576
A58: 4. Body Corporate - Administrative | B58: 922.72 | C58: =B58*4 -> 3690.88 | D58: =C58* (1 + Scenarios!$K$10) -> 3783.152 | E58: =D58* (1 + Scenarios!$K$10) -> 3877.7308 | F58: =E58* (1 + Scenarios!$K$10) -> 3974.6741 | G58: =F58* (1 + Scenarios!$K$10) -> 4074.0409 | H58: =G58* (1 + Scenarios!$K$10) -> 4175.8919 | I58: =H58* (1 + Scenarios!$K$10) -> 4280.2892 | J58: =I58* (1 + Scenarios!$K$10) -> 4387.2965 | K58: =J58* (1 + Scenarios!$K$10) -> 4496.9789 | ... AZ58: =AY58* (1 + Scenarios!$K$10) -> 12376.542
A59: 5. Body Corporate - Capital Works | B59: =Properties!$C$22 -> 770 | C59: {=Properties!$D$22} -> 1262.8 | D59: {=Properties!$E$22} -> 1894.2 | E59: {=Properties!$F$22} -> 1969.94 | F59: {=Properties!$G$22} -> 2048.76 | G59: {=Properties!$H$22} -> 2130.73 | H59: {=Properties!$I$22} -> 3089.52 | I59: {=Properties!$J$22} -> 3213.14 | J59: {=Properties!$K$22} -> 3341.66 | K59: {=Properties!$L$22} -> 3475.29 | L59: {=Properties!$M$22} -> 3614.31 | M59: {=Properties!$N$22} -> 3758.93 | N59: {=Properties!$O$22} -> 3909.22 | O59: {=Properties!$P$22} -> 4065.6 | P59: {=Properties!$Q$22} -> 4228.28 | Q59: {=P59*(1+Scenarios!$K$10)} -> 4333.987 | R59: {=Q59*(1+Scenarios!$K$10)} -> 4442.3367 | S59: {=R59*(1+Scenarios!$K$10)} -> 4553.3951 | T59: {=S59*(1+Scenarios!$K$10)} -> 4667.23 | U59: {=T59*(1+Scenarios!$K$10)} -> 4783.9107 | V59: {=U59*(1+Scenarios!$K$10)} -> 4903.5085 | W59: {=V59*(1+Scenarios!$K$10)} -> 5026.0962 | X59: {=W59*(1+Scenarios!$K$10)} -> 5151.7486 | ... AZ59: {=AY59*(1+Scenarios!$K$10)} -> 10285.44
A60: 6. Insurance - Building [N/A IP1 - Included in Body Corporate Administrative budget] | C60: 0 | D60: =C60* (1 + Scenarios!$K$10) -> 0 | E60: =D60* (1 + Scenarios!$K$10) -> 0 | F60: =E60* (1 + Scenarios!$K$10) -> 0 | G60: =F60* (1 + Scenarios!$K$10) -> 0 | H60: =G60* (1 + Scenarios!$K$10) -> 0 | I60: =H60* (1 + Scenarios!$K$10) -> 0 | J60: =I60* (1 + Scenarios!$K$10) -> 0 | K60: =J60* (1 + Scenarios!$K$10) -> 0 | ... AZ60: =AY60* (1 + Scenarios!$K$10) -> 0
A61: 7. Insurance - Contents [N/A; assumption continuously tennated] | C61: 0 | D61: =C61* (1 + Scenarios!$K$10) -> 0 | E61: =D61* (1 + Scenarios!$K$10) -> 0 | F61: =E61* (1 + Scenarios!$K$10) -> 0 | G61: =F61* (1 + Scenarios!$K$10) -> 0 | H61: =G61* (1 + Scenarios!$K$10) -> 0 | I61: =H61* (1 + Scenarios!$K$10) -> 0 | J61: =I61* (1 + Scenarios!$K$10) -> 0 | K61: =J61* (1 + Scenarios!$K$10) -> 0 | ... AZ61: =AY61* (1 + Scenarios!$K$10) -> 0
A62: 8. Insurance - Landlord | B62: 700 | C62: =B62 -> 700 | D62: =C62* (1 + Scenarios!$K$10) -> 717.5 | E62: =D62* (1 + Scenarios!$K$10) -> 735.4375 | F62: =E62* (1 + Scenarios!$K$10) -> 753.82344 | G62: =F62* (1 + Scenarios!$K$10) -> 772.66902 | H62: =G62* (1 + Scenarios!$K$10) -> 791.98575 | I62: =H62* (1 + Scenarios!$K$10) -> 811.78539 | J62: =I62* (1 + Scenarios!$K$10) -> 832.08003 | K62: =J62* (1 + Scenarios!$K$10) -> 852.88203 | ... AZ62: =AY62* (1 + Scenarios!$K$10) -> 2347.2938
A63: MANAGEMENT & MAINTENANCE: Real estate agent fees/commissions, cleaning, gardening, lawn mowing, and pest control.
A64: 9. RE Property Management Fees % (assumption row) | B64: 0.066 | C64: =B64 -> 0.066 | D64: =C64 -> 0.066 | E64: =D64 -> 0.066 | F64: =E64 -> 0.066 | G64: =F64 -> 0.066 | H64: =G64 -> 0.066 | I64: =H64 -> 0.066 | J64: =I64 -> 0.066 | ... AZ64: =AY64 -> 0.066
A65: 10. RE Property Management Fees | B65: =B54*B64 -> 2814.24 | C65: =C54*C64 -> 2814.24 | D65: =D54*D64 -> 2898.6672 | E65: =E54*E64 -> 2985.6272 | F65: =F54*F64 -> 3075.196 | G65: =G54*G64 -> 3167.4519 | H65: =H54*H64 -> 3262.4755 | I65: =I54*I64 -> 3360.3497 | J65: =J54*J64 -> 3461.1602 | K65: ='Property Expenses (Detail)'!$C$7*Property_CF!K54 -> 3564.6657 | L65: ='Property Expenses (Detail)'!$C$7*Property_CF!L54 -> 3671.6056 | M65: ='Property Expenses (Detail)'!$C$7*Property_CF!M54 -> 3781.7538 | N65: ='Property Expenses (Detail)'!$C$7*Property_CF!N54 -> 3895.2064 | O65: ='Property Expenses (Detail)'!$C$7*Property_CF!O54 -> 4012.0626 | P65: ='Property Expenses (Detail)'!$C$7*Property_CF!P54 -> 4132.4245 | Q65: ='Property Expenses (Detail)'!$C$7*Property_CF!Q54 -> 4256.3972 | R65: ='Property Expenses (Detail)'!$C$7*Property_CF!R54 -> 4384.0892 | ... AZ65: ='Property Expenses (Detail)'!$C$7*Property_CF!AZ54 -> 11976.916
A66: 11. Cleaning | D66: =C66* (1 + Scenarios!$K$10) -> 0 | E66: =D66* (1 + Scenarios!$K$10) -> 0 | F66: =E66* (1 + Scenarios!$K$10) -> 0 | G66: =F66* (1 + Scenarios!$K$10) -> 0 | H66: =G66* (1 + Scenarios!$K$10) -> 0 | I66: =H66* (1 + Scenarios!$K$10) -> 0 | J66: =I66* (1 + Scenarios!$K$10) -> 0 | K66: =J66* (1 + Scenarios!$K$10) -> 0 | ... AZ66: =AY66* (1 + Scenarios!$K$10) -> 0
A67: 12. Gardening [N/A IP1] | C67: 0 | D67: =C67* (1 + Scenarios!$K$10) -> 0 | E67: =D67* (1 + Scenarios!$K$10) -> 0 | F67: =E67* (1 + Scenarios!$K$10) -> 0 | G67: =F67* (1 + Scenarios!$K$10) -> 0 | H67: =G67* (1 + Scenarios!$K$10) -> 0 | I67: =H67* (1 + Scenarios!$K$10) -> 0 | J67: =I67* (1 + Scenarios!$K$10) -> 0 | K67: =J67* (1 + Scenarios!$K$10) -> 0 | ... AZ67: =AY67* (1 + Scenarios!$K$10) -> 0
A68: 13. Lawn Mowing [N/A IP1] | C68: 0 | D68: =C68* (1 + Scenarios!$K$10) -> 0 | E68: =D68* (1 + Scenarios!$K$10) -> 0 | F68: =E68* (1 + Scenarios!$K$10) -> 0 | G68: =F68* (1 + Scenarios!$K$10) -> 0 | H68: =G68* (1 + Scenarios!$K$10) -> 0 | I68: =H68* (1 + Scenarios!$K$10) -> 0 | J68: =I68* (1 + Scenarios!$K$10) -> 0 | K68: =J68* (1 + Scenarios!$K$10) -> 0 | ... AZ68: =AY68* (1 + Scenarios!$K$10) -> 0
A69: 14. Pest Control [N/A IP1] | C69: 0 | D69: =C69* (1 + Scenarios!$K$10) -> 0 | E69: =D69* (1 + Scenarios!$K$10) -> 0 | F69: =E69* (1 + Scenarios!$K$10) -> 0 | G69: =F69* (1 + Scenarios!$K$10) -> 0 | H69: =G69* (1 + Scenarios!$K$10) -> 0 | I69: =H69* (1 + Scenarios!$K$10) -> 0 | J69: =I69* (1 + Scenarios!$K$10) -> 0 | K69: =J69* (1 + Scenarios!$K$10) -> 0 | ... AZ69: =AY69* (1 + Scenarios!$K$10) -> 0
A70: FINANCIAL & LEGAL: Interest on loans, bank charges, and legal expenses for tenant issues.
A71: 15. Interest Expense | C71: =Loan_IO_to_PI!N26 -> 27444.211 | D71: =Loan_IO_to_PI!O26 -> 27444.211 | E71: =Loan_IO_to_PI!P26 -> 27444.211 | F71: =Loan_IO_to_PI!Q26 -> 27444.211 | G71: =Loan_IO_to_PI!R26 -> 27444.211 | H71: =Loan_IO_to_PI!S26 -> 25341.452 | I71: =Loan_IO_to_PI!T26 -> 23116.944 | J71: =Loan_IO_to_PI!U26 -> 20763.636 | ... AZ71: =Loan_IO_to_PI!BK26 -> 0
A72: 16. Principle Repayment (cash non-deductible) | C72: =Loan_IO_to_PI!C28 -> 0 | D72: =Loan_IO_to_PI!D28 -> 0 | E72: =Loan_IO_to_PI!E28 -> 0 | F72: =Loan_IO_to_PI!F28 -> 0 | G72: =Loan_IO_to_PI!G28 -> 0 | H72: =Loan_IO_to_PI!H28 -> 0 | I72: =Loan_IO_to_PI!I28 -> 0 | J72: =Loan_IO_to_PI!J28 -> 0 | ... AZ72: =Loan_IO_to_PI!AZ28 -> 0
A73: 17. Bank Charges | C73: =IF( AND( Loan_IO_to_PI!N$24="P&I", Loan_IO_to_PI!M$24="IO", Loan_IO_to_PI!N$28>0 ), Loan_IO_to_PI!$B$8, 0 ) -> 0 | D73: =IF( AND( Loan_IO_to_PI!O$24="P&I", Loan_IO_to_PI!N$24="IO", Loan_IO_to_PI!O$28>0 ), Loan_IO_to_PI!$B$8, 0 ) -> 0 | E73: =IF( AND( Loan_IO_to_PI!P$24="P&I", Loan_IO_to_PI!O$24="IO", Loan_IO_to_PI!P$28>0 ), Loan_IO_to_PI!$B$8, 0 ) -> 0 | F73: =IF( AND( Loan_IO_to_PI!Q$24="P&I", Loan_IO_to_PI!P$24="IO", Loan_IO_to_PI!Q$28>0 ), Loan_IO_to_PI!$B$8, 0 ) -> 0 | G73: =IF( AND( Loan_IO_to_PI!R$24="P&I", Loan_IO_to_PI!Q$24="IO", Loan_IO_to_PI!R$28>0 ), Loan_IO_to_PI!$B$8, 0 ) -> 650 | H73: =IF( AND( Loan_IO_to_PI!S$24="P&I", Loan_IO_to_PI!R$24="IO", Loan_IO_to_PI!S$28>0 ), Loan_IO_to_PI!$B$8, 0 ) -> 0 | I73: =IF( AND( Loan_IO_to_PI!T$24="P&I", Loan_IO_to_PI!S$24="IO", Loan_IO_to_PI!T$28>0 ), Loan_IO_to_PI!$B$8, 0 ) -> 0 | J73: =IF( AND( Loan_IO_to_PI!U$24="P&I", Loan_IO_to_PI!T$24="IO", Loan_IO_to_PI!U$28>0 ), Loan_IO_to_PI!$B$8, 0 ) -> 0 | ... AZ73: =IF( AND( Loan_IO_to_PI!BK$24="P&I", Loan_IO_to_PI!BJ$24="IO", Loan_IO_to_PI!BK$28>0 ), Loan_IO_to_PI!$B$8, 0 ) -> 0
A74: 18. Legal Expenses | C74: =0 -> 0 | D74: =C74* (1 + Scenarios!$K$10) -> 0 | E74: =D74* (1 + Scenarios!$K$10) -> 0 | F74: =E74* (1 + Scenarios!$K$10) -> 0 | G74: =F74* (1 + Scenarios!$K$10) -> 0 | H74: =G74* (1 + Scenarios!$K$10) -> 0 | I74: =H74* (1 + Scenarios!$K$10) -> 0 | J74: =I74* (1 + Scenarios!$K$10) -> 0 | K74: =J74* (1 + Scenarios!$K$10) -> 0 | ... AZ74: =AY74* (1 + Scenarios!$K$10) -> 0
A75: OPERATIONAL: Advertising for tenants, stationery, postage, phone calls, and, in some cases, travel expenses (though travel to inspect residential property is generally not deductible).
A76: 19. Advertising for tenants | C76: =IF( MOD(C50-1, Assumptions!$B$57)=0, Assumptions!$B$54+Assumptions!$B$55, 0 ) -> 1462 | D76: =IF( MOD(D50-1, Assumptions!$B$57)=0, Assumptions!$B$54+Assumptions!$B$55, 0 ) -> 0 | E76: =IF( MOD(E50-1, Assumptions!$B$57)=0, Assumptions!$B$54+Assumptions!$B$55, 0 ) -> 0 | F76: =IF( MOD(F50-1, Assumptions!$B$57)=0, Assumptions!$B$54+Assumptions!$B$55, 0 ) -> 0 | G76: =IF( MOD(G50-1, Assumptions!$B$57)=0, Assumptions!$B$54+Assumptions!$B$55, 0 ) -> 1462 | H76: =IF( MOD(H50-1, Assumptions!$B$57)=0, Assumptions!$B$54+Assumptions!$B$55, 0 ) -> 0 | I76: =IF( MOD(I50-1, Assumptions!$B$57)=0, Assumptions!$B$54+Assumptions!$B$55, 0 ) -> 0 | J76: =IF( MOD(J50-1, Assumptions!$B$57)=0, Assumptions!$B$54+Assumptions!$B$55, 0 ) -> 0 | ... AZ76: =IF( MOD(AZ50-1, Assumptions!$B$57)=0, Assumptions!$B$54+Assumptions!$B$55, 0 ) -> 0
A77: 20. Stationery | C77: =0 -> 0 | D77: =C77* (1 + Scenarios!$K$10) -> 0 | E77: =D77* (1 + Scenarios!$K$10) -> 0 | F77: =E77* (1 + Scenarios!$K$10) -> 0 | G77: =F77* (1 + Scenarios!$K$10) -> 0 | H77: =G77* (1 + Scenarios!$K$10) -> 0 | I77: =H77* (1 + Scenarios!$K$10) -> 0 | J77: =I77* (1 + Scenarios!$K$10) -> 0 | K77: =J77* (1 + Scenarios!$K$10) -> 0 | ... AZ77: =AY77* (1 + Scenarios!$K$10) -> 0
A78: 21. Postage | C78: =0 -> 0 | D78: =C78* (1 + Scenarios!$K$10) -> 0 | E78: =D78* (1 + Scenarios!$K$10) -> 0 | F78: =E78* (1 + Scenarios!$K$10) -> 0 | G78: =F78* (1 + Scenarios!$K$10) -> 0 | H78: =G78* (1 + Scenarios!$K$10) -> 0 | I78: =H78* (1 + Scenarios!$K$10) -> 0 | J78: =I78* (1 + Scenarios!$K$10) -> 0 | K78: =J78* (1 + Scenarios!$K$10) -> 0 | ... AZ78: =AY78* (1 + Scenarios!$K$10) -> 0
A79: 22. Phone Calls | C79: =0 -> 0 | D79: =C79* (1 + Scenarios!$K$10) -> 0 | E79: =D79* (1 + Scenarios!$K$10) -> 0 | F79: =E79* (1 + Scenarios!$K$10) -> 0 | G79: =F79* (1 + Scenarios!$K$10) -> 0 | H79: =G79* (1 + Scenarios!$K$10) -> 0 | I79: =H79* (1 + Scenarios!$K$10) -> 0 | J79: =I79* (1 + Scenarios!$K$10) -> 0 | K79: =J79* (1 + Scenarios!$K$10) -> 0 | ... AZ79: =AY79* (1 + Scenarios!$K$10) -> 0
A80: 23. Travel Expenses [Travel to inspect residential property is generally not deductible.] | C80: =0 -> 0 | D80: =C80* (1 + Scenarios!$K$10) -> 0 | E80: =D80* (1 + Scenarios!$K$10) -> 0 | F80: =E80* (1 + Scenarios!$K$10) -> 0 | G80: =F80* (1 + Scenarios!$K$10) -> 0 | H80: =G80* (1 + Scenarios!$K$10) -> 0 | I80: =H80* (1 + Scenarios!$K$10) -> 0 | J80: =I80* (1 + Scenarios!$K$10) -> 0 | K80: =J80* (1 + Scenarios!$K$10) -> 0 | ... AZ80: =AY80* (1 + Scenarios!$K$10) -> 0
A81: REPAIRS: Costs to fix damage or deterioration (e.g., repairing a broken fence, fixing a leaking tap).
A82: 24. Repairs & Maintenance | D82: =C82* (1 + Scenarios!$K$10) -> 0 | E82: =D82* (1 + Scenarios!$K$10) -> 0 | F82: =E82* (1 + Scenarios!$K$10) -> 0 | G82: =F82* (1 + Scenarios!$K$10) -> 0 | H82: =G82* (1 + Scenarios!$K$10) -> 0 | I82: =H82* (1 + Scenarios!$K$10) -> 0 | J82: =I82* (1 + Scenarios!$K$10) -> 0 | K82: =J82* (1 + Scenarios!$K$10) -> 0 | ... AZ82: =AY82* (1 + Scenarios!$K$10) -> 0
A83: DEDUCTIONS CLAIMED OVER SEVERAL YEARS:
A84: 25. Depreciation (Decline in Value) - Plant & Equipment: For plant and equipment (e.g., blinds, carpets, appliances) costing over $300 Second-hand assets purchased after 9 May 2017 are not deductible. (Zero if post-2017 second-hand assets.) | C84: =0 -> 0 | D84: =0 -> 0 | E84: =0 -> 0 | F84: =0 -> 0 | G84: =0 -> 0 | H84: =0 -> 0 | I84: =0 -> 0 | J84: =0 -> 0 | ... AZ84: =0 -> 0
A85: 26. Capital Works Deduction: Structural improvements, such as building renovations, extensions, or new fences, generally depreciated at 2.5% per year. | C85: =Assumptions!$B$69*Assumptions!$B$70 -> 5538.775 | D85: =Assumptions!$B$69*Assumptions!$B$70 -> 5538.775 | E85: =Assumptions!$B$69*Assumptions!$B$70 -> 5538.775 | F85: =Assumptions!$B$69*Assumptions!$B$70 -> 5538.775 | G85: =Assumptions!$B$69*Assumptions!$B$70 -> 5538.775 | H85: =Assumptions!$B$69*Assumptions!$B$70 -> 5538.775 | I85: =Assumptions!$B$69*Assumptions!$B$70 -> 5538.775 | J85: =Assumptions!$B$69*Assumptions!$B$70 -> 5538.775 | ... AZ85: =Assumptions!$B$69*Assumptions!$B$70 -> 5538.775
A86: 27. Borrowing Expenses Amortised: Fees for obtaining a loan (e.g., mortgage application fees, mortgage broker fees), generally spread over 5 years or the loan term. | C86: =Loan_IO_to_PI!N31 -> 0 | D86: =Loan_IO_to_PI!O31 -> 0 | E86: =Loan_IO_to_PI!P31 -> 0 | F86: =Loan_IO_to_PI!Q31 -> 0 | G86: =Loan_IO_to_PI!R31 -> 0 | H86: =Loan_IO_to_PI!S31 -> 0 | I86: =Loan_IO_to_PI!T31 -> 0 | J86: =Loan_IO_to_PI!U31 -> 0 | ... AZ86: =Loan_IO_to_PI!BK31 -> 0
A87: 28. Other Deductible Expenses | D87: =C87* (1 + Scenarios!$K$10) -> 0 | E87: =D87* (1 + Scenarios!$K$10) -> 0 | F87: =E87* (1 + Scenarios!$K$10) -> 0 | G87: =F87* (1 + Scenarios!$K$10) -> 0 | H87: =G87* (1 + Scenarios!$K$10) -> 0 | I87: =H87* (1 + Scenarios!$K$10) -> 0 | J87: =I87* (1 + Scenarios!$K$10) -> 0 | K87: =J87* (1 + Scenarios!$K$10) -> 0 | ... AZ87: =AY87* (1 + Scenarios!$K$10) -> 0
A88: TOTALS:
A89: 29. Total Deductible Expenses | C89: =SUM(C56,C57,C58,C59,C60,C61,C62,C65,C66,C67,C68,C69,C71,C73,C74,C76,C77,C78,C79,C82,C84,C85,C86,C87) -> 44982.931 | D89: =SUM(D56,D57,D58,D59,D60,D61,D62,D65,D66,D67,D68,D69,D71,D73,D74,D76,D77,D78,D79,D82,D84,D85,D86,D87) -> 44398.281 | E89: =SUM(E56,E57,E58,E59,E60,E61,E62,E65,E66,E67,E68,E69,E71,E73,E74,E76,E77,E78,E79,E82,E84,E85,E86,E87) -> 44726.542 | F89: =SUM(F56,F57,F58,F59,F60,F61,F62,F65,F66,F67,F68,F69,F71,F73,F74,F76,F77,F78,F79,F82,F84,F85,F86,F87) -> 45064.631 | G89: =SUM(G56,G57,G58,G59,G60,G61,G62,G65,G66,G67,G68,G69,G71,G73,G74,G76,G77,G78,G79,G82,G84,G85,G86,G87) -> 47524.799 | H89: =SUM(H56,H57,H58,H59,H60,H61,H62,H65,H66,H67,H68,H69,H71,H73,H74,H76,H77,H78,H79,H82,H84,H85,H86,H87) -> 44542.144 | I89: =SUM(I56,I57,I58,I59,I60,I61,I62,I65,I66,I67,I68,I69,I71,I73,I74,I76,I77,I78,I79,I82,I84,I85,I86,I87) -> 42721.877 | J89: =SUM(J56,J57,J58,J59,J60,J61,J62,J65,J66,J67,J68,J69,J71,J73,J74,J76,J77,J78,J79,J82,J84,J85,J86,J87) -> 40785.217 | ... AZ89: =SUM(AZ56,AZ57,AZ58,AZ59,AZ60,AZ61,AZ62,AZ65,AZ66,AZ67,AZ68,AZ69,AZ71,AZ73,AZ74,AZ76,AZ77,AZ78,AZ79,AZ82,AZ84,AZ85,AZ86,AZ87) -> 49466.335
A90: 30. Net Rental Income / (Loss) | C90: =C54 - C89 -> -2342.9315 | D90: =D54 - D89 -> -479.08132 | E90: =E54 - E89 -> 510.23398 | F90: =F54 - F89 -> 1529.2487 | G90: =G54 - G89 -> 466.89703 | H90: =H54 - H89 -> 4889.3026 | I90: =I54 - I89 -> 8192.5126 | J90: =J54 - J89 -> 11656.605 | ... AZ90: =AZ54 - AZ89 -> 132018.86
A91: 31. Net Rental Cashflow (cash only) | C91: =C54-C56-C57-C58-C59-C60-C61-C62-C65-C66-C67-C68-C69-C71-C72-C73-C74-C76-C77-C78-C79-C80-C82 -> 3195.8435 | D91: =D54-D56-D57-D58-D59-D60-D61-D62-D65-D66-D67-D68-D69-D71-D72-D73-D74-D76-D77-D78-D79-D80-D82 -> 5059.6937 | E91: =E54-E56-E57-E58-E59-E60-E61-E62-E65-E66-E67-E68-E69-E71-E72-E73-E74-E76-E77-E78-E79-E80-E82 -> 6049.009 | F91: =F54-F56-F57-F58-F59-F60-F61-F62-F65-F66-F67-F68-F69-F71-F72-F73-F74-F76-F77-F78-F79-F80-F82 -> 7068.0237 | G91: =G54-G56-G57-G58-G59-G60-G61-G62-G65-G66-G67-G68-G69-G71-G72-G73-G74-G76-G77-G78-G79-G80-G82 -> 6005.672 | H91: =H54-H56-H57-H58-H59-H60-H61-H62-H65-H66-H67-H68-H69-H71-H72-H73-H74-H76-H77-H78-H79-H80-H82 -> 10428.078 | I91: =I54-I56-I57-I58-I59-I60-I61-I62-I65-I66-I67-I68-I69-I71-I72-I73-I74-I76-I77-I78-I79-I80-I82 -> 13731.288 | J91: =J54-J56-J57-J58-J59-J60-J61-J62-J65-J66-J67-J68-J69-J71-J72-J73-J74-J76-J77-J78-J79-J80-J82 -> 17195.38 | ... AZ91: =AZ54-AZ56-AZ57-AZ58-AZ59-AZ60-AZ61-AZ62-AZ65-AZ66-AZ67-AZ68-AZ69-AZ71-AZ72-AZ73-AZ74-AZ76-AZ77-AZ78-AZ79-AZ80-AZ82 -> 137557.64
C94: 2026 | D94: 2027 | E94: 2028 | F94: 2029 | G94: 2030 | H94: 2031 | I94: 2032 | J94: 2033 | K94: 2034 | L94: 2035 | M94: 2036 | N94: 2037 | O94: 2038 | P94: 2039 | Q94: 2040 | R94: 2041 | S94: 2042 | T94: 2043
A95: Description / Years | C95: 1 | D95: 2 | E95: 3 | F95: 4 | G95: 5 | H95: 6 | I95: 7 | J95: 8 | K95: 9 | L95: 10 | M95: 11 | N95: 12 | O95: 13 | P95: 14 | Q95: 15 | R95: 16 | S95: 17 | T95: 18 | U95: 19 | V95: 20 | W95: 21 | X95: 22 | Y95: 23 | Z95: 24 | AA95: 25 | AB95: 26 | AC95: 27 | AD95: 28 | AE95: 29 | AF95: 30 | AG95: 31 | AH95: 32 | AI95: 33 | AJ95: 34 | AK95: 35 | AL95: 36 | AM95: 37 | AN95: 38 | AO95: 39 | AP95: 40 | AQ95: 41 | AR95: 42 | AS95: 43 | AT95: 44 | AU95: 45 | AV95: 46 | AW95: 47 | AX95: 48 | AY95: 49 | AZ95: 50
A96: =Properties!A8 -> IP2
A98: INCOME
A99: 1. Gross Rent | C99: =820*52 -> 42640 | D99: =C99 * (1 + Scenarios!$K$13) -> 43919.2 | E99: =D99 * (1 + Scenarios!$K$13) -> 45236.776 | F99: =E99 * (1 + Scenarios!$K$13) -> 46593.879 | G99: =F99 * (1 + Scenarios!$K$13) -> 47991.696 | H99: =G99 * (1 + Scenarios!$K$13) -> 49431.447 | I99: =H99 * (1 + Scenarios!$K$13) -> 50914.39 | J99: =I99 * (1 + Scenarios!$K$13) -> 52441.822 | K99: =J99 * (1 + Scenarios!$K$13) -> 54015.076 | ... AZ99: =AY99 * (1 + Scenarios!$K$13) -> 181485.2
A100: PROPERTY EXPENSES (Statutory & Fixed): Council rates, land tax, water charges, body corporate fees, and insurance (building, contents, landlord).
A101: 2. Council Rates | C101: =660+(660*1+Scenarios!K53) -> 1320 | D101: =C101 * (1 + Scenarios!$K$10) -> 1353 | E101: =D101 * (1 + Scenarios!$K$10) -> 1386.825 | F101: =E101 * (1 + Scenarios!$K$10) -> 1421.4956 | G101: =F101 * (1 + Scenarios!$K$10) -> 1457.033 | H101: =G101 * (1 + Scenarios!$K$10) -> 1493.4588 | I101: =H101 * (1 + Scenarios!$K$10) -> 1530.7953 | J101: =I101 * (1 + Scenarios!$K$10) -> 1569.0652 | K101: =J101 * (1 + Scenarios!$K$10) -> 1608.2918 | ... AZ101: =AY101 * (1 + Scenarios!$K$10) -> 4426.3254
A102: 3. Water Charges | C102: 750 | D102: =C102* (1 + Scenarios!$K$10) -> 768.75 | E102: =D102* (1 + Scenarios!$K$10) -> 787.96875 | F102: =E102* (1 + Scenarios!$K$10) -> 807.66797 | G102: =F102* (1 + Scenarios!$K$10) -> 827.85967 | H102: =G102* (1 + Scenarios!$K$10) -> 848.55616 | I102: =H102* (1 + Scenarios!$K$10) -> 869.77006 | J102: =I102* (1 + Scenarios!$K$10) -> 891.51432 | K102: =J102* (1 + Scenarios!$K$10) -> 913.80217 | ... AZ102: =AY102* (1 + Scenarios!$K$10) -> 2514.9576
A103: 4. Body Corporate - Administrative | C103: =922.72*4 -> 3690.88 | D103: =C103* (1 + Scenarios!$K$10) -> 3783.152 | E103: =D103* (1 + Scenarios!$K$10) -> 3877.7308 | F103: =E103* (1 + Scenarios!$K$10) -> 3974.6741 | G103: =F103* (1 + Scenarios!$K$10) -> 4074.0409 | H103: =G103* (1 + Scenarios!$K$10) -> 4175.8919 | I103: =H103* (1 + Scenarios!$K$10) -> 4280.2892 | J103: =I103* (1 + Scenarios!$K$10) -> 4387.2965 | K103: =J103* (1 + Scenarios!$K$10) -> 4496.9789 | ... AZ103: =AY103* (1 + Scenarios!$K$10) -> 12376.542
A104: 5. Body Corporate - Capital Works | B104: =Properties!$C$22 -> 770 | C104: {=Properties!$D$22} -> 1262.8 | D104: {=Properties!$E$22} -> 1894.2 | E104: {=Properties!$F$22} -> 1969.94 | F104: {=Properties!$G$22} -> 2048.76 | G104: {=Properties!$H$22} -> 2130.73 | H104: {=Properties!$I$22} -> 3089.52 | I104: {=Properties!$J$22} -> 3213.14 | J104: {=Properties!$K$22} -> 3341.66 | K104: {=Properties!$L$22} -> 3475.29 | L104: {=Properties!$M$22} -> 3614.31 | M104: {=Properties!$N$22} -> 3758.93 | N104: {=Properties!$O$22} -> 3909.22 | O104: {=Properties!$P$22} -> 4065.6 | P104: {=Properties!$Q$22} -> 4228.28 | Q104: {=P104*(1+Scenarios!$K$10)} -> 4333.987 | R104: {=Q104*(1+Scenarios!$K$10)} -> 4442.3367 | S104: {=R104*(1+Scenarios!$K$10)} -> 4553.3951 | T104: {=S104*(1+Scenarios!$K$10)} -> 4667.23 | U104: {=T104*(1+Scenarios!$K$10)} -> 4783.9107 | V104: {=U104*(1+Scenarios!$K$10)} -> 4903.5085 | W104: {=V104*(1+Scenarios!$K$10)} -> 5026.0962 | X104: {=W104*(1+Scenarios!$K$10)} -> 5151.7486 | ... AZ104: {=AY104*(1+Scenarios!$K$10)} -> 10285.44
A105: 6. Insurance - Building [N/A IP1 - Included in Body Corporate Administrative budget] | C105: 0 | D105: =C105* (1 + Scenarios!$K$10) -> 0 | E105: =D105* (1 + Scenarios!$K$10) -> 0 | F105: =E105* (1 + Scenarios!$K$10) -> 0 | G105: =F105* (1 + Scenarios!$K$10) -> 0 | H105: =G105* (1 + Scenarios!$K$10) -> 0 | I105: =H105* (1 + Scenarios!$K$10) -> 0 | J105: =I105* (1 + Scenarios!$K$10) -> 0 | K105: =J105* (1 + Scenarios!$K$10) -> 0 | ... AZ105: =AY105* (1 + Scenarios!$K$10) -> 0
A106: 7. Insurance - Contents [N/A; assumption continuously tennated] | C106: 0 | D106: =C106* (1 + Scenarios!$K$10) -> 0 | E106: =D106* (1 + Scenarios!$K$10) -> 0 | F106: =E106* (1 + Scenarios!$K$10) -> 0 | G106: =F106* (1 + Scenarios!$K$10) -> 0 | H106: =G106* (1 + Scenarios!$K$10) -> 0 | I106: =H106* (1 + Scenarios!$K$10) -> 0 | J106: =I106* (1 + Scenarios!$K$10) -> 0 | K106: =J106* (1 + Scenarios!$K$10) -> 0 | ... AZ106: =AY106* (1 + Scenarios!$K$10) -> 0
A107: 8. Insurance - Landlord | C107: 700 | D107: =C107* (1 + Scenarios!$K$10) -> 717.5 | E107: =D107* (1 + Scenarios!$K$10) -> 735.4375 | F107: =E107* (1 + Scenarios!$K$10) -> 753.82344 | G107: =F107* (1 + Scenarios!$K$10) -> 772.66902 | H107: =G107* (1 + Scenarios!$K$10) -> 791.98575 | I107: =H107* (1 + Scenarios!$K$10) -> 811.78539 | J107: =I107* (1 + Scenarios!$K$10) -> 832.08003 | K107: =J107* (1 + Scenarios!$K$10) -> 852.88203 | ... AZ107: =AY107* (1 + Scenarios!$K$10) -> 2347.2938
A108: MANAGEMENT & MAINTENANCE: Real estate agent fees/commissions, cleaning, gardening, lawn mowing, and pest control.
...

Sheet GSB_Bank_Cash_50455259
A4: Transaction history
A5: Statement period: 22 JAN 2019 To 21 JUL 2019
A6: Account: 50455259 Brett William Hofman, Laura Nicole Hofman TFN Known: Y
A7: E-4470/S-145169/I-267063 EM. 4470NNNNNN 9018614
A8: Date | B8: Description | C8: Debits | D8: Credits | E8: Balance
A9: 46044 | B9: OPENING BALANCE | E9: 310892.12
A10: 46053 | B10: Fast Pymt In | D10: 3000
A11: 46053 | B11: REF:..
A12: 46054 | B12: Auto Payment TRANSFER TO 814282 50503609 Hofman Brett
A13: 3,000.00 313,892.12
A14: 31 Jan REF:..
A15: 1 Feb Auto Payment TRANSFER TO 814282 50503609 Hofman Brett 656.35 1 Feb Auto Payment TRANSFER TO 814282 50503609 Hofman Brett 656.35 313,235.77
A16: 313235.77
A17: 1 Feb FREE TXNS UNLIMITED
A18: 1 Mar Auto Payment TRANSFER TO 814282 50503609 Hofman Brett 584.45 1 Mar Auto Payment TRANSFER TO 814282 50503609 Hofman Brett 584.45 312,651.32
A19: 312651.32
A20: 1 Mar FREE TXNS UNLIMITED
A21: 10 Mar Fast Pymt Out March CC Brett W Hofman 10 Mar Fast Pymt Out March CC Brett W Hofman 5,000.00 5,000.00 14 Mar Fast Pymt In 307,651.32
A22: 307651.32
A23: 10,000.00 317,651.32
A24: 14 Mar REF:..
A25: 14 Mar REF:..
A26: 14 Mar Fast Pymt In 8,000.00 325,651.32
A27: 14 Mar REF:Sti.
A28: 14 Mar REF:Sti.
A29: 1 Apr Auto Payment TRANSFER TO 814282 50503609 Hofman Brett 620.99 325,030.33
A30: 1 of 2
A31: Please check all entries on this statement and notify CUA immediately of any errors or omissions. For transaction fee package information for all accounts, please refer to the Schedule of Fees brochure. For information
A32: on our complaints and dispute resolution system, or in relation to your financial products, their benefits or fees and charges call 133 282 or drop into any of our branches.Credit Union Australia Limited
A33: ABN 44 087 650 959
A34: AFSL and Australian credit licence 238317
... A40: Shareholder: 1 x Member Share
A41: 324451.25
A42: 5,000.00 4,500.00 4,500.00 319,451.25
A43: 314951.25
A44: 314951.25
A45: 314331.43
A46: Date Description Debits Credits Balance
A47: 1 Apr FREE TXNS UNLIMITED
A48: 1 Apr FREE TXNS UNLIMITED
A49: 1 May Auto Payment TRANSFER TO 814282 50503609 Hofman Brett 579.08 1 May FREE TXNS UNLIMITED
A50: 1 May FREE TXNS UNLIMITED
A51: 16 May Fast Pymt Out RWC Flights Brett W Hofman 18 May Fast Pymt Out RWC Trip Brett W Hofman 18 May Fast Pymt Out RWC Trip Brett W Hofman 1 Jun Auto Payment TRANSFER TO 814282 50503609 Hofman Brett 619.82 1 Jun FREE TXNS UNLIMITED
A52: 1 Jun FREE TXNS UNLIMITED
A53: 13 Jun Fast Pymt Out June behind Brett W Hofman 1 Jul Auto Payment TRANSFER TO 814282 50503609 Hofman Brett 617.96 1 Jul Auto Payment TRANSFER TO 814282 50503609 Hofman Brett 617.96 1 Jul FREE TXNS UNLIMITED
A54: 3 Jul 3 Jul TXN INITIATED BY-9018614 TRANSFER TO 065125 10110962 Toop Real
A55: TXN INITIATED BY-9018614 TRANSFER TO 065125 10110962 Toop Real
A56: 4,331.43 310,000.00
A57: 309382.04
A58: 309382.04
A59: Estate S REF: 10 Arnold Parkside 112,500.00 196,882.04
A60: Estate S REF: 10 Arnold Parkside 112,500.00 196,882.04
A61: 17 Jul Fast Pymt Out Car service Brett W Hofman 4,999.00 191,883.04
A62: 21 Jul CLOSING BALANCE 191,883.04

Sheet GSB_Bank_Statement
A6: Credit Union Australia Limited
A7: ABN 44 087 650 959
A8: AFSL and Australian credit licence 238317
A9: GPO Box 100, Brisbane QLD 4001
A10: For help or enquiries?
A11: 133 282
A12: www.cua.com.au
A13: 7
A14: Your details
A15: Customer number: 9018614
A16: BSB: 814-282
A17: Issue date: 21/07/2019
A18: Shareholder: 1 x Member Share
A19: 4470
A20: Mr Brett William Hofman
A21: 103/29 ALBANY ST
A22: CROWS NEST NSW 2065
A24: 50455259 | B24: Prime Access $310,892.12 | D24: $21,000.00 | E24: $140,009.08 | F24: 191883.04
A25: 50456034 | B25: eSaver Plus $0.00 | D25: $0.00 | E25: $0.00 | F25: 0
B26: 50503609 Fresh Start Variable IO -$470,000.00 $3,678.65 $3,678.65 -$470,000.00
A28: Transaction history
A29: Statement period: 22 JAN 2019 To 21 JUL 2019
A30: Account: 50455259 Brett William Hofman, Laura Nicole Hofman TFN Known: Y
A31: E-4470/S-145169/I-267063 EM. 4470NNNNNN 9018614
A32: Date Description Debits Credits Balance
A33: 22 Jan OPENING BALANCE 310,892.12
A34: 31 Jan Fast Pymt In 31 Jan Fast Pymt In 3,000.00 313,892.12
A35: 3,000.00 313,892.12
A36: 31 Jan REF:..
A37: 1 Feb Auto Payment TRANSFER TO 814282 50503609 Hofman Brett 656.35 1 Feb Auto Payment TRANSFER TO 814282 50503609 Hofman Brett 656.35 313,235.77
A38: 313235.77
A39: 1 Feb FREE TXNS UNLIMITED
A40: 1 Mar Auto Payment TRANSFER TO 814282 50503609 Hofman Brett 584.45 1 Mar Auto Payment TRANSFER TO 814282 50503609 Hofman Brett 584.45 312,651.32
A41: 312651.32
A42: 1 Mar FREE TXNS UNLIMITED
A43: 10 Mar Fast Pymt Out March CC Brett W Hofman 10 Mar Fast Pymt Out March CC Brett W Hofman 5,000.00 5,000.00 14 Mar Fast Pymt In 307,651.32
A44: 307651.32
A45: 10,000.00 317,651.32
A46: 14 Mar REF:..
A47: 14 Mar REF:..
A48: 14 Mar Fast Pymt In 8,000.00 325,651.32
A49: 14 Mar REF:Sti.
A50: 14 Mar REF:Sti.
A51: 1 Apr Auto Payment TRANSFER TO 814282 50503609 Hofman Brett 620.99 325,030.33
A52: 1 of 2
A53: Please check all entries on this statement and notify CUA immediately of any errors or omissions. For transaction fee package information for all accounts, please refer to the Schedule of Fees brochure. For information
A54: on our complaints and dispute resolution system, or in relation to your financial products, their benefits or fees and charges call 133 282 or drop into any of our branches.Credit Union Australia Limited
A55: ABN 44 087 650 959
A56: AFSL and Australian credit licence 238317
... A62: Shareholder: 1 x Member Share
A63: 324451.25
A64: 5,000.00 4,500.00 4,500.00 319,451.25
A65: 314951.25
A66: 314951.25
A67: 314331.43
A68: Date Description Debits Credits Balance
A69: 1 Apr FREE TXNS UNLIMITED
A70: 1 Apr FREE TXNS UNLIMITED
A71: 1 May Auto Payment TRANSFER TO 814282 50503609 Hofman Brett 579.08 1 May FREE TXNS UNLIMITED
A72: 1 May FREE TXNS UNLIMITED
A73: 16 May Fast Pymt Out RWC Flights Brett W Hofman 18 May Fast Pymt Out RWC Trip Brett W Hofman 18 May Fast Pymt Out RWC Trip Brett W Hofman 1 Jun Auto Payment TRANSFER TO 814282 50503609 Hofman Brett 619.82 1 Jun FREE TXNS UNLIMITED
A74: 1 Jun FREE TXNS UNLIMITED
A75: 13 Jun Fast Pymt Out June behind Brett W Hofman 1 Jul Auto Payment TRANSFER TO 814282 50503609 Hofman Brett 617.96 1 Jul Auto Payment TRANSFER TO 814282 50503609 Hofman Brett 617.96 1 Jul FREE TXNS UNLIMITED
A76: 3 Jul 3 Jul TXN INITIATED BY-9018614 TRANSFER TO 065125 10110962 Toop Real
A77: TXN INITIATED BY-9018614 TRANSFER TO 065125 10110962 Toop Real
A78: 4,331.43 310,000.00
A79: 309382.04
A80: 309382.04
A81: Estate S REF: 10 Arnold Parkside 112,500.00 196,882.04
A82: Estate S REF: 10 Arnold Parkside 112,500.00 196,882.04
A83: 17 Jul Fast Pymt Out Car service Brett W Hofman 4,999.00 191,883.04
A84: 21 Jul CLOSING BALANCE 191,883.04
A85: 21 Jul CLOSING BALANCE 191,883.04
A86: Statement period: 22 JAN 2019 To 21 JUL 2019
A87: Account: 50456034 Brett William Hofman, Laura Nicole Hofman TFN Known: Y
A88: Date Description Debits Credits Balance
A89: 22 Jan OPENING BALANCE 0.00
A90: 21 Jul CLOSING BALANCE 0.00
A91: 21 Jul CLOSING BALANCE 0.00
A92: TFN Known: Y
... A143: www.cua.com.au
A144: 7
A145: Your details
A146: Customer number: 9018614
A147: BSB: 814-282
A148: Issue date: 21/01/2020
A149: Shareholder: 1 x Member Share
A150: 525
A151: Mr Brett William Hofman
A152: 103/29 ALBANY ST
A153: CROWS NEST NSW 2065
A155: 50455259 | B155: Prime Access | C155: $191,883.04 | D155: $925,143.56 $1,116,933.51 | E155: 93.09
A156: 50456034 | B156: eSaver Plus | C156: $0.00 | D156: $0.00 $0.00 | E156: 0
A157: 50503609 | B157: Fresh Start Variable IO | C157: -$470,000.00 | D157: $9,602.18 $9,602.18 | E157: -470000
C158: 51001645 Achieve Var Inv P&I $0.00 $24,908.02 $917,760.39 -$892,852.37
A160: Transaction history
A161: Account name: Prime Access
A162: Product name: Prime Access
A163: Statement period: 22 JUL 2019 To 21 JAN 2020
A164: Account: 50455259 Brett William Hofman, Laura Nicole Hofman E-525/S-149329/I-277480EM. 525NNNNNN 9018614
...

Sheet Sheet1

Sheet Bank_Statement
B5: 46218 | C5: 46239 | D5: 46261 | E5: 46265 | F5: 46266 | G5: 46270 | H5: 46288 | I5: 46295 | J5: 46300 | K5: 46324 | L5: 46324 | M5: 46326 | N5: 46331 | O5: 46356 | P5: 46361 | Q5: 46387 | R5: 46027 | S5: 46043
A6: Interest Rate | B6: 3.76 | C6: 3.76 | D6: 3.76 | E6: 3.76 | F6: 3.76 | G6: 3.76 | H6: 3.76 | I6: 3.76
A7: BALANCE | B7: 900000
A8: Interest Charged | E8: 2503.23 | H8: =I12-H12-I8 -> 8400 | I8: 2768.41
A9: Auto Payment | G9: 4173.15 | J9: 4182.61
A10: Loan Repayment | F10: 4200 | H10: -4200
B12: =B7 -> 900000 | E12: =B12+E8 -> 902503.23 | F12: =E12-F10 -> 898303.23 | G12: =F12-G9 -> 894130.08 | H12: =G12+H10 -> 889930.08 | I12: 901098.49

Sheet Loan_IO_to_PI
A1: Loan Inputs
A2: IP1
A3: Opening Loan Balance | B3: =Properties!D7 -> 473993.29
A4: Interest Rate (annual) | B4: =Properties!E7 -> 0.0579
A5: Loan Start Year | B5: 2015
A6: IO End Age | B6: 2030
A7: Original Loan Term (yrs) | B7: 25
A8: Bank_Charge_Assumption_Loan_Change_Fee | B8: 650
A10: Borrowing Costs | B10: =SUM(B11:B14) -> 1909.5
A11: Conveyance | B11: 1200
A12: Loan Establishment Fee | B12: 600
A13: Registration of Title | B13: 109.5
A14: Stamp Duty (add to cost base for CGT when disposal of property) | B14: Exempt
A15: First year available for rent | B15: =H21 -> 2020
A16: Amort years (ATO) | B16: =MIN(5, H25) -> 5
H17: ACTUAL INTEREST FROM GSB
H18: 19058.56 | I18: 16536.76 | J18: 26584.83 | K18: 33276.35 | L18: 31228.6
A19: Schedule (Annual) | H19: =H18/H23 -> 0.040208502 | I19: =I18/I23 -> 0.034888173 | J19: =J18/J23 -> 0.056086933 | K19: =K18/K23 -> 0.070204264 | L19: =L18/L23 -> 0.065884055
B20: Age | C20: 37 | D20: 38 | E20: 39 | F20: 40 | G20: 41 | H20: 42 | I20: 43 | J20: 44 | K20: 45 | L20: 46 | M20: 47 | N20: 48 | O20: 49 | P20: 50 | Q20: 51 | R20: 52 | S20: 53 | T20: 54 | U20: 55 | V20: 56 | W20: 57 | X20: 58 | Y20: 59 | Z20: 60 | AA20: 61 | AB20: 62 | AC20: 63 | AD20: 64 | AE20: 65 | AF20: 66 | AG20: 67 | AH20: 68 | AI20: 69 | AJ20: 70 | AK20: 71
A21: Year | C21: =$B$5 + 0 -> 2015 | D21: =$B$5 + 1 -> 2016 | E21: =$B$5 + 2 -> 2017 | F21: =$B$5 + 3 -> 2018 | G21: =$B$5 + 4 -> 2019 | H21: =$B$5 + 5 -> 2020 | I21: =$B$5 + 6 -> 2021 | J21: =$B$5 + 7 -> 2022 | K21: =$B$5 + 8 -> 2023 | L21: =$B$5 + 9 -> 2024 | M21: =$B$5 + 10 -> 2025 | N21: =$B$5 + 11 -> 2026 | O21: =$B$5 + 12 -> 2027 | P21: =$B$5 + 13 -> 2028 | Q21: =$B$5 + 14 -> 2029 | R21: =$B$5 + 15 -> 2030 | S21: =$B$5 + 16 -> 2031 | T21: =$B$5 + 17 -> 2032 | U21: =$B$5 + 18 -> 2033 | V21: =$B$5 + 19 -> 2034 | W21: =$B$5 + 20 -> 2035 | X21: =$B$5 + 21 -> 2036 | Y21: =$B$5 + 22 -> 2037 | Z21: =$B$5 + 23 -> 2038 | AA21: =$B$5 + 24 -> 2039 | AB21: =$B$5 + 25 -> 2040 | AC21: =$B$5 + 26 -> 2041 | AD21: =$B$5 + 27 -> 2042 | AE21: =$B$5 + 28 -> 2043 | AF21: =$B$5 + 29 -> 2044 | AG21: =$B$5 + 30 -> 2045 | AH21: =$B$5 + 31 -> 2046 | AI21: =$B$5 + 32 -> 2047 | AJ21: =$B$5 + 33 -> 2048 | AK21: =$B$5 + 34 -> 2049
A22: IP1 | C22: 1 | D22: 2 | E22: 3 | F22: 4 | G22: 5 | H22: 6 | I22: 7 | J22: 8 | K22: 9 | L22: 10 | M22: 11 | N22: 12 | O22: 13 | P22: 14 | Q22: 15 | R22: 16 | S22: 17 | T22: 18 | U22: 19 | V22: 20 | W22: 21 | X22: 22 | Y22: 23 | Z22: 24 | AA22: 25 | AB22: 26 | AC22: 27 | AD22: 28 | AE22: 29 | AF22: 30 | AG22: 31 | AH22: 32 | AI22: 33 | AJ22: 34 | AK22: 35
A23: Opening Balance | C23: =$B$3 -> 473993.29 | D23: =C29 -> 473993.29 | E23: =D29 -> 473993.29 | F23: =E29 -> 473993.29 | G23: =F29 -> 473993.29 | H23: =G29 -> 473993.29 | I23: =H29 -> 473993.29 | J23: =I29 -> 473993.29 | K23: =J29 -> 473993.29 | ... AK23: =AJ29 -> 0
A24: Repayment Mode | C24: =IF(C21<$B$6,"IO","P&I") -> IO | D24: =IF(D21<$B$6,"IO","P&I") -> IO | E24: =IF(E21<$B$6,"IO","P&I") -> IO | F24: =IF(F21<$B$6,"IO","P&I") -> IO | G24: =IF(G21<$B$6,"IO","P&I") -> IO | H24: =IF(H21<$B$6,"IO","P&I") -> IO | I24: =IF(I21<$B$6,"IO","P&I") -> IO | J24: =IF(J21<$B$6,"IO","P&I") -> IO | ... AK24: =IF(AK21<$B$6,"IO","P&I") -> P&I
A25: Remaining Term (yrs) | C25: =MAX(0,$B$7-(C21-$B$5)) -> 25 | D25: =MAX(0,$B$7-(D21-$B$5)) -> 24 | E25: =MAX(0,$B$7-(E21-$B$5)) -> 23 | F25: =MAX(0,$B$7-(F21-$B$5)) -> 22 | G25: =MAX(0,$B$7-(G21-$B$5)) -> 21 | H25: =MAX(0,$B$7-(H21-$B$5)) -> 20 | I25: =MAX(0,$B$7-(I21-$B$5)) -> 19 | J25: =MAX(0,$B$7-(J21-$B$5)) -> 18 | ... AK25: =MAX(0,$B$7-(AK21-$B$5)) -> 0
A26: Interest Expense | C26: =C23*$B$4 -> 27444.211 | D26: =D23*$B$4 -> 27444.211 | E26: =E23*$B$4 -> 27444.211 | F26: =F23*$B$4 -> 27444.211 | G26: =G23*$B$4 -> 27444.211 | H26: =H23*$B$4 -> 27444.211 | I26: =I23*$B$4 -> 27444.211 | J26: =J23*$B$4 -> 27444.211 | ... AK26: =AK23*$B$4 -> 0
A27: Annual Repayment | C27: =IF(C25=0,0,IF(C24="IO",C26,PMT($B$4,C25,-C23))) -> 27444.211 | D27: =IF(D25=0,0,IF(D24="IO",D26,PMT($B$4,D25,-D23))) -> 27444.211 | E27: =IF(E25=0,0,IF(E24="IO",E26,PMT($B$4,E25,-E23))) -> 27444.211 | F27: =IF(F25=0,0,IF(F24="IO",F26,PMT($B$4,F25,-F23))) -> 27444.211 | G27: =IF(G25=0,0,IF(G24="IO",G26,PMT($B$4,G25,-G23))) -> 27444.211 | H27: =IF(H25=0,0,IF(H24="IO",H26,PMT($B$4,H25,-H23))) -> 27444.211 | I27: =IF(I25=0,0,IF(I24="IO",I26,PMT($B$4,I25,-I23))) -> 27444.211 | J27: =IF(J25=0,0,IF(J24="IO",J26,PMT($B$4,J25,-J23))) -> 27444.211 | ... AK27: =IF(AK25=0,0,IF(AK24="IO",AK26,PMT($B$4,AK25,-AK23))) -> 0
A28: Principal Repayment | C28: =MAX(0,C27-C26) -> 0 | D28: =MAX(0,D27-D26) -> 0 | E28: =MAX(0,E27-E26) -> 0 | F28: =MAX(0,F27-F26) -> 0 | G28: =MAX(0,G27-G26) -> 0 | H28: =MAX(0,H27-H26) -> 0 | I28: =MAX(0,I27-I26) -> 0 | J28: =MAX(0,J27-J26) -> 0 | ... AK28: =MAX(0,AK27-AK26) -> 0
A29: Closing Balance | C29: =MAX(0,C23-C28) -> 473993.29 | D29: =MAX(0,D23-D28) -> 473993.29 | E29: =MAX(0,E23-E28) -> 473993.29 | F29: =MAX(0,F23-F28) -> 473993.29 | G29: =MAX(0,G23-G28) -> 473993.29 | H29: =MAX(0,H23-H28) -> 473993.29 | I29: =MAX(0,I23-I28) -> 473993.29 | J29: =MAX(0,J23-J28) -> 473993.29 | ... AK29: =MAX(0,AK23-AK28) -> 0
A31: “Borrowing Exp – Theoretical” | C31: =IF( AND(C$21 >= $B$15, C$21 < $B$15 + 5), -$B$10 / 5, 0 ) -> 0 | D31: =IF( AND(D$21 >= $B$15, D$21 < $B$15 + 5), -$B$10 / 5, 0 ) -> 0 | E31: =IF( AND(E$21 >= $B$15, E$21 < $B$15 + 5), -$B$10 / 5, 0 ) -> 0 | F31: =IF( AND(F$21 >= $B$15, F$21 < $B$15 + 5), -$B$10 / 5, 0 ) -> 0 | G31: =IF( AND(G$21 >= $B$15, G$21 < $B$15 + 5), -$B$10 / 5, 0 ) -> 0 | H31: =IF( AND(H$21 >= $B$15, H$21 < $B$15 + 5), -$B$10 / 5, 0 ) -> -381.9 | I31: =IF( AND(I$21 >= $B$15, I$21 < $B$15 + 5), -$B$10 / 5, 0 ) -> -381.9 | J31: =IF( AND(J$21 >= $B$15, J$21 < $B$15 + 5), -$B$10 / 5, 0 ) -> -381.9 | ... AK31: =IF( AND(AK$21 >= $B$15, AK$21 < $B$15 + 5), -$B$10 / 5, 0 ) -> 0
A36: IP2
A37: Opening Loan Balance | B37: 473993
A38: Interest Rate (annual) | B38: 0.0579
A39: Loan Start Year | B39: 2015
A40: IO End Age | B40: 2030
A41: Original Loan Term (yrs) | B41: 25
A43: Borrowing Costs | B43: =SUM(B44:B47) -> 1909.5
A44: Conveyance | B44: 1200
A45: Loan Establishment Fee | B45: 600
A46: Registration of Title | B46: 109.5
A47: Stamp Duty (add to cost base for CGT when disposal of property) | B47: Exempt
A48: First year available for rent | B48: =H55 -> 473993
A49: Amort years (ATO) | B49: =MIN(5, H59) -> 5
A51: Schedule (Annual)
A53: Year | C53: =$B$5 + 0 -> 2015 | D53: =$B$5 + 1 -> 2016 | E53: =$B$5 + 2 -> 2017 | F53: =$B$5 + 3 -> 2018 | G53: =$B$5 + 4 -> 2019 | H53: =$B$5 + 5 -> 2020 | I53: =$B$5 + 6 -> 2021 | J53: =$B$5 + 7 -> 2022 | K53: =$B$5 + 8 -> 2023 | L53: =$B$5 + 9 -> 2024 | M53: =$B$5 + 10 -> 2025 | N53: =$B$5 + 11 -> 2026 | O53: =$B$5 + 12 -> 2027 | P53: =$B$5 + 13 -> 2028 | Q53: =$B$5 + 14 -> 2029 | R53: =$B$5 + 15 -> 2030 | S53: =$B$5 + 16 -> 2031 | T53: =$B$5 + 17 -> 2032 | U53: =$B$5 + 18 -> 2033 | V53: =$B$5 + 19 -> 2034 | W53: =$B$5 + 20 -> 2035 | X53: =$B$5 + 21 -> 2036 | Y53: =$B$5 + 22 -> 2037 | Z53: =$B$5 + 23 -> 2038 | AA53: =$B$5 + 24 -> 2039 | AB53: =$B$5 + 25 -> 2040 | AC53: =$B$5 + 26 -> 2041 | AD53: =$B$5 + 27 -> 2042 | AE53: =$B$5 + 28 -> 2043 | AF53: =$B$5 + 29 -> 2044 | AG53: =$B$5 + 30 -> 2045 | AH53: =$B$5 + 31 -> 2046 | AI53: =$B$5 + 32 -> 2047 | AJ53: =$B$5 + 33 -> 2048 | AK53: =$B$5 + 34 -> 2049
A54: IP2 | C54: 1 | D54: 2 | E54: 3 | F54: 4 | G54: 5 | H54: 6 | I54: 7 | J54: 8 | K54: 9 | L54: 10 | M54: 11 | N54: 12 | O54: 13 | P54: 14 | Q54: 15 | R54: 16 | S54: 17 | T54: 18 | U54: 19 | V54: 20 | W54: 21 | X54: 22 | Y54: 23 | Z54: 24 | AA54: 25 | AB54: 26 | AC54: 27 | AD54: 28 | AE54: 29 | AF54: 30 | AG54: 31 | AH54: 32 | AI54: 33 | AJ54: 34 | AK54: 35
A55: Opening Balance | C55: =$B$37 -> 473993 | D55: =C61 -> 473993 | E55: =D61 -> 473993 | F55: =E61 -> 473993 | G55: =F61 -> 473993 | H55: =G61 -> 473993 | I55: =H61 -> 473993 | J55: =I61 -> 473993 | K55: =J61 -> 473993 | ... AK55: =AJ61 -> 0
A56: Repayment Mode | C56: =IF(C53<$B$6,"IO","P&I") -> IO | D56: =IF(D53<$B$6,"IO","P&I") -> IO | E56: =IF(E53<$B$6,"IO","P&I") -> IO | F56: =IF(F53<$B$6,"IO","P&I") -> IO | G56: =IF(G53<$B$6,"IO","P&I") -> IO | H56: =IF(H53<$B$6,"IO","P&I") -> IO | I56: =IF(I53<$B$6,"IO","P&I") -> IO | J56: =IF(J53<$B$6,"IO","P&I") -> IO | ... AK56: =IF(AK53<$B$6,"IO","P&I") -> P&I
A57: Remaining Term (yrs) | C57: =MAX(0,$B$41-(C53-$B$39)) -> 25 | D57: =MAX(0,$B$41-(D53-$B$39)) -> 24 | E57: =MAX(0,$B$41-(E53-$B$39)) -> 23 | F57: =MAX(0,$B$41-(F53-$B$39)) -> 22 | G57: =MAX(0,$B$41-(G53-$B$39)) -> 21 | H57: =MAX(0,$B$41-(H53-$B$39)) -> 20 | I57: =MAX(0,$B$41-(I53-$B$39)) -> 19 | J57: =MAX(0,$B$41-(J53-$B$39)) -> 18 | ... AK57: =MAX(0,$B$41-(AK53-$B$39)) -> 0
A58: Interest Expense | C58: =C55*$B$38 -> 27444.195 | D58: =D55*$B$38 -> 27444.195 | E58: =E55*$B$38 -> 27444.195 | F58: =F55*$B$38 -> 27444.195 | G58: =G55*$B$38 -> 27444.195 | H58: =H55*$B$38 -> 27444.195 | I58: =I55*$B$38 -> 27444.195 | J58: =J55*$B$38 -> 27444.195 | ... AK58: =AK55*$B$38 -> 0
A59: Annual Repayment | C59: =IF(C57=0,0,IF(C56="IO",C58,PMT($B$4,C57,-C55))) -> 27444.195 | D59: =IF(D57=0,0,IF(D56="IO",D58,PMT($B$4,D57,-D55))) -> 27444.195 | E59: =IF(E57=0,0,IF(E56="IO",E58,PMT($B$4,E57,-E55))) -> 27444.195 | F59: =IF(F57=0,0,IF(F56="IO",F58,PMT($B$4,F57,-F55))) -> 27444.195 | G59: =IF(G57=0,0,IF(G56="IO",G58,PMT($B$4,G57,-G55))) -> 27444.195 | H59: =IF(H57=0,0,IF(H56="IO",H58,PMT($B$4,H57,-H55))) -> 27444.195 | I59: =IF(I57=0,0,IF(I56="IO",I58,PMT($B$4,I57,-I55))) -> 27444.195 | J59: =IF(J57=0,0,IF(J56="IO",J58,PMT($B$4,J57,-J55))) -> 27444.195 | ... AK59: =IF(AK57=0,0,IF(AK56="IO",AK58,PMT($B$4,AK57,-AK55))) -> 0
A60: Principal Repayment | C60: =MAX(0,C59-C58) -> 0 | D60: =MAX(0,D59-D58) -> 0 | E60: =MAX(0,E59-E58) -> 0 | F60: =MAX(0,F59-F58) -> 0 | G60: =MAX(0,G59-G58) -> 0 | H60: =MAX(0,H59-H58) -> 0 | I60: =MAX(0,I59-I58) -> 0 | J60: =MAX(0,J59-J58) -> 0 | ... AK60: =MAX(0,AK59-AK58) -> 0
A61: Closing Balance | C61: =MAX(0,C55-C60) -> 473993 | D61: =MAX(0,D55-D60) -> 473993 | E61: =MAX(0,E55-E60) -> 473993 | F61: =MAX(0,F55-F60) -> 473993 | G61: =MAX(0,G55-G60) -> 473993 | H61: =MAX(0,H55-H60) -> 473993 | I61: =MAX(0,I55-I60) -> 473993 | J61: =MAX(0,J55-J60) -> 473993 | ... AK61: =MAX(0,AK55-AK60) -> 0
A63: “Borrowing Exp – Theoretical” | C63: =IF( AND(C$21 >= $B$15, C$21 < $B$15 + 5), -$B$10 / 5, 0 ) -> 0 | D63: =IF( AND(D$21 >= $B$15, D$21 < $B$15 + 5), -$B$10 / 5, 0 ) -> 0 | E63: =IF( AND(E$21 >= $B$15, E$21 < $B$15 + 5), -$B$10 / 5, 0 ) -> 0 | F63: =IF( AND(F$21 >= $B$15, F$21 < $B$15 + 5), -$B$10 / 5, 0 ) -> 0 | G63: =IF( AND(G$21 >= $B$15, G$21 < $B$15 + 5), -$B$10 / 5, 0 ) -> 0 | H63: =IF( AND(H$21 >= $B$15, H$21 < $B$15 + 5), -$B$10 / 5, 0 ) -> -381.9 | I63: =IF( AND(I$21 >= $B$15, I$21 < $B$15 + 5), -$B$10 / 5, 0 ) -> -381.9 | J63: =IF( AND(J$21 >= $B$15, J$21 < $B$15 + 5), -$B$10 / 5, 0 ) -> -381.9 | ... AK63: =IF( AND(AK$21 >= $B$15, AK$21 < $B$15 + 5), -$B$10 / 5, 0 ) -> 0
A68: IP3
A69: Opening Loan Balance | B69: 650000
A70: Interest Rate (annual) | B70: 0.0544
A71: Loan Start Year | B71: 2019
A72: IO End Age | B72: 2018
A73: Original Loan Term (yrs) | B73: 25
A75: Borrowing Costs | B75: =SUM(B76:B79) -> 1909.5
A76: Conveyance | B76: 1200
A77: Loan Establishment Fee | B77: 600
A78: Registration of Title | B78: 109.5
A79: Stamp Duty (add to cost base for CGT when disposal of property) | B79: Exempt
A80: First year available for rent | B80: =H85 -> 2020
A81: Amort years (ATO) | B81: =MIN(5, H89) -> 5
A83: Schedule (Annual)
H84: 0.0363
A85: Year | C85: =$B$5 + 0 -> 2015 | D85: =$B$5 + 1 -> 2016 | E85: =$B$5 + 2 -> 2017 | F85: =$B$5 + 3 -> 2018 | G85: =$B$5 + 4 -> 2019 | H85: =$B$5 + 5 -> 2020 | I85: =$B$5 + 6 -> 2021 | J85: =$B$5 + 7 -> 2022 | K85: =$B$5 + 8 -> 2023 | L85: =$B$5 + 9 -> 2024 | M85: =$B$5 + 10 -> 2025 | N85: =$B$5 + 11 -> 2026 | O85: =$B$5 + 12 -> 2027 | P85: =$B$5 + 13 -> 2028 | Q85: =$B$5 + 14 -> 2029 | R85: =$B$5 + 15 -> 2030 | S85: =$B$5 + 16 -> 2031 | T85: =$B$5 + 17 -> 2032 | U85: =$B$5 + 18 -> 2033 | V85: =$B$5 + 19 -> 2034 | W85: =$B$5 + 20 -> 2035 | X85: =$B$5 + 21 -> 2036 | Y85: =$B$5 + 22 -> 2037 | Z85: =$B$5 + 23 -> 2038 | AA85: =$B$5 + 24 -> 2039 | AB85: =$B$5 + 25 -> 2040 | AC85: =$B$5 + 26 -> 2041 | AD85: =$B$5 + 27 -> 2042 | AE85: =$B$5 + 28 -> 2043 | AF85: =$B$5 + 29 -> 2044 | AG85: =$B$5 + 30 -> 2045 | AH85: =$B$5 + 31 -> 2046 | AI85: =$B$5 + 32 -> 2047 | AJ85: =$B$5 + 33 -> 2048 | AK85: =$B$5 + 34 -> 2049
A86: IP3 | C86: 1 | D86: 2 | E86: 3 | F86: 4 | G86: 5 | H86: 6 | I86: 7 | J86: 8 | K86: 9 | L86: 10 | M86: 11 | N86: 12 | O86: 13 | P86: 14 | Q86: 15 | R86: 16 | S86: 17 | T86: 18 | U86: 19 | V86: 20 | W86: 21 | X86: 22 | Y86: 23 | Z86: 24 | AA86: 25 | AB86: 26 | AC86: 27 | AD86: 28 | AE86: 29 | AF86: 30 | AG86: 31 | AH86: 32 | AI86: 33 | AJ86: 34 | AK86: 35
A87: Opening Balance | C87: =B69 -> 650000 | D87: =C93 -> 650000 | E87: =D93 -> 650000 | F87: =E93 -> 650000 | G87: =F93 -> 650000 | H87: =G93 -> 650000 | I87: =H93 -> 650000 | J87: =I93 -> 650000 | K87: =J93 -> 650000 | ... AK87: =AJ93 -> 0
A88: Repayment Mode | C88: =IF(C85<$B$6,"IO","P&I") -> IO | D88: =IF(D85<$B$6,"IO","P&I") -> IO | E88: =IF(E85<$B$6,"IO","P&I") -> IO | F88: =IF(F85<$B$6,"IO","P&I") -> IO | G88: =IF(G85<$B$6,"IO","P&I") -> IO | H88: =IF(H85<$B$6,"IO","P&I") -> IO | I88: =IF(I85<$B$6,"IO","P&I") -> IO | J88: =IF(J85<$B$6,"IO","P&I") -> IO | ... AK88: =IF(AK85<$B$6,"IO","P&I") -> P&I
A89: Remaining Term (yrs) | C89: =MAX(0,$B$41-(C85-$B$39)) -> 25 | D89: =MAX(0,$B$41-(D85-$B$39)) -> 24 | E89: =MAX(0,$B$41-(E85-$B$39)) -> 23 | F89: =MAX(0,$B$41-(F85-$B$39)) -> 22 | G89: =MAX(0,$B$41-(G85-$B$39)) -> 21 | H89: =MAX(0,$B$41-(H85-$B$39)) -> 20 | I89: =MAX(0,$B$41-(I85-$B$39)) -> 19 | J89: =MAX(0,$B$41-(J85-$B$39)) -> 18 | ... AK89: =MAX(0,$B$41-(AK85-$B$39)) -> 0
A90: Interest Expense | C90: =C87*$B$70 -> 35360 | D90: =D87*$B$70 -> 35360 | E90: =E87*$B$70 -> 35360 | F90: =F87*$B$70 -> 35360 | G90: =G87*$B$70 -> 35360 | H90: =H87*$B$70 -> 35360 | I90: =I87*$B$70 -> 35360 | J90: =J87*$B$70 -> 35360 | ... AK90: =AK87*$B$70 -> 0
A91: Annual Repayment | C91: =IF(C89=0,0,IF(C88="IO",C90,PMT($B$4,C89,-C87))) -> 35360 | D91: =IF(D89=0,0,IF(D88="IO",D90,PMT($B$4,D89,-D87))) -> 35360 | E91: =IF(E89=0,0,IF(E88="IO",E90,PMT($B$4,E89,-E87))) -> 35360 | F91: =IF(F89=0,0,IF(F88="IO",F90,PMT($B$4,F89,-F87))) -> 35360 | G91: =IF(G89=0,0,IF(G88="IO",G90,PMT($B$4,G89,-G87))) -> 35360 | H91: =IF(H89=0,0,IF(H88="IO",H90,PMT($B$4,H89,-H87))) -> 35360 | I91: =IF(I89=0,0,IF(I88="IO",I90,PMT($B$4,I89,-I87))) -> 35360 | J91: =IF(J89=0,0,IF(J88="IO",J90,PMT($B$4,J89,-J87))) -> 35360 | ... AK91: =IF(AK89=0,0,IF(AK88="IO",AK90,PMT($B$4,AK89,-AK87))) -> 0
A92: Principal Repayment | C92: =MAX(0,C91-C90) -> 0 | D92: =MAX(0,D91-D90) -> 0 | E92: =MAX(0,E91-E90) -> 0 | F92: =MAX(0,F91-F90) -> 0 | G92: =MAX(0,G91-G90) -> 0 | H92: =MAX(0,H91-H90) -> 0 | I92: =MAX(0,I91-I90) -> 0 | J92: =MAX(0,J91-J90) -> 0 | ... AK92: =MAX(0,AK91-AK90) -> 0
A93: Closing Balance | C93: =MAX(0,C87-C92) -> 650000 | D93: =MAX(0,D87-D92) -> 650000 | E93: =MAX(0,E87-E92) -> 650000 | F93: =MAX(0,F87-F92) -> 650000 | G93: =MAX(0,G87-G92) -> 650000 | H93: =MAX(0,H87-H92) -> 650000 | I93: =MAX(0,I87-I92) -> 650000 | J93: =MAX(0,J87-J92) -> 650000 | ... AK93: =MAX(0,AK87-AK92) -> 0
A95: “Borrowing Exp – Theoretical” | C95: =IF( AND(C$21 >= $B$15, C$21 < $B$15 + 5), -$B$10 / 5, 0 ) -> 0 | D95: =IF( AND(D$21 >= $B$15, D$21 < $B$15 + 5), -$B$10 / 5, 0 ) -> 0 | E95: =IF( AND(E$21 >= $B$15, E$21 < $B$15 + 5), -$B$10 / 5, 0 ) -> 0 | F95: =IF( AND(F$21 >= $B$15, F$21 < $B$15 + 5), -$B$10 / 5, 0 ) -> 0 | G95: =IF( AND(G$21 >= $B$15, G$21 < $B$15 + 5), -$B$10 / 5, 0 ) -> 0 | H95: =IF( AND(H$21 >= $B$15, H$21 < $B$15 + 5), -$B$10 / 5, 0 ) -> -381.9 | I95: =IF( AND(I$21 >= $B$15, I$21 < $B$15 + 5), -$B$10 / 5, 0 ) -> -381.9 | J95: =IF( AND(J$21 >= $B$15, J$21 < $B$15 + 5), -$B$10 / 5, 0 ) -> -381.9 | ... AK95: =IF( AND(AK$21 >= $B$15, AK$21 < $B$15 + 5), -$B$10 / 5, 0 ) -> 0
A100: PPOR
A101: Opening Loan Balance | B101: =Properties!D100 -> 0
A102: Interest Rate (annual) | B102: =Properties!E100 -> 0
A103: Loan Start Year | B103: 2019
A104: IO End Age
A105: Original Loan Term (yrs) | B105: 25
A106: Bank_Charge_Assumption_Loan_Change_Fee | B106: 650
A108: Borrowing Costs | B108: =SUM(B109:B115) -> 66708
A109: Conveyance | B109: 695
A110: Loan Establishment Fee | B110: 300
A111: Registration of Title / Lands Titles Office Fee | B111: 9635
A112: Stamp Duty (add to cost base for CGT when disposal of property) | B112: 55705
A113: Lands Titles / Electronic settlement fee | B113: 115
A114: ID Verification | B114: =59*2 -> 118
A115: File administrative costs | B115: 140
A116: First year available for rent | B116: N/A
A117: Amort years (ATO) | B117: N/A
A119: Schedule (Annual)
H120: 0.0273 | I120: 0.0255 | J120: 0.0197 | K120: 0.0197 | L120: 0.0197 | M120: 0.0639 | N120: 0.0544 | O120: 0.06 | P120: 0.06 | Q120: 0.06 | R120: 0.06
A121: Year | C121: =$B$5 + 0 -> 2015 | D121: =$B$5 + 1 -> 2016 | E121: =$B$5 + 2 -> 2017 | F121: =$B$5 + 3 -> 2018 | G121: =$B$5 + 4 -> 2019 | H121: =$B$5 + 5 -> 2020 | I121: =$B$5 + 6 -> 2021 | J121: =$B$5 + 7 -> 2022 | K121: =$B$5 + 8 -> 2023 | L121: =$B$5 + 9 -> 2024 | M121: =$B$5 + 10 -> 2025 | N121: =$B$5 + 11 -> 2026 | O121: =$B$5 + 12 -> 2027 | P121: =$B$5 + 13 -> 2028 | Q121: =$B$5 + 14 -> 2029 | R121: =$B$5 + 15 -> 2030 | S121: =$B$5 + 16 -> 2031 | T121: =$B$5 + 17 -> 2032 | U121: =$B$5 + 18 -> 2033 | V121: =$B$5 + 19 -> 2034 | W121: =$B$5 + 20 -> 2035 | X121: =$B$5 + 21 -> 2036 | Y121: =$B$5 + 22 -> 2037 | Z121: =$B$5 + 23 -> 2038 | AA121: =$B$5 + 24 -> 2039 | AB121: =$B$5 + 25 -> 2040 | AC121: =$B$5 + 26 -> 2041 | AD121: =$B$5 + 27 -> 2042 | AE121: =$B$5 + 28 -> 2043 | AF121: =$B$5 + 29 -> 2044 | AG121: =$B$5 + 30 -> 2045 | AH121: =$B$5 + 31 -> 2046 | AI121: =$B$5 + 32 -> 2047 | AJ121: =$B$5 + 33 -> 2048 | AK121: =$B$5 + 34 -> 2049
A122: PPOR | C122: 1 | D122: 2 | E122: 3 | F122: 4 | G122: 5 | H122: 6 | I122: 7 | J122: 8 | K122: 9 | L122: 10 | M122: 11 | N122: 12 | O122: 13 | P122: 14 | Q122: 15 | R122: 16 | S122: 17 | T122: 18 | U122: 19 | V122: 20 | W122: 21 | X122: 22 | Y122: 23 | Z122: 24 | AA122: 25 | AB122: 26 | AC122: 27 | AD122: 28 | AE122: 29 | AF122: 30 | AG122: 31 | AH122: 32 | AI122: 33 | AJ122: 34 | AK122: 35
A123: Opening Balance | C123: =B101 -> 0 | D123: =C129 -> 0 | E123: =D129 -> 0 | F123: =E129 -> 0 | G123: =F129 -> 0 | H123: =G129 -> 892852.37 | I123: =H129 -> 872968.04 | J123: =I129 -> 835062.74 | K123: =J129 -> 807792.75 | ... AK123: =AJ129 -> 0
...

Sheet Property Expenses (Detail)
A1: Investment Property Expenses – Detailed (Annual)
A3: Enter annual landlord costs per property. Feeds rental cashflow and negative gearing.
A5: Property | B5: Landlord Insurance | C5: Property Management % | D5: Property Management | E5: Repairs & Maintenance | F5: Strata – Admin | G5: Strata – Capital Works | H5: Council Rates | I5: Water Charges | J5: Other | K5: TOTAL
B6: NRMA | D6: Lane Marriott | E6: C/O Lane Marriott | F6: StrataChoice | G6: StrataChoice | H6: North Sydney | I6: Sydney Water | L6: Vendors
A7: IP1 - Albany St Crows Nest | B7: 700 | C7: =D7/Property_CF!C54 -> 0.065993902 | D7: =108.23*26 -> 2813.98 | E7: 500 | F7: 922.72 | G7: 1000 | H7: 1320 | I7: 750 | J7: 0 | K7: =SUM(B7:J7) -> 8006.766
L8: Vendors
A9: IP2 | B9: 700 | D9: =6%*Properties!H8 -> 1716 | E9: 1500 | H9: 1900 | I9: 830 | J9: 0 | K9: =SUM(B9:J9) -> 6646
L10: Vendors
A11: IP3 | B11: 700 | D11: =6%*Properties!H9 -> 1794 | E11: 1500 | H11: 2200 | I11: 890 | J11: 0 | K11: =SUM(B11:J11) -> 7084

Sheet Rental Tax & Gearing
A1: Rental Tax & Negative Gearing (AU)
A3: AU taxable rental income, negative gearing benefit, after-tax cashflow.
A5: Property | B5: Gross Rent | C5: Total Expenses | D5: Interest | E5: Taxable Rental Income | F5: Marginal Tax Rate | G5: Tax Benefit / (Payable) | H5: After-Tax Cashflow
A6: =Properties!A7 -> IP1 - Albany St Crows Nest | B6: =Properties!H7 -> 42640 | C6: ='Property Expenses (Detail)'!K7 -> 8006.766 | D6: ='Loan Amortisation retired'!F6 -> 27444.211 | E6: =B6-C6-D6 -> 7189.0225 | F6: 0.45 | G6: =-E6*F6 -> -3235.0601 | H6: =E6+G6 -> 3953.9624
A7: =Properties!A9 -> IP3 | B7: =Properties!H8 -> 28600 | C7: ='Property Expenses (Detail)'!K9 -> 6646 | D7: ='Loan Amortisation retired'!F7 -> 34740 | E7: =B7-C7-D7 -> -12786 | F7: 0.45 | G7: =-E7*F7 -> 5753.7 | H7: =E7+G7 -> -7032.3
A8: =Properties!A11 -> Capital Works Fund Plan | B8: =Properties!H9 -> 29900 | C8: ='Property Expenses (Detail)'!K11 -> 7084 | D8: ='Loan Amortisation retired'!F8 -> 37635 | E8: =B8-C8-D8 -> -14819 | F8: 0.45 | G8: =-E8*F8 -> 6668.55 | H8: =E8+G8 -> -8150.45

Sheet Assumptions
A1: Assumptions (Active Scenario View)
A3: Single-source assumptions used by projections.
A5: Assumption | B5: Value | C5: Notes
A6: Inflation | B6: =Scenarios!K10 -> 0.025 | C6: Scenario-linked
A7: Return Mean | B7: =Scenarios!K8 -> 0.065 | C7: Scenario-linked
A8: Volatility | B8: =Scenarios!K9 -> 0.11 | C8: Scenario-linked
A9: Property Growth | B9: =Scenarios!K11 -> 0.045 | C9: Scenario-linked
A10: Rent Yield | B10: =Scenarios!K12 -> 0.050164706 | C10: Scenario-linked
A11: Rental Expense Ratio | B11: 0.25 | C11: Editable
A12: Monte Carlo sims | B12: 2000 | C12: Generated values
A20: Property_CF Assumptions
A22: 8. Insurance - Landlord
A23: Landlords insurance on an apartment in Crows Nest, NSW, a reasonable assumption for annual percentage increase would be 5-7%.
A24: Weekly Rental Premium Annual Increase % ~ For your financial workbook, I'd suggest:
A26: Conservative estimate: 7% (accounts for continued market volatility)
A27: Moderate estimate: 5-6% (assumes market stabilization)
A28: Optimistic estimate: 4-5% (if market conditions improve significantly)
A30: I'd recommend using 6% as a reasonable middle-ground assumption for medium-term planning (3-5 years), but you might want to stress-test your model with a higher rate like 8% to ensure your investment remains viable even if premiums rise more than expected.
A31: Keep in mind that actual increases can vary significantly year-to-year based on insurer performance, claims history, and broader market conditions.
A33: 16. Bank Charges
A34: (Likely IO rollover / admin / package fees)
A35: Assumption (planner-grade): Bank charges are lumpy, not inflationary |Typically occur: At IO expiry, Possibly at refinance / extension
... A43: (Tenant disputes, tribunal, etc.)
A44: Formula | B44: =0
A46: 18. Advertising for Tenants
A47: (This one matters — let’s do it properly)
A48: Year-to-year leases ≠ new tenant every year
A49: Typical metro assumption: | B49: New tenant every 3–5 years
A50: Advertising + letting costs occur only on tenant change (Letting Costs - One weeks rent plus GST)
A51: Adviser-grade deterministic assumption Tenant_Turnover_Years = 4 (good default) Letting_Cost = 1 week rent + GST Letting_Advertising = $560
A52: Gross_Weekly_Rent | B52: =Property_CF!C54/52 -> 820
A53: Marriott Lane
A54: Letting_Cost | B54: =B52*1.1 -> 902
A55: Letting Advertising | B55: 560
A57: Tenant_Turnover_Years = 4 (good default) | B57: 4
A58: Letting_Cost = e.g. 1 week rent + $500 advertising
A60: 24. Depreciation – Plant & Equipment
A61: ATO reality (post-2017)
A62: Second-hand assets purchased after 9 May 2017 → NOT deductible
A63: New assets (e.g. blinds, appliances added later) → deductible
A64: Formula - Unless you explicitly know you have deductible P&E: | B64: =0
A65: You can later replace with: | B65: = Depreciation_Schedule!Current_Year
A67: 25. Capital Works Deduction (2.5%)
A69: Capital_Works_Base = eligible construction amount | B69: 221551
A70: Capital_Works_Rate = 2.5% | B70: 0.025
A72: 26. Borrowing Expenses (Amortised)
A73: ATO rule
A74: Amortise over 5 years or loan term, whichever is shorter
A75: Inputs
A76: Total_Borrowing_Costs
A77: Loan_Term_Years
A78: Borrowing Amort Years | B78: =MIN(5, B75)
A80: 28. Total Deductible Expenses
A82: Formula
A83: Sum only deductible items:
A85: = SUM( Council_Rates_Cell, Water_Charges_Cell, BC_Admin_Cell, BC_Capital_Works_Cell, Landlord_Insurance_Cell, RE_Management_Fees_Cell, Cleaning_Cell, Gardening_Cell, Lawn_Cell, Pest_Cell, Interest_Expense_Cell, Bank_Charges_Cell, Legal_Expenses_Cell, Advertising_Cell, Repairs_Cell, Depreciation_Cell, Capital_Works_Deduction_Cell, Borrowing_Expenses_Cell, Other_Deductible_Cell)
A86: ✔ Excludes non-deductible travel
A87: ✔ Matches tax logic
A89: Formula
A91: = Gross_Rent_Cell - Total_Deductible_Expenses_Cell
A93: This is the only number that flows into Taxable Income.
A95: 30. Net Rental Cashflow (cash only) ← CASH NUMBER
A97: Formula
A99: = Net_Rental_Income_Cell + Depreciation_Cell + Capital_Works_Deduction_Cell + Borrowing_Expenses_Cell
... A103: They reduce tax but not cash

Sheet Rental Cashflow
A1: Rental Cashflow (Snapshot, p.a.)
A3: Net cashflow = Rent - expenses - interest. Snapshot for IPs.
A5: Property | B5: Gross Rent | C5: Expenses | D5: Interest | E5: Net Cashflow
A6: =Properties!A7 -> IP1 - Albany St Crows Nest | B6: =Properties!H7 -> 42640 | C6: =B6*Assumptions!B10 -> 2139.0231 | D6: =Properties!D7*Properties!E7 -> 27444.211 | E6: =B6-C6-D6 -> 13056.765
A7: =Properties!A8 -> IP2 | B7: =Properties!H8 -> 28600 | C7: =B7*Assumptions!B10 -> 1434.7106 | D7: =Properties!D8*Properties!E8 -> 34740 | E7: =B7-C7-D7 -> -7574.7106
A8: =Properties!A9 -> IP3 | B8: =Properties!H9 -> 29900 | C8: =B8*Assumptions!B10 -> 1499.9247 | D8: =Properties!D9*Properties!E9 -> 37635 | E8: =B8-C8-D8 -> -9234.9247

Sheet Monte Carlo
A1: Monte Carlo Probability Fan (Generated Demo)
A3: Year-by-year P10/P50/P90 balance for retirement years (generated with demo parameters).
A5: Year | B5: Age | C5: P10 | D5: P50 | E5: P90
A6: 0 | B6: 60 | C6: 2489138.1 | D6: 2881594.1 | E6: 3284616.5 | G6: Success Probability | H6: 0.8365
A7: 1 | B7: 61 | C7: 2373853.3 | D7: 2936991 | E7: 3544206.9 | G7: Start Assets (demo) | H7: 2800000
A8: 2 | B8: 62 | C8: 2296357.3 | D8: 2980052.4 | E8: 3804318.1 | G8: Start Spending (demo) | H8: 110000
A9: 3 | B9: 63 | C9: 2239042.4 | D9: 3044067.8 | E9: 4045922.3
A10: 4 | B10: 64 | C10: 2154484.4 | D10: 3110203.3 | E10: 4335957.8
A11: 5 | B11: 65 | C11: 2113805.3 | D11: 3119165 | E11: 4571001.9
A12: 6 | B12: 66 | C12: 2029923.3 | D12: 3201390.9 | E12: 4818483.2
A13: 7 | B13: 67 | C13: 2049040.9 | D13: 3264545.8 | E13: 5110588.9
A14: 8 | B14: 68 | C14: 1955491.5 | D14: 3321908 | E14: 5419163.3
A15: 9 | B15: 69 | C15: 1926011.9 | D15: 3372292.8 | E15: 5641683.6
A16: 10 | B16: 70 | C16: 1865588.6 | D16: 3473646.5 | E16: 5947621.9
A17: 11 | B17: 71 | C17: 1799743.5 | D17: 3539986.2 | E17: 6246989.5
A18: 12 | B18: 72 | C18: 1694340.1 | D18: 3631186 | E18: 6560007.4
A19: 13 | B19: 73 | C19: 1626584.5 | D19: 3670921.3 | E19: 6880757.7
A20: 14 | B20: 74 | C20: 1579186.4 | D20: 3723067.3 | E20: 7325330.9
... A36: 30 | B36: 90 | C36: -1053470.5 | D36: 4285630.8 | E36: 16123666

Sheet Dashboard
A1: EXECUTIVE DASHBOARD (Report View)
A3: KPI tiles + charts. Green & Gold theme across the workbook.
A5: Active Scenario | D5: =Scenarios!J5 -> Base | G5: Target Retire Age | J5: =Scenarios!K7 -> 60
A8: Total Net Worth (Today) | D8: =INDEX(Projections!X:X, MATCH(Profile!B6, Projections!C:C, 0)) -> 3124388 | G8: Property Equity | J8: =Properties!M8 -> 1683071.9
A11: Net Rental Cashflow | D11: =SUM('Rental Cashflow'!E6:E8) -> -3752.8698 | G11: MC Success Probability | J11: ='Monte Carlo'!$H$6 -> 0.8365

Sheet Loan Amortisation retired
A1: Investment Loan Modelling (IO → P&I)
A2: Models IO until IO End Age, then P&I thereafter.
A5: Property | B5: Loan Balance | C5: Rate | D5: IO End Age | E5: Remaining Term (yrs) | F5: Annual Interest | G5: Annual Principal | H5: Annual P&I
A6: ='Property Expenses (Detail)'!A7 -> IP1 - Albany St Crows Nest | B6: =Properties!D7 -> 473993.29 | C6: =Properties!E7 -> 0.0579 | D6: =Properties!F7 -> 52 | E6: 25 | F6: =B6*C6 -> 27444.211 | G6: =IF(Profile!B6>=D6,PMT(C6,E6,-B6),0) -> 0 | H6: =F6+G6 -> 27444.211
A7: ='Property Expenses (Detail)'!A8 -> 0 | B7: =Properties!D8 -> 600000 | C7: =Properties!E8 -> 0.0579 | D7: =Properties!F8 -> 57 | E7: 25 | F7: =B7*C7 -> 34740 | G7: =IF(Profile!B7>=D7,PMT(C7,E7,-B7),0) -> 0 | H7: =F7+G7 -> 34740
A8: ='Property Expenses (Detail)'!A9 -> IP2 | B8: =Properties!D9 -> 650000 | C8: =Properties!E9 -> 0.0579 | D8: =Properties!F9 -> 59 | E8: 25 | F8: =B8*C8 -> 37635 | G8: =IF(Profile!B8>=D8,PMT(C8,E8,-B8),0) -> 49837.202 | H8: =F8+G8 -> 87472.202
